Workbook

Sheet Overview
A1: Summary
A2: Topic | B2: Details
A3: Project | B3: LSC End of Coal Program - Apparel Sustainable Supply Chain
A4: Case | B4: TEXIN Factory Vietnam
A5: Key Outcome | B5: ~64% CO2 reduction after replacing 78% coal with biomass
A6: Strategic Impact | B6: Supplier decarbonization and ESG compliance
A7: Case 2A Challenge | B7: 5-year ESG CAPEX/OPEX phasing + P&L constraints, supported by 2026 actual volume and 2027-2029 potential-order scenarios
A9: LSC Strategy
A10: Area | B10: Requirement
A11: Carbon | B11: Measure and reduce emissions
A12: Energy | B12: Renewable energy and coal elimination
A13: Suppliers | B13: Decarbonization roadmap
A15: TEXIN SOP
A16: Fuel Receiving | B16: Rice husk pellets/wood pellets
A17: QC | B17: Moisture and particle-size inspection
A18: Storage | B18: Covered warehouse and fire prevention
A19: Fuel Feeding | B19: Automatic feeding system
A20: Combustion | B20: Air/fuel ratio control
A21: Steam Generation | B21: Boiler operation
A22: Production | B22: Steam consumption in manufacturing
A23: Ash Handling | B23: Reuse or disposal

Sheet Fuel comparison
A1: Metric | B1: Coal | C1: Rice Husk Pellet | D1: Wood Pellet
A2: NCV kcal/kg | B2: 6300-7000 | C2: 3800-4500 | D2: 4200-4800
A3: CO2 tCO2/t fuel | B3: 2.4-2.7 | C3: 0.15-0.30 | D3: 0.10-0.25
A4: Ash % | B4: 10-25 | C4: 8-15 | D4: 1-5
A5: Cost VNĐ/Tons | B5: 2.5-3.0M | C5: 1.8-3.0M | D5: 3.5-5.0M

Sheet CO2 Emission Calculation
A1: CO2 Emission Calculation - Fuel Comparison
A3: Fuel | B3: NCV (GJ/t) | C3: EF (kgCO2/GJ) | D3: Formula | E3: CO2 (kg/t fuel) | F3: CO2 (t/t fuel)
A4: Coal | B4: 25 | C4: 94.6 | D4: NCV × EF | E4: =B4*C4 -> 2365 | F4: =E4/1000 -> 2.365
A5: Rice Husk Pellet | B5: 16 | C5: 10 | D5: NCV × EF | E5: =B5*C5 -> 160 | F5: =E5/1000 -> 0.16
A6: Wood Pellet | B6: 18 | C6: 7 | D6: NCV × EF | E6: =B6*C6 -> 126 | F6: =E6/1000 -> 0.126
A8: Fuel comparison
A9: Metric | B9: Coal | C9: Rice husk pellet | D9: Wood pellet
A10: NCV kcal/kg | B10: 6,300 - 7,000 | C10: 3,800 - 4,500 | D10: 4,200 - 4,800
A11: CO2 tCO2/t fuel | B11: 2.4-2.7 | C11: 0.15-0.30 | D11: 0.10-0.25
A12: Ash % | B12: 10-25 | C12: 8-15 | D12: 1-5
A13: Cost VND/Tons | B13: 2.5-3.0M | C13: 1.8-3.0M | D13: 3.5-5.0M
A15: Carbon reduction
A16: Scenario | B16: Emission Index
A17: 100% Coal | B17: 100
A18: 78% Biomass + 22% Coal | B18: 36
A19: Reduction % | B19: 64
A21: Index | B21: Meaning
A22: NCV (Net Calorific Value) | B22: Useful heat energy generated by 1 ton of fuel. Higher NCV means less fuel is needed to produce the same heat.
A23: EF (Emission Factor) | B23: Amount of CO2 emitted per GJ of energy generated. For biomass, the EF shown here is life-cycle CO2e, mainly from collection, pelletizing, and transport.
A24: CO2 kg/t fuel | B24: CO2 emitted when burning or using 1 ton of fuel, calculated as NCV × EF.
A25: CO2 t/t fuel | B25: CO2 kg/t fuel divided by 1,000.
A27: Simple example | B27: Coal | C27: Rice husk pellet | D27: Wood pellet | E27: Note
A28: Fuel amount used (t/year) | B28: 1000 | C28: 1560 | D28: 1390 | E28: Biomass amount adjusted to generate similar heat as 1,000 t coal
A29: Total energy (GJ/year) | B29: =B28*B4 -> 25000 | C29: =C28*B5 -> 24960 | D29: =D28*B6 -> 25020 | E29: Fuel amount × NCV
A30: Total CO2 (tCO2e/year) | B30: =B28*F4 -> 2365 | C30: =C28*F5 -> 249.6 | D30: =D28*F6 -> 175.14 | E30: Fuel amount × CO2 t/t fuel
A31: CO2 reduction vs coal | B31: - | C31: =(B30-C30)/B30 -> 0.89446089 | D31: =(B30-D30)/B30 -> 0.92594503 | E31: Compared with coal baseline
A33: Key takeaway | B33: Coal has higher heat value, but also much higher emission factor.
A34: 1 | B34: Rice husk pellet and wood pellet require more tons of fuel for the same heat output.
A35: 2 | B35: However, their life-cycle CO2e is much lower, which is why coal-to-biomass conversion can significantly reduce Scope 1-related emissions.
A36: 3 | B36: In the TEXIN/LSC case, partial replacement of coal with biomass led to an estimated ~64% CO2 reduction.

Sheet Carbon-Allowed Capacity
B1: CARBON-ALLOWED CAPACITY 2027–2031 · supporting calculation for Task 2
B2: Reverse calculation from the buyer caps: CO2e = heat intensity × volume × emission factor ≤ cap, so maximum volume = cap × 1,000 ÷ (heat intensity × EF). Both caps are tested: absolute tCO2e and kgCO2e/GJ intensity.
B4: DESIGN BIOMASS MIX | C4: CAPACITY 2027 | E4: CAPACITY 2029 | G4: CAPACITY 2031 | J4: MIN. BIOMASS SHARE 2031 | L4: COAL-ONLY VOLUME 2031 | N4: PEAK HEAT AT CAPACITY
B5: =C21 -> 0.78 | C5: =D36 -> 9100807.2 | E5: =F36 -> 9358316 | G5: =H36 -> 6125443.2 | J5: =H28 -> 0.70811696 | L5: =H53 -> 1807200 | N5: =MAX(D38:H38) -> 2.3726263
B6: Emission Target F11 (~78% biomass) | C6: =TEXT(D27,"0%")&" of 2027 on biomass" -> 75% of 2027 on biomass | E6: ="vs potential orders "&TEXT(F48/1000000,"0.00")&"M" -> vs potential orders 9.80M | G6: Caps tighten faster than EF falls | J6: Below this, any volume fails | L6: Absolute cap on 100% coal | N6: × 2026 heat; no boiler rating in the case
B8: Inputs and method
B9: Parameter | C9: Value | D9: Unit | E9: Basis / source | J9: Reading the result
B10: 2026 useful heat demand | C10: ='ESG_CAPEX OPEX'!B6 -> 300000 | D10: GJ/yr | E10: ESG_CAPEX OPEX B6 (sized for dyeing/finishing steam demand). | J10: 1. The reverse calculation is valid only because heat is assumed to scale with volume. If heat were fixed at 300,000 GJ, CO2e would not depend on volume and no capacity could be derived from the caps.
B11: 2026 actual sales volume | C11: ='Sales Forecast & Case 2A KPI'!C21 -> 5020000 | D11: pcs | E11: Sales Forecast C21; produces the 28,380 t baseline (Emission Target J6).
B12: Heat intensity (held at 2026 level) | C12: =$C$10/$C$11 -> 0.059760956 | D12: GJ/pc | E12: Team assumption: heat moves in proportion to output (steam per kg of fabric dyed and finished). | J12: 2. Team decision: this envelope is adopted in Task 2 as the planning capacity. Sewing labour is variable and costed per piece through COGS, and the case gives no boiler rating, so the carbon budget is the only hard volume limit the case quantifies.
B13: Emission factor: coal | C13: ='CO2 Emission Calculation'!C4 -> 94.6 | D13: kgCO2e/GJ | E13: CO2 Emission Calculation C4.
B14: Emission factor: rice husk pellet | C14: ='CO2 Emission Calculation'!C5 -> 10 | D14: kgCO2e/GJ | E14: CO2 Emission Calculation C5 (life-cycle). | J14: 3. Against risk-adjusted demand (Task 2) the envelope does not bind in 2027–2029 and binds in 2030–2031. Against the full potential orders it would already bind in 2029.
B15: Emission factor: wood pellet | C15: ='CO2 Emission Calculation'!C6 -> 7 | D15: kgCO2e/GJ | E15: CO2 Emission Calculation C6 (life-cycle).
B16: Rice husk share of biomass heat | C16: ='ESG_CAPEX OPEX'!B10 -> 0.7 | D16: % of heat | E16: ESG_CAPEX OPEX B10 (base-case blend). | J16: 4. Capacity shrinks from 2028 to 2031 at a constant mix because the caps tighten faster than EF falls. Growth after 2029 needs a higher biomass share or heat-recovery savings (Emission Target F10).
B17: Wood pellet share of biomass heat | C17: ='ESG_CAPEX OPEX'!B11 -> 0.3 | D17: % of heat | E17: ESG_CAPEX OPEX B11.
B18: Emission factor: biomass blend | C18: =$C$16*$C$14+$C$17*$C$15 -> 9.1 | D18: kgCO2e/GJ | E18: Heat-weighted blend of the two pellets. | J18: 5. At the envelope CO2e equals the cap exactly. Task 1 therefore runs the boiler at the next 5% biomass step above the requirement, keeping CO2e at least 5% below the cap (R01, R02).
B19: Biomass firing starts (2027) | C19: ='Task 1_ESG Roadmap'!$C$117 -> 46478 | D19: date | E19: Linked to the Task 1 commissioning milestone (in service 1 Apr 2027).
B20: Share of 2027 with the biomass system in service | C20: =(DATE(2027,12,31)-$C$19+1)/365 -> 0.75342466 | D20: % of year | E20: Days in service ÷ 365. | J20: 6. Case consistency: with the case emission factors, 78% biomass gives a 70.5% reduction, not the ~64% quoted in Overview B5; a 64% cut on fixed heat needs about 70.8% biomass. This model uses the CO2 Emission Calculation factors throughout.
B21: Case target operating mix: biomass share | C21: 0.78 | D21: % of heat | E21: Emission Target F11 ('~78% biomass/22% coal equivalent performance'); Overview B5.
B23: Buyer caps and the minimum biomass share they imply
B24: Metric | C24: 2026 | D24: 2027 | E24: 2028 | F24: 2029 | G24: 2030 | H24: 2031
B25: Buyer cap: maximum annual CO2e (t) | C25: ='Emission Target'!D6 -> 28380 | D25: ='Emission Target'!D7 -> 24123 | E25: ='Emission Target'!D8 -> 19866 | F25: ='Emission Target'!D9 -> 15609 | G25: ='Emission Target'!D10 -> 12771 | H25: ='Emission Target'!D11 -> 10216.8
B26: Buyer cap: maximum CO2e intensity (kg/GJ) | C26: ='Emission Target'!E6 -> 94.6 | D26: ='Emission Target'!E7 -> 80.41 | E26: ='Emission Target'!E8 -> 66.22 | F26: ='Emission Target'!E9 -> 52.03 | G26: ='Emission Target'!E10 -> 42.57 | H26: ='Emission Target'!E11 -> 34.056
B27: Share of year biomass system in service | C27: 0 | D27: =$C$20 -> 0.75342466 | E27: 1 | F27: 1 | G27: 1 | H27: 1
B28: Minimum biomass share while in service (intensity cap) | C28: n/a | D28: =MAX(0,($C$13-D26)/($C$13-$C$18)/D27) -> 0.2202807 | E28: =MAX(0,($C$13-E26)/($C$13-$C$18)/E27) -> 0.33192982 | F28: =MAX(0,($C$13-F26)/($C$13-$C$18)/F27) -> 0.49789474 | G28: =MAX(0,($C$13-G26)/($C$13-$C$18)/G27) -> 0.60853801 | H28: =MAX(0,($C$13-H26)/($C$13-$C$18)/H27) -> 0.70811696
B30: Carbon-allowed capacity at the case design mix
B31: Metric | C31: 2026 | D31: 2027 | E31: 2028 | F31: 2029 | G31: 2030 | H31: 2031
B32: Operating biomass share while in service | C32: 0 | D32: =$C$21 -> 0.78 | E32: =$C$21 -> 0.78 | F32: =$C$21 -> 0.78 | G32: =$C$21 -> 0.78 | H32: =$C$21 -> 0.78
B33: Annual average biomass share of heat | C33: =C32*C27 -> 0 | D33: =D32*D27 -> 0.58767123 | E33: =E32*E27 -> 0.78 | F33: =F32*F27 -> 0.78 | G33: =G32*G27 -> 0.78 | H33: =H32*H27 -> 0.78
B34: Annual average emission factor (kg/GJ) | C34: =$C$13-C33*($C$13-$C$18) -> 94.6 | D34: =$C$13-D33*($C$13-$C$18) -> 44.35411 | E34: =$C$13-E33*($C$13-$C$18) -> 27.91 | F34: =$C$13-F33*($C$13-$C$18) -> 27.91 | G34: =$C$13-G33*($C$13-$C$18) -> 27.91 | H34: =$C$13-H33*($C$13-$C$18) -> 27.91
B35: Intensity cap met? | C35: =IF(C34<=C26+0.000001,"Yes","No") -> Yes | D35: =IF(D34<=D26+0.000001,"Yes","No") -> Yes | E35: =IF(E34<=E26+0.000001,"Yes","No") -> Yes | F35: =IF(F34<=F26+0.000001,"Yes","No") -> Yes | G35: =IF(G34<=G26+0.000001,"Yes","No") -> Yes | H35: =IF(H34<=H26+0.000001,"Yes","No") -> Yes
B36: Carbon-allowed capacity (pcs) | C36: =IF(C35="Yes",C25*1000/($C$12*C34),0) -> 5020000 | D36: =IF(D35="Yes",D25*1000/($C$12*D34),0) -> 9100807.2 | E36: =IF(E35="Yes",E25*1000/($C$12*E34),0) -> 11910584 | F36: =IF(F35="Yes",F25*1000/($C$12*F34),0) -> 9358316 | G36: =IF(G35="Yes",G25*1000/($C$12*G34),0) -> 7656804 | H36: =IF(H35="Yes",H25*1000/($C$12*H34),0) -> 6125443.2
B37: Heat required at this volume (GJ) | C37: =C36*$C$12 -> 300000 | D37: =D36*$C$12 -> 543872.94 | E37: =E36*$C$12 -> 711787.89 | F37: =F36*$C$12 -> 559261.91 | G37: =G36*$C$12 -> 457577.93 | H37: =H36*$C$12 -> 366062.34
B38: Heat required vs 2026 heat demand (×) | C38: =C37/$C$10 -> 1 | D38: =D37/$C$10 -> 1.8129098 | E38: =E37/$C$10 -> 2.3726263 | F38: =F37/$C$10 -> 1.8642064 | G38: =G37/$C$10 -> 1.5252598 | H38: =H37/$C$10 -> 1.2202078
B39: CO2e at this volume (t), check | C39: =C37*C34/1000 -> 28380 | D39: =D37*D34/1000 -> 24123 | E39: =E37*E34/1000 -> 19866 | F39: =F37*F34/1000 -> 15609 | G39: =G37*G34/1000 -> 12771 | H39: =H37*H34/1000 -> 10216.8
B40: Check: CO2e within the absolute and intensity caps | C40: =IF(AND(C39<=C25+0.5,C35="Yes"),"OK","Check") -> OK | D40: =IF(AND(D39<=D25+0.5,D35="Yes"),"OK","Check") -> OK | E40: =IF(AND(E39<=E25+0.5,E35="Yes"),"OK","Check") -> OK | F40: =IF(AND(F39<=F25+0.5,F35="Yes"),"OK","Check") -> OK | G40: =IF(AND(G39<=G25+0.5,G35="Yes"),"OK","Check") -> OK | H40: =IF(AND(H39<=H25+0.5,H35="Yes"),"OK","Check") -> OK
B46: Comparison with the case volumes
B47: Metric | C47: 2026 | D47: 2027 | E47: 2028 | F47: 2029 | G47: 2030 | H47: 2031
B48: ESG scenario: potential orders (pcs) | C48: ='Sales Forecast & Case 2A KPI'!C21 -> 5020000 | D48: ='Sales Forecast & Case 2A KPI'!D21 -> 6124400 | E48: ='Sales Forecast & Case 2A KPI'!E21 -> 7655500 | F48: ='Sales Forecast & Case 2A KPI'!F21 -> 9799040 | G48: n/a | H48: n/a
B49: Carbon-allowed capacity − potential orders (pcs) | C49: =C36-C48 -> 0 | D49: =D36-D48 -> 2976407.2 | E49: =E36-E48 -> 4255084 | F49: =F36-F48 -> -440723.98 | G49: n/a | H49: n/a
B50: Does the CO2 cap bind? | C50: =IF(C49<-0.5,"Yes","No") -> No | D50: =IF(D49<-0.5,"Yes","No") -> No | E50: =IF(E49<-0.5,"Yes","No") -> No | F50: =IF(F49<-0.5,"Yes","No") -> Yes | G50: ="If > "&TEXT(G36/1000000,"0.00")&"M" -> If > 7.66M | H50: ="If > "&TEXT(H36/1000000,"0.00")&"M" -> If > 6.13M
B51: Min. operating biomass share to serve potential orders | C51: n/a | D51: =MAX(D28,($C$13-D25*1000/($C$12*D48))/($C$13-$C$18)/D27) -> 0.44537628 | E51: =MAX(E28,($C$13-E25*1000/($C$12*E48))/($C$13-$C$18)/E27) -> 0.59856198 | F51: =MAX(F28,($C$13-F25*1000/($C$12*F48))/($C$13-$C$18)/F27) -> 0.79468172 | G51: n/a | H51: n/a
B52: Traditional scenario volume (pcs) | C52: ='Sales Forecast & Case 2A KPI'!C21 -> 5020000 | D52: ='Sales Forecast & Case 2A KPI'!G21 -> 4518000 | E52: ='Sales Forecast & Case 2A KPI'!H21 -> 3975840 | F52: ='Sales Forecast & Case 2A KPI'!I21 -> 3379464 | G52: n/a | H52: n/a
B53: Volume allowed by the absolute cap on 100% coal (pcs) | C53: =C25*1000/($C$12*$C$13) -> 5020000 | D53: =D25*1000/($C$12*$C$13) -> 4267000 | E53: =E25*1000/($C$12*$C$13) -> 3514000 | F53: =F25*1000/($C$12*$C$13) -> 2761000 | G53: =G25*1000/($C$12*$C$13) -> 2259000 | H53: =H25*1000/($C$12*$C$13) -> 1807200
B55: Sensitivity: carbon-allowed capacity (million pcs) by operating biomass share
B56: Operating biomass share while in service | C56: 2026 | D56: 2027 | E56: 2028 | F56: 2029 | G56: 2030 | H56: 2031
B57: 0 | C57: =IF(($C$13-$B57*C$27*($C$13-$C$18))<=C$26+0.000001,C$25*1000/($C$12*($C$13-$B57*C$27*($C$13-$C$18)))/1000000,"Fails cap") -> 5.02 | D57: =IF(($C$13-$B57*D$27*($C$13-$C$18))<=D$26+0.000001,D$25*1000/($C$12*($C$13-$B57*D$27*($C$13-$C$18)))/1000000,"Fails cap") -> Fails cap | E57: =IF(($C$13-$B57*E$27*($C$13-$C$18))<=E$26+0.000001,E$25*1000/($C$12*($C$13-$B57*E$27*($C$13-$C$18)))/1000000,"Fails cap") -> Fails cap | F57: =IF(($C$13-$B57*F$27*($C$13-$C$18))<=F$26+0.000001,F$25*1000/($C$12*($C$13-$B57*F$27*($C$13-$C$18)))/1000000,"Fails cap") -> Fails cap | G57: =IF(($C$13-$B57*G$27*($C$13-$C$18))<=G$26+0.000001,G$25*1000/($C$12*($C$13-$B57*G$27*($C$13-$C$18)))/1000000,"Fails cap") -> Fails cap | H57: =IF(($C$13-$B57*H$27*($C$13-$C$18))<=H$26+0.000001,H$25*1000/($C$12*($C$13-$B57*H$27*($C$13-$C$18)))/1000000,"Fails cap") -> Fails cap | J57: How to read the matrix
B58: 0.3 | C58: =IF(($C$13-$B58*C$27*($C$13-$C$18))<=C$26+0.000001,C$25*1000/($C$12*($C$13-$B58*C$27*($C$13-$C$18)))/1000000,"Fails cap") -> 5.02 | D58: =IF(($C$13-$B58*D$27*($C$13-$C$18))<=D$26+0.000001,D$25*1000/($C$12*($C$13-$B58*D$27*($C$13-$C$18)))/1000000,"Fails cap") -> 5.3624714 | E58: =IF(($C$13-$B58*E$27*($C$13-$C$18))<=E$26+0.000001,E$25*1000/($C$12*($C$13-$B58*E$27*($C$13-$C$18)))/1000000,"Fails cap") -> Fails cap | F58: =IF(($C$13-$B58*F$27*($C$13-$C$18))<=F$26+0.000001,F$25*1000/($C$12*($C$13-$B58*F$27*($C$13-$C$18)))/1000000,"Fails cap") -> Fails cap | G58: =IF(($C$13-$B58*G$27*($C$13-$C$18))<=G$26+0.000001,G$25*1000/($C$12*($C$13-$B58*G$27*($C$13-$C$18)))/1000000,"Fails cap") -> Fails cap | H58: =IF(($C$13-$B58*H$27*($C$13-$C$18))<=H$26+0.000001,H$25*1000/($C$12*($C$13-$B58*H$27*($C$13-$C$18)))/1000000,"Fails cap") -> Fails cap | J58: 'Fails cap' = the intensity cap is breached at any volume. When the share just meets the intensity minimum, capacity equals the 2026 volume (5.02M), because each absolute cap = intensity cap × 300,000 GJ. The intensity cap decides whether TEXIN may keep producing; the absolute cap decides how much it may grow. At 90–100% the numbers far exceed any plausible plant output: CO2 then stops being the binding constraint and labour, machines and boiler rating take over.
B59: 0.5 | C59: =IF(($C$13-$B59*C$27*($C$13-$C$18))<=C$26+0.000001,C$25*1000/($C$12*($C$13-$B59*C$27*($C$13-$C$18)))/1000000,"Fails cap") -> 5.02 | D59: =IF(($C$13-$B59*D$27*($C$13-$C$18))<=D$26+0.000001,D$25*1000/($C$12*($C$13-$B59*D$27*($C$13-$C$18)))/1000000,"Fails cap") -> 6.4698046 | E59: =IF(($C$13-$B59*E$27*($C$13-$C$18))<=E$26+0.000001,E$25*1000/($C$12*($C$13-$B59*E$27*($C$13-$C$18)))/1000000,"Fails cap") -> 6.411271 | F59: =IF(($C$13-$B59*F$27*($C$13-$C$18))<=F$26+0.000001,F$25*1000/($C$12*($C$13-$B59*F$27*($C$13-$C$18)))/1000000,"Fails cap") -> 5.0374272 | G59: =IF(($C$13-$B59*G$27*($C$13-$C$18))<=G$26+0.000001,G$25*1000/($C$12*($C$13-$B59*G$27*($C$13-$C$18)))/1000000,"Fails cap") -> Fails cap | H59: =IF(($C$13-$B59*H$27*($C$13-$C$18))<=H$26+0.000001,H$25*1000/($C$12*($C$13-$B59*H$27*($C$13-$C$18)))/1000000,"Fails cap") -> Fails cap
B60: 0.6 | C60: =IF(($C$13-$B60*C$27*($C$13-$C$18))<=C$26+0.000001,C$25*1000/($C$12*($C$13-$B60*C$27*($C$13-$C$18)))/1000000,"Fails cap") -> 5.02 | D60: =IF(($C$13-$B60*D$27*($C$13-$C$18))<=D$26+0.000001,D$25*1000/($C$12*($C$13-$B60*D$27*($C$13-$C$18)))/1000000,"Fails cap") -> 7.2147121 | E60: =IF(($C$13-$B60*E$27*($C$13-$C$18))<=E$26+0.000001,E$25*1000/($C$12*($C$13-$B60*E$27*($C$13-$C$18)))/1000000,"Fails cap") -> 7.6772379 | F60: =IF(($C$13-$B60*F$27*($C$13-$C$18))<=F$26+0.000001,F$25*1000/($C$12*($C$13-$B60*F$27*($C$13-$C$18)))/1000000,"Fails cap") -> 6.0321155 | G60: =IF(($C$13-$B60*G$27*($C$13-$C$18))<=G$26+0.000001,G$25*1000/($C$12*($C$13-$B60*G$27*($C$13-$C$18)))/1000000,"Fails cap") -> Fails cap | H60: =IF(($C$13-$B60*H$27*($C$13-$C$18))<=H$26+0.000001,H$25*1000/($C$12*($C$13-$B60*H$27*($C$13-$C$18)))/1000000,"Fails cap") -> Fails cap
B61: 0.7 | C61: =IF(($C$13-$B61*C$27*($C$13-$C$18))<=C$26+0.000001,C$25*1000/($C$12*($C$13-$B61*C$27*($C$13-$C$18)))/1000000,"Fails cap") -> 5.02 | D61: =IF(($C$13-$B61*D$27*($C$13-$C$18))<=D$26+0.000001,D$25*1000/($C$12*($C$13-$B61*D$27*($C$13-$C$18)))/1000000,"Fails cap") -> 8.1534701 | E61: =IF(($C$13-$B61*E$27*($C$13-$C$18))<=E$26+0.000001,E$25*1000/($C$12*($C$13-$B61*E$27*($C$13-$C$18)))/1000000,"Fails cap") -> 9.5661698 | F61: =IF(($C$13-$B61*F$27*($C$13-$C$18))<=F$26+0.000001,F$25*1000/($C$12*($C$13-$B61*F$27*($C$13-$C$18)))/1000000,"Fails cap") -> 7.5162763 | G61: =IF(($C$13-$B61*G$27*($C$13-$C$18))<=G$26+0.000001,G$25*1000/($C$12*($C$13-$B61*G$27*($C$13-$C$18)))/1000000,"Fails cap") -> 6.1496806 | H61: =IF(($C$13-$B61*H$27*($C$13-$C$18))<=H$26+0.000001,H$25*1000/($C$12*($C$13-$B61*H$27*($C$13-$C$18)))/1000000,"Fails cap") -> Fails cap
B62: 0.78 | C62: =IF(($C$13-$B62*C$27*($C$13-$C$18))<=C$26+0.000001,C$25*1000/($C$12*($C$13-$B62*C$27*($C$13-$C$18)))/1000000,"Fails cap") -> 5.02 | D62: =IF(($C$13-$B62*D$27*($C$13-$C$18))<=D$26+0.000001,D$25*1000/($C$12*($C$13-$B62*D$27*($C$13-$C$18)))/1000000,"Fails cap") -> 9.1008072 | E62: =IF(($C$13-$B62*E$27*($C$13-$C$18))<=E$26+0.000001,E$25*1000/($C$12*($C$13-$B62*E$27*($C$13-$C$18)))/1000000,"Fails cap") -> 11.910584 | F62: =IF(($C$13-$B62*F$27*($C$13-$C$18))<=F$26+0.000001,F$25*1000/($C$12*($C$13-$B62*F$27*($C$13-$C$18)))/1000000,"Fails cap") -> 9.358316 | G62: =IF(($C$13-$B62*G$27*($C$13-$C$18))<=G$26+0.000001,G$25*1000/($C$12*($C$13-$B62*G$27*($C$13-$C$18)))/1000000,"Fails cap") -> 7.656804 | H62: =IF(($C$13-$B62*H$27*($C$13-$C$18))<=H$26+0.000001,H$25*1000/($C$12*($C$13-$B62*H$27*($C$13-$C$18)))/1000000,"Fails cap") -> 6.1254432
B63: 0.9 | C63: =IF(($C$13-$B63*C$27*($C$13-$C$18))<=C$26+0.000001,C$25*1000/($C$12*($C$13-$B63*C$27*($C$13-$C$18)))/1000000,"Fails cap") -> 5.02 | D63: =IF(($C$13-$B63*D$27*($C$13-$C$18))<=D$26+0.000001,D$25*1000/($C$12*($C$13-$B63*D$27*($C$13-$C$18)))/1000000,"Fails cap") -> 11.021693 | E63: =IF(($C$13-$B63*E$27*($C$13-$C$18))<=E$26+0.000001,E$25*1000/($C$12*($C$13-$B63*E$27*($C$13-$C$18)))/1000000,"Fails cap") -> 18.834244 | F63: =IF(($C$13-$B63*F$27*($C$13-$C$18))<=F$26+0.000001,F$25*1000/($C$12*($C$13-$B63*F$27*($C$13-$C$18)))/1000000,"Fails cap") -> 14.798334 | G63: =IF(($C$13-$B63*G$27*($C$13-$C$18))<=G$26+0.000001,G$25*1000/($C$12*($C$13-$B63*G$27*($C$13-$C$18)))/1000000,"Fails cap") -> 12.107728 | H63: =IF(($C$13-$B63*H$27*($C$13-$C$18))<=H$26+0.000001,H$25*1000/($C$12*($C$13-$B63*H$27*($C$13-$C$18)))/1000000,"Fails cap") -> 9.6861824
B64: 1 | C64: =IF(($C$13-$B64*C$27*($C$13-$C$18))<=C$26+0.000001,C$25*1000/($C$12*($C$13-$B64*C$27*($C$13-$C$18)))/1000000,"Fails cap") -> 5.02 | D64: =IF(($C$13-$B64*D$27*($C$13-$C$18))<=D$26+0.000001,D$25*1000/($C$12*($C$13-$B64*D$27*($C$13-$C$18)))/1000000,"Fails cap") -> 13.374052 | E64: =IF(($C$13-$B64*E$27*($C$13-$C$18))<=E$26+0.000001,E$25*1000/($C$12*($C$13-$B64*E$27*($C$13-$C$18)))/1000000,"Fails cap") -> 36.530154 | F64: =IF(($C$13-$B64*F$27*($C$13-$C$18))<=F$26+0.000001,F$25*1000/($C$12*($C$13-$B64*F$27*($C$13-$C$18)))/1000000,"Fails cap") -> 28.702264 | G64: =IF(($C$13-$B64*G$27*($C$13-$C$18))<=G$26+0.000001,G$25*1000/($C$12*($C$13-$B64*G$27*($C$13-$C$18)))/1000000,"Fails cap") -> 23.48367 | H64: =IF(($C$13-$B64*H$27*($C$13-$C$18))<=H$26+0.000001,H$25*1000/($C$12*($C$13-$B64*H$27*($C$13-$C$18)))/1000000,"Fails cap") -> 18.786936
B66: Sources: Emission Target (A–C), CO2 Emission Calculation (EF), ESG_CAPEX OPEX (B6, B10:B11, J17), Sales Forecast & Case 2A KPI (C21:I21), Task 1 (commissioning date).

Sheet Task 1_ESG Roadmap
B1: TASK 1 - ESG ROAD MAP
B2: Requirement 1: five-year roadmap with CAPEX tranches, commissioning milestones, cumulative ESG completion and straight-line depreciation (5 years from the commissioning year, no salvage). Inputs in blue on cream, links to other sheets in green, formulas in black.
B4: TOTAL CAPEX ENVELOPE | C4: TRANCHE 1 · 2027 | E4: BIOMASS FIRING FROM | G4: ESG COMPLETION END-2027 | I4: CO2e CUT BY 2031 | K4: BUYER CAPS MET | M4: DEPRECIATION, FULL YEAR
B5: =C107 -> 940500 | C5: =C89 -> 896500 | E5: =C117 -> 46478 | G5: =D95 -> 0.95321637 | I5: =H77 -> 0.66205661 | K5: =COUNTIF(D78:H78,"Compliant")&" / 5 years" -> 5 / 5 years | M5: =E94 -> 188100
B6: Incl. 10% contingency; full scope kept | C6: =TEXT(C89/C107,"0.0%")&" of the envelope" -> 95.3% of the envelope | E6: Boiler tie-in in the LNY 2027 shutdown | G6: =TEXT(E95,"0%")&" from 2028 (Tranche 2)" -> 100% from 2028 (Tranche 2) | I6: ="Target "&TEXT('Emission Target'!C11,"0%")&"; index "&TEXT(H76,"0.0") -> Target 64%; index 33.8 | K6: ="Lowest headroom "&TEXT(MIN(D75:H75),"0.0%") -> Lowest headroom 6.1% | M6: 5-year straight line, no salvage
B8: Investment roadmap: CAPEX tranches, commissioning milestones and spend by year (USD)
B9: CAPEX item | C9: Priority | D9: Base cost | E9: Incl. 10% contingency | F9: Works start | G9: In service (milestone) | H9: Tranche | I9: 2027 | J9: 2028 | K9: 2029 | L9: 2030 | M9: 2031 | N9: Why this timing
B10: ='ESG_CAPEX OPEX'!A17 -> Biomass boiler/furnace retrofit package | C10: ='ESG_CAPEX OPEX'!H17 -> Critical | D10: ='ESG_CAPEX OPEX'!E17 -> 280000 | E10: =D10*(1+$C$108) -> 308000 | F10: 46388 | G10: 46478 | H10: ="T"&(YEAR(G10)-2026)&" ("&YEAR(G10)&")" -> T1 (2027) | I10: =IF(YEAR($G10)=2027,$E10,0) -> 308000 | J10: =IF(YEAR($G10)=2028,$E10,0) -> 0 | K10: =IF(YEAR($G10)=2029,$E10,0) -> 0 | L10: =IF(YEAR($G10)=2030,$E10,0) -> 0 | M10: =IF(YEAR($G10)=2031,$E10,0) -> 0 | N10: Critical. Core of conversion; tie-in during LNY 2027 shutdown. Needed to fire biomass at scale from Q2 2027 and meet the 2027 absolute cap.
B11: ='ESG_CAPEX OPEX'!A18 -> Fuel receiving, conveyor & automatic feeding | C11: ='ESG_CAPEX OPEX'!H18 -> Critical | D11: ='ESG_CAPEX OPEX'!E18 -> 120000 | E11: =D11*(1+$C$108) -> 132000 | F11: 46327 | G11: 46478 | H11: ="T"&(YEAR(G11)-2026)&" ("&YEAR(G11)&")" -> T1 (2027) | I11: =IF(YEAR($G11)=2027,$E11,0) -> 132000 | J11: =IF(YEAR($G11)=2028,$E11,0) -> 0 | K11: =IF(YEAR($G11)=2029,$E11,0) -> 0 | L11: =IF(YEAR($G11)=2030,$E11,0) -> 0 | M11: =IF(YEAR($G11)=2031,$E11,0) -> 0 | N11: Critical. Automatic feeding required before biomass firing; reduces manual handling (R05 dust/fire).
B12: ='ESG_CAPEX OPEX'!A19 -> Covered biomass warehouse & day silo | C12: ='ESG_CAPEX OPEX'!H19 -> Critical | D12: ='ESG_CAPEX OPEX'!E19 -> 85000 | E12: =D12*(1+$C$108) -> 93500 | F12: 46296 | G12: 46447 | H12: ="T"&(YEAR(G12)-2026)&" ("&YEAR(G12)&")" -> T1 (2027) | I12: =IF(YEAR($G12)=2027,$E12,0) -> 93500 | J12: =IF(YEAR($G12)=2028,$E12,0) -> 0 | K12: =IF(YEAR($G12)=2029,$E12,0) -> 0 | L12: =IF(YEAR($G12)=2030,$E12,0) -> 0 | M12: =IF(YEAR($G12)=2031,$E12,0) -> 0 | N12: Critical. 10–14 day covered buffer must be stocked before firing; protects moisture spec (R02) and rainy-season supply (R01).
B13: ='ESG_CAPEX OPEX'!A20 -> Ash extraction & handling system | C13: ='ESG_CAPEX OPEX'!H20 -> High | D13: ='ESG_CAPEX OPEX'!E20 -> 45000 | E13: =D13*(1+$C$108) -> 49500 | F13: 46388 | G13: 46478 | H13: ="T"&(YEAR(G13)-2026)&" ("&YEAR(G13)&")" -> T1 (2027) | I13: =IF(YEAR($G13)=2027,$E13,0) -> 49500 | J13: =IF(YEAR($G13)=2028,$E13,0) -> 0 | K13: =IF(YEAR($G13)=2029,$E13,0) -> 0 | L13: =IF(YEAR($G13)=2030,$E13,0) -> 0 | M13: =IF(YEAR($G13)=2031,$E13,0) -> 0 | N13: High. Silica-rich rice-husk ash needs dedicated handling from first firing (R04 fouling).
B14: ='ESG_CAPEX OPEX'!A21 -> Multi-cyclone + bag filter upgrade | C14: ='ESG_CAPEX OPEX'!H21 -> Critical | D14: ='ESG_CAPEX OPEX'!E21 -> 95000 | E14: =D14*(1+$C$108) -> 104500 | F14: 46388 | G14: 46478 | H14: ="T"&(YEAR(G14)-2026)&" ("&YEAR(G14)&")" -> T1 (2027) | I14: =IF(YEAR($G14)=2027,$E14,0) -> 104500 | J14: =IF(YEAR($G14)=2028,$E14,0) -> 0 | K14: =IF(YEAR($G14)=2029,$E14,0) -> 0 | L14: =IF(YEAR($G14)=2030,$E14,0) -> 0 | M14: =IF(YEAR($G14)=2031,$E14,0) -> 0 | N14: Critical. Particulate control is a legal precondition for biomass combustion.
B15: ='ESG_CAPEX OPEX'!A22 -> Stack emission & energy metering system | C15: ='ESG_CAPEX OPEX'!H22 -> High | D15: ='ESG_CAPEX OPEX'!E22 -> 35000 | E15: =D15*(1+$C$108) -> 38500 | F15: 46296 | G15: 46388 | H15: ="T"&(YEAR(G15)-2026)&" ("&YEAR(G15)&")" -> T1 (2027) | I15: =IF(YEAR($G15)=2027,$E15,0) -> 38500 | J15: =IF(YEAR($G15)=2028,$E15,0) -> 0 | K15: =IF(YEAR($G15)=2029,$E15,0) -> 0 | L15: =IF(YEAR($G15)=2030,$E15,0) -> 0 | M15: =IF(YEAR($G15)=2031,$E15,0) -> 0 | N15: High. Metering first: verified 2026–2027 baseline and auditable annual CO2e (Emission Target F7, B19).
B16: ='ESG_CAPEX OPEX'!A23 -> Water treatment & condensate recovery upgrade | C16: ='ESG_CAPEX OPEX'!H23 -> Medium | D16: ='ESG_CAPEX OPEX'!E23 -> 40000 | E16: =D16*(1+$C$108) -> 44000 | F16: 46661 | G16: 46813 | H16: ="T"&(YEAR(G16)-2026)&" ("&YEAR(G16)&")" -> T2 (2028) | I16: =IF(YEAR($G16)=2027,$E16,0) -> 0 | J16: =IF(YEAR($G16)=2028,$E16,0) -> 44000 | K16: =IF(YEAR($G16)=2029,$E16,0) -> 0 | L16: =IF(YEAR($G16)=2030,$E16,0) -> 0 | M16: =IF(YEAR($G16)=2031,$E16,0) -> 0 | N16: Medium. Efficiency upgrade; installed after the main system stabilises, during LNY 2028. Savings not counted (conservative).
B17: ='ESG_CAPEX OPEX'!A24 -> Fire detection, dust control & safety system | C17: ='ESG_CAPEX OPEX'!H24 -> Critical | D17: ='ESG_CAPEX OPEX'!E24 -> 30000 | E17: =D17*(1+$C$108) -> 33000 | F17: 46327 | G17: 46447 | H17: ="T"&(YEAR(G17)-2026)&" ("&YEAR(G17)&")" -> T1 (2027) | I17: =IF(YEAR($G17)=2027,$E17,0) -> 33000 | J17: =IF(YEAR($G17)=2028,$E17,0) -> 0 | K17: =IF(YEAR($G17)=2029,$E17,0) -> 0 | L17: =IF(YEAR($G17)=2030,$E17,0) -> 0 | M17: =IF(YEAR($G17)=2031,$E17,0) -> 0 | N17: Critical. Must be live before biomass is stored on site (R05).
B18: ='ESG_CAPEX OPEX'!A25 -> Civil, electrical & piping modification | C18: ='ESG_CAPEX OPEX'!H25 -> High | D18: ='ESG_CAPEX OPEX'!E25 -> 55000 | E18: =D18*(1+$C$108) -> 60500 | F18: 46296 | G18: 46447 | H18: ="T"&(YEAR(G18)-2026)&" ("&YEAR(G18)&")" -> T1 (2027) | I18: =IF(YEAR($G18)=2027,$E18,0) -> 60500 | J18: =IF(YEAR($G18)=2028,$E18,0) -> 0 | K18: =IF(YEAR($G18)=2029,$E18,0) -> 0 | L18: =IF(YEAR($G18)=2030,$E18,0) -> 0 | M18: =IF(YEAR($G18)=2031,$E18,0) -> 0 | N18: High. Foundations, piping, MCC needed to integrate the retrofit.
B19: ='ESG_CAPEX OPEX'!A26 -> Engineering, commissioning & performance test | C19: ='ESG_CAPEX OPEX'!H26 -> High | D19: ='ESG_CAPEX OPEX'!E26 -> 45000 | E19: =D19*(1+$C$108) -> 49500 | F19: 46296 | G19: 46478 | H19: ="T"&(YEAR(G19)-2026)&" ("&YEAR(G19)&")" -> T1 (2027) | I19: =IF(YEAR($G19)=2027,$E19,0) -> 49500 | J19: =IF(YEAR($G19)=2028,$E19,0) -> 0 | K19: =IF(YEAR($G19)=2029,$E19,0) -> 0 | L19: =IF(YEAR($G19)=2030,$E19,0) -> 0 | M19: =IF(YEAR($G19)=2031,$E19,0) -> 0 | N19: High. Performance test is the formal commissioning gate of Tranche 1.
B20: ='ESG_CAPEX OPEX'!A27 -> ESG certification/traceability setup | C20: ='ESG_CAPEX OPEX'!H27 -> Medium | D20: ='ESG_CAPEX OPEX'!E27 -> 25000 | E20: =D20*(1+$C$108) -> 27500 | F20: 46327 | G20: 46419 | H20: ="T"&(YEAR(G20)-2026)&" ("&YEAR(G20)&")" -> T1 (2027) | I20: =IF(YEAR($G20)=2027,$E20,0) -> 27500 | J20: =IF(YEAR($G20)=2028,$E20,0) -> 0 | K20: =IF(YEAR($G20)=2029,$E20,0) -> 0 | L20: =IF(YEAR($G20)=2030,$E20,0) -> 0 | M20: =IF(YEAR($G20)=2031,$E20,0) -> 0 | N20: Medium in case data, but needed before the first biomass purchase to avoid greenwashing claims (R06).
B21: CAPEX spend in year | D21: =SUM(D10:D20) -> 855000 | E21: =SUM(E10:E20) -> 940500 | I21: =SUM(I10:I20) -> 896500 | J21: =SUM(J10:J20) -> 44000 | K21: =SUM(K10:K20) -> 0 | L21: =SUM(L10:L20) -> 0 | M21: =SUM(M10:M20) -> 0 | N21: Spend is booked in the tranche (commissioning) year, as in the case template row 47.
B22: Cumulative CAPEX in service | I22: =I21 -> 896500 | J22: =J21+I22 -> 940500 | K22: =K21+J22 -> 940500 | L22: =L21+K22 -> 940500 | M22: =M21+L22 -> 940500 | N22: ESG completion = CAPEX value in service ÷ envelope (USD 940,500). A tranche counts only from its in-service date: a CAPEX commitment alone earns no credit (Emission Target F18).
B23: Cumulative ESG completion (% of the CAPEX envelope) | I23: =I22/$C$107 -> 0.95321637 | J23: =J22/$C$107 -> 1 | K23: =K22/$C$107 -> 1 | L23: =L22/$C$107 -> 1 | M23: =M22/$C$107 -> 1
B24: Check: tranche total = CAPEX envelope | E24: =IF(ABS(E21-C107)<1,"OK","CHECK") -> OK
B26: Commissioning Gantt by quarter, Q4 2026 to Q2 2029 (bars follow the dates in the roadmap table)
B27: Year | C27: 2026 | D27: 2027 | H27: 2028 | L27: 2029 | N27: Works window → in service | O27: Start | P27: In service / end
B28: CAPEX item / milestone | C28: Q4 2026 | D28: Q1 2027 | E28: Q2 2027 | F28: Q3 2027 | G28: Q4 2027 | H28: Q1 2028 | I28: Q2 2028 | J28: Q3 2028 | K28: Q4 2028 | L28: Q1 2029 | M28: Q2 2029
B29: Tranche 1 (2027): biomass conversion core, 10 items | C29: =IF(AND($P29>=DATE(2026,10,1),$P29<DATE(2026,13,1)),DAY($P29)&" "&CHOOSE(MONTH($P29),"Jan","Feb","Mar","Apr","May","Jun","Jul","Aug","Sep","Oct","Nov","Dec"),"") | D29: =IF(AND($P29>=DATE(2027,1,1),$P29<DATE(2027,4,1)),DAY($P29)&" "&CHOOSE(MONTH($P29),"Jan","Feb","Mar","Apr","May","Jun","Jul","Aug","Sep","Oct","Nov","Dec"),"") | E29: =IF(AND($P29>=DATE(2027,4,1),$P29<DATE(2027,7,1)),DAY($P29)&" "&CHOOSE(MONTH($P29),"Jan","Feb","Mar","Apr","May","Jun","Jul","Aug","Sep","Oct","Nov","Dec"),"") -> 1 Apr | F29: =IF(AND($P29>=DATE(2027,7,1),$P29<DATE(2027,10,1)),DAY($P29)&" "&CHOOSE(MONTH($P29),"Jan","Feb","Mar","Apr","May","Jun","Jul","Aug","Sep","Oct","Nov","Dec"),"") | G29: =IF(AND($P29>=DATE(2027,10,1),$P29<DATE(2027,13,1)),DAY($P29)&" "&CHOOSE(MONTH($P29),"Jan","Feb","Mar","Apr","May","Jun","Jul","Aug","Sep","Oct","Nov","Dec"),"") | H29: =IF(AND($P29>=DATE(2028,1,1),$P29<DATE(2028,4,1)),DAY($P29)&" "&CHOOSE(MONTH($P29),"Jan","Feb","Mar","Apr","May","Jun","Jul","Aug","Sep","Oct","Nov","Dec"),"") | I29: =IF(AND($P29>=DATE(2028,4,1),$P29<DATE(2028,7,1)),DAY($P29)&" "&CHOOSE(MONTH($P29),"Jan","Feb","Mar","Apr","May","Jun","Jul","Aug","Sep","Oct","Nov","Dec"),"") | J29: =IF(AND($P29>=DATE(2028,7,1),$P29<DATE(2028,10,1)),DAY($P29)&" "&CHOOSE(MONTH($P29),"Jan","Feb","Mar","Apr","May","Jun","Jul","Aug","Sep","Oct","Nov","Dec"),"") | K29: =IF(AND($P29>=DATE(2028,10,1),$P29<DATE(2028,13,1)),DAY($P29)&" "&CHOOSE(MONTH($P29),"Jan","Feb","Mar","Apr","May","Jun","Jul","Aug","Sep","Oct","Nov","Dec"),"") | L29: =IF(AND($P29>=DATE(2029,1,1),$P29<DATE(2029,4,1)),DAY($P29)&" "&CHOOSE(MONTH($P29),"Jan","Feb","Mar","Apr","May","Jun","Jul","Aug","Sep","Oct","Nov","Dec"),"") | M29: =IF(AND($P29>=DATE(2029,4,1),$P29<DATE(2029,7,1)),DAY($P29)&" "&CHOOSE(MONTH($P29),"Jan","Feb","Mar","Apr","May","Jun","Jul","Aug","Sep","Oct","Nov","Dec"),"") | N29: =CHOOSE(MONTH(O29),"Jan","Feb","Mar","Apr","May","Jun","Jul","Aug","Sep","Oct","Nov","Dec")&" "&YEAR(O29)&" → "&DAY(P29)&" "&CHOOSE(MONTH(P29),"Jan","Feb","Mar","Apr","May","Jun","Jul","Aug","Sep","Oct","Nov","Dec")&" "&YEAR(P29)&" ("&((YEAR(P29)-YEAR(O29))*12+MONTH(P29)-MONTH(O29))&" months)" -> Oct 2026 → 1 Apr 2027 (6 months) | O29: =MIN(F15,F12,F18,F19,F11,F17,F20,F10,F13,F14) -> 46296 | P29: =MAX(G15,G12,G18,G19,G11,G17,G20,G10,G13,G14) -> 46478
B30: =B15 -> Stack emission & energy metering system | C30: =IF(AND($P30>=DATE(2026,10,1),$P30<DATE(2026,13,1)),DAY($P30)&" "&CHOOSE(MONTH($P30),"Jan","Feb","Mar","Apr","May","Jun","Jul","Aug","Sep","Oct","Nov","Dec"),"") | D30: =IF(AND($P30>=DATE(2027,1,1),$P30<DATE(2027,4,1)),DAY($P30)&" "&CHOOSE(MONTH($P30),"Jan","Feb","Mar","Apr","May","Jun","Jul","Aug","Sep","Oct","Nov","Dec"),"") -> 1 Jan | E30: =IF(AND($P30>=DATE(2027,4,1),$P30<DATE(2027,7,1)),DAY($P30)&" "&CHOOSE(MONTH($P30),"Jan","Feb","Mar","Apr","May","Jun","Jul","Aug","Sep","Oct","Nov","Dec"),"") | F30: =IF(AND($P30>=DATE(2027,7,1),$P30<DATE(2027,10,1)),DAY($P30)&" "&CHOOSE(MONTH($P30),"Jan","Feb","Mar","Apr","May","Jun","Jul","Aug","Sep","Oct","Nov","Dec"),"") | G30: =IF(AND($P30>=DATE(2027,10,1),$P30<DATE(2027,13,1)),DAY($P30)&" "&CHOOSE(MONTH($P30),"Jan","Feb","Mar","Apr","May","Jun","Jul","Aug","Sep","Oct","Nov","Dec"),"") | H30: =IF(AND($P30>=DATE(2028,1,1),$P30<DATE(2028,4,1)),DAY($P30)&" "&CHOOSE(MONTH($P30),"Jan","Feb","Mar","Apr","May","Jun","Jul","Aug","Sep","Oct","Nov","Dec"),"") | I30: =IF(AND($P30>=DATE(2028,4,1),$P30<DATE(2028,7,1)),DAY($P30)&" "&CHOOSE(MONTH($P30),"Jan","Feb","Mar","Apr","May","Jun","Jul","Aug","Sep","Oct","Nov","Dec"),"") | J30: =IF(AND($P30>=DATE(2028,7,1),$P30<DATE(2028,10,1)),DAY($P30)&" "&CHOOSE(MONTH($P30),"Jan","Feb","Mar","Apr","May","Jun","Jul","Aug","Sep","Oct","Nov","Dec"),"") | K30: =IF(AND($P30>=DATE(2028,10,1),$P30<DATE(2028,13,1)),DAY($P30)&" "&CHOOSE(MONTH($P30),"Jan","Feb","Mar","Apr","May","Jun","Jul","Aug","Sep","Oct","Nov","Dec"),"") | L30: =IF(AND($P30>=DATE(2029,1,1),$P30<DATE(2029,4,1)),DAY($P30)&" "&CHOOSE(MONTH($P30),"Jan","Feb","Mar","Apr","May","Jun","Jul","Aug","Sep","Oct","Nov","Dec"),"") | M30: =IF(AND($P30>=DATE(2029,4,1),$P30<DATE(2029,7,1)),DAY($P30)&" "&CHOOSE(MONTH($P30),"Jan","Feb","Mar","Apr","May","Jun","Jul","Aug","Sep","Oct","Nov","Dec"),"") | N30: =CHOOSE(MONTH(O30),"Jan","Feb","Mar","Apr","May","Jun","Jul","Aug","Sep","Oct","Nov","Dec")&" "&YEAR(O30)&" → "&DAY(P30)&" "&CHOOSE(MONTH(P30),"Jan","Feb","Mar","Apr","May","Jun","Jul","Aug","Sep","Oct","Nov","Dec")&" "&YEAR(P30)&" ("&((YEAR(P30)-YEAR(O30))*12+MONTH(P30)-MONTH(O30))&" months)" -> Oct 2026 → 1 Jan 2027 (3 months) | O30: =F15 -> 46296 | P30: =G15 -> 46388
B31: =B12 -> Covered biomass warehouse & day silo | C31: =IF(AND($P31>=DATE(2026,10,1),$P31<DATE(2026,13,1)),DAY($P31)&" "&CHOOSE(MONTH($P31),"Jan","Feb","Mar","Apr","May","Jun","Jul","Aug","Sep","Oct","Nov","Dec"),"") | D31: =IF(AND($P31>=DATE(2027,1,1),$P31<DATE(2027,4,1)),DAY($P31)&" "&CHOOSE(MONTH($P31),"Jan","Feb","Mar","Apr","May","Jun","Jul","Aug","Sep","Oct","Nov","Dec"),"") -> 1 Mar | E31: =IF(AND($P31>=DATE(2027,4,1),$P31<DATE(2027,7,1)),DAY($P31)&" "&CHOOSE(MONTH($P31),"Jan","Feb","Mar","Apr","May","Jun","Jul","Aug","Sep","Oct","Nov","Dec"),"") | F31: =IF(AND($P31>=DATE(2027,7,1),$P31<DATE(2027,10,1)),DAY($P31)&" "&CHOOSE(MONTH($P31),"Jan","Feb","Mar","Apr","May","Jun","Jul","Aug","Sep","Oct","Nov","Dec"),"") | G31: =IF(AND($P31>=DATE(2027,10,1),$P31<DATE(2027,13,1)),DAY($P31)&" "&CHOOSE(MONTH($P31),"Jan","Feb","Mar","Apr","May","Jun","Jul","Aug","Sep","Oct","Nov","Dec"),"") | H31: =IF(AND($P31>=DATE(2028,1,1),$P31<DATE(2028,4,1)),DAY($P31)&" "&CHOOSE(MONTH($P31),"Jan","Feb","Mar","Apr","May","Jun","Jul","Aug","Sep","Oct","Nov","Dec"),"") | I31: =IF(AND($P31>=DATE(2028,4,1),$P31<DATE(2028,7,1)),DAY($P31)&" "&CHOOSE(MONTH($P31),"Jan","Feb","Mar","Apr","May","Jun","Jul","Aug","Sep","Oct","Nov","Dec"),"") | J31: =IF(AND($P31>=DATE(2028,7,1),$P31<DATE(2028,10,1)),DAY($P31)&" "&CHOOSE(MONTH($P31),"Jan","Feb","Mar","Apr","May","Jun","Jul","Aug","Sep","Oct","Nov","Dec"),"") | K31: =IF(AND($P31>=DATE(2028,10,1),$P31<DATE(2028,13,1)),DAY($P31)&" "&CHOOSE(MONTH($P31),"Jan","Feb","Mar","Apr","May","Jun","Jul","Aug","Sep","Oct","Nov","Dec"),"") | L31: =IF(AND($P31>=DATE(2029,1,1),$P31<DATE(2029,4,1)),DAY($P31)&" "&CHOOSE(MONTH($P31),"Jan","Feb","Mar","Apr","May","Jun","Jul","Aug","Sep","Oct","Nov","Dec"),"") | M31: =IF(AND($P31>=DATE(2029,4,1),$P31<DATE(2029,7,1)),DAY($P31)&" "&CHOOSE(MONTH($P31),"Jan","Feb","Mar","Apr","May","Jun","Jul","Aug","Sep","Oct","Nov","Dec"),"") | N31: =CHOOSE(MONTH(O31),"Jan","Feb","Mar","Apr","May","Jun","Jul","Aug","Sep","Oct","Nov","Dec")&" "&YEAR(O31)&" → "&DAY(P31)&" "&CHOOSE(MONTH(P31),"Jan","Feb","Mar","Apr","May","Jun","Jul","Aug","Sep","Oct","Nov","Dec")&" "&YEAR(P31)&" ("&((YEAR(P31)-YEAR(O31))*12+MONTH(P31)-MONTH(O31))&" months)" -> Oct 2026 → 1 Mar 2027 (5 months) | O31: =F12 -> 46296 | P31: =G12 -> 46447
B32: =B18 -> Civil, electrical & piping modification | C32: =IF(AND($P32>=DATE(2026,10,1),$P32<DATE(2026,13,1)),DAY($P32)&" "&CHOOSE(MONTH($P32),"Jan","Feb","Mar","Apr","May","Jun","Jul","Aug","Sep","Oct","Nov","Dec"),"") | D32: =IF(AND($P32>=DATE(2027,1,1),$P32<DATE(2027,4,1)),DAY($P32)&" "&CHOOSE(MONTH($P32),"Jan","Feb","Mar","Apr","May","Jun","Jul","Aug","Sep","Oct","Nov","Dec"),"") -> 1 Mar | E32: =IF(AND($P32>=DATE(2027,4,1),$P32<DATE(2027,7,1)),DAY($P32)&" "&CHOOSE(MONTH($P32),"Jan","Feb","Mar","Apr","May","Jun","Jul","Aug","Sep","Oct","Nov","Dec"),"") | F32: =IF(AND($P32>=DATE(2027,7,1),$P32<DATE(2027,10,1)),DAY($P32)&" "&CHOOSE(MONTH($P32),"Jan","Feb","Mar","Apr","May","Jun","Jul","Aug","Sep","Oct","Nov","Dec"),"") | G32: =IF(AND($P32>=DATE(2027,10,1),$P32<DATE(2027,13,1)),DAY($P32)&" "&CHOOSE(MONTH($P32),"Jan","Feb","Mar","Apr","May","Jun","Jul","Aug","Sep","Oct","Nov","Dec"),"") | H32: =IF(AND($P32>=DATE(2028,1,1),$P32<DATE(2028,4,1)),DAY($P32)&" "&CHOOSE(MONTH($P32),"Jan","Feb","Mar","Apr","May","Jun","Jul","Aug","Sep","Oct","Nov","Dec"),"") | I32: =IF(AND($P32>=DATE(2028,4,1),$P32<DATE(2028,7,1)),DAY($P32)&" "&CHOOSE(MONTH($P32),"Jan","Feb","Mar","Apr","May","Jun","Jul","Aug","Sep","Oct","Nov","Dec"),"") | J32: =IF(AND($P32>=DATE(2028,7,1),$P32<DATE(2028,10,1)),DAY($P32)&" "&CHOOSE(MONTH($P32),"Jan","Feb","Mar","Apr","May","Jun","Jul","Aug","Sep","Oct","Nov","Dec"),"") | K32: =IF(AND($P32>=DATE(2028,10,1),$P32<DATE(2028,13,1)),DAY($P32)&" "&CHOOSE(MONTH($P32),"Jan","Feb","Mar","Apr","May","Jun","Jul","Aug","Sep","Oct","Nov","Dec"),"") | L32: =IF(AND($P32>=DATE(2029,1,1),$P32<DATE(2029,4,1)),DAY($P32)&" "&CHOOSE(MONTH($P32),"Jan","Feb","Mar","Apr","May","Jun","Jul","Aug","Sep","Oct","Nov","Dec"),"") | M32: =IF(AND($P32>=DATE(2029,4,1),$P32<DATE(2029,7,1)),DAY($P32)&" "&CHOOSE(MONTH($P32),"Jan","Feb","Mar","Apr","May","Jun","Jul","Aug","Sep","Oct","Nov","Dec"),"") | N32: =CHOOSE(MONTH(O32),"Jan","Feb","Mar","Apr","May","Jun","Jul","Aug","Sep","Oct","Nov","Dec")&" "&YEAR(O32)&" → "&DAY(P32)&" "&CHOOSE(MONTH(P32),"Jan","Feb","Mar","Apr","May","Jun","Jul","Aug","Sep","Oct","Nov","Dec")&" "&YEAR(P32)&" ("&((YEAR(P32)-YEAR(O32))*12+MONTH(P32)-MONTH(O32))&" months)" -> Oct 2026 → 1 Mar 2027 (5 months) | O32: =F18 -> 46296 | P32: =G18 -> 46447
B33: =B19 -> Engineering, commissioning & performance test | C33: =IF(AND($P33>=DATE(2026,10,1),$P33<DATE(2026,13,1)),DAY($P33)&" "&CHOOSE(MONTH($P33),"Jan","Feb","Mar","Apr","May","Jun","Jul","Aug","Sep","Oct","Nov","Dec"),"") | D33: =IF(AND($P33>=DATE(2027,1,1),$P33<DATE(2027,4,1)),DAY($P33)&" "&CHOOSE(MONTH($P33),"Jan","Feb","Mar","Apr","May","Jun","Jul","Aug","Sep","Oct","Nov","Dec"),"") | E33: =IF(AND($P33>=DATE(2027,4,1),$P33<DATE(2027,7,1)),DAY($P33)&" "&CHOOSE(MONTH($P33),"Jan","Feb","Mar","Apr","May","Jun","Jul","Aug","Sep","Oct","Nov","Dec"),"") -> 1 Apr | F33: =IF(AND($P33>=DATE(2027,7,1),$P33<DATE(2027,10,1)),DAY($P33)&" "&CHOOSE(MONTH($P33),"Jan","Feb","Mar","Apr","May","Jun","Jul","Aug","Sep","Oct","Nov","Dec"),"") | G33: =IF(AND($P33>=DATE(2027,10,1),$P33<DATE(2027,13,1)),DAY($P33)&" "&CHOOSE(MONTH($P33),"Jan","Feb","Mar","Apr","May","Jun","Jul","Aug","Sep","Oct","Nov","Dec"),"") | H33: =IF(AND($P33>=DATE(2028,1,1),$P33<DATE(2028,4,1)),DAY($P33)&" "&CHOOSE(MONTH($P33),"Jan","Feb","Mar","Apr","May","Jun","Jul","Aug","Sep","Oct","Nov","Dec"),"") | I33: =IF(AND($P33>=DATE(2028,4,1),$P33<DATE(2028,7,1)),DAY($P33)&" "&CHOOSE(MONTH($P33),"Jan","Feb","Mar","Apr","May","Jun","Jul","Aug","Sep","Oct","Nov","Dec"),"") | J33: =IF(AND($P33>=DATE(2028,7,1),$P33<DATE(2028,10,1)),DAY($P33)&" "&CHOOSE(MONTH($P33),"Jan","Feb","Mar","Apr","May","Jun","Jul","Aug","Sep","Oct","Nov","Dec"),"") | K33: =IF(AND($P33>=DATE(2028,10,1),$P33<DATE(2028,13,1)),DAY($P33)&" "&CHOOSE(MONTH($P33),"Jan","Feb","Mar","Apr","May","Jun","Jul","Aug","Sep","Oct","Nov","Dec"),"") | L33: =IF(AND($P33>=DATE(2029,1,1),$P33<DATE(2029,4,1)),DAY($P33)&" "&CHOOSE(MONTH($P33),"Jan","Feb","Mar","Apr","May","Jun","Jul","Aug","Sep","Oct","Nov","Dec"),"") | M33: =IF(AND($P33>=DATE(2029,4,1),$P33<DATE(2029,7,1)),DAY($P33)&" "&CHOOSE(MONTH($P33),"Jan","Feb","Mar","Apr","May","Jun","Jul","Aug","Sep","Oct","Nov","Dec"),"") | N33: =CHOOSE(MONTH(O33),"Jan","Feb","Mar","Apr","May","Jun","Jul","Aug","Sep","Oct","Nov","Dec")&" "&YEAR(O33)&" → "&DAY(P33)&" "&CHOOSE(MONTH(P33),"Jan","Feb","Mar","Apr","May","Jun","Jul","Aug","Sep","Oct","Nov","Dec")&" "&YEAR(P33)&" ("&((YEAR(P33)-YEAR(O33))*12+MONTH(P33)-MONTH(O33))&" months)" -> Oct 2026 → 1 Apr 2027 (6 months) | O33: =F19 -> 46296 | P33: =G19 -> 46478
B34: =B11 -> Fuel receiving, conveyor & automatic feeding | C34: =IF(AND($P34>=DATE(2026,10,1),$P34<DATE(2026,13,1)),DAY($P34)&" "&CHOOSE(MONTH($P34),"Jan","Feb","Mar","Apr","May","Jun","Jul","Aug","Sep","Oct","Nov","Dec"),"") | D34: =IF(AND($P34>=DATE(2027,1,1),$P34<DATE(2027,4,1)),DAY($P34)&" "&CHOOSE(MONTH($P34),"Jan","Feb","Mar","Apr","May","Jun","Jul","Aug","Sep","Oct","Nov","Dec"),"") | E34: =IF(AND($P34>=DATE(2027,4,1),$P34<DATE(2027,7,1)),DAY($P34)&" "&CHOOSE(MONTH($P34),"Jan","Feb","Mar","Apr","May","Jun","Jul","Aug","Sep","Oct","Nov","Dec"),"") -> 1 Apr | F34: =IF(AND($P34>=DATE(2027,7,1),$P34<DATE(2027,10,1)),DAY($P34)&" "&CHOOSE(MONTH($P34),"Jan","Feb","Mar","Apr","May","Jun","Jul","Aug","Sep","Oct","Nov","Dec"),"") | G34: =IF(AND($P34>=DATE(2027,10,1),$P34<DATE(2027,13,1)),DAY($P34)&" "&CHOOSE(MONTH($P34),"Jan","Feb","Mar","Apr","May","Jun","Jul","Aug","Sep","Oct","Nov","Dec"),"") | H34: =IF(AND($P34>=DATE(2028,1,1),$P34<DATE(2028,4,1)),DAY($P34)&" "&CHOOSE(MONTH($P34),"Jan","Feb","Mar","Apr","May","Jun","Jul","Aug","Sep","Oct","Nov","Dec"),"") | I34: =IF(AND($P34>=DATE(2028,4,1),$P34<DATE(2028,7,1)),DAY($P34)&" "&CHOOSE(MONTH($P34),"Jan","Feb","Mar","Apr","May","Jun","Jul","Aug","Sep","Oct","Nov","Dec"),"") | J34: =IF(AND($P34>=DATE(2028,7,1),$P34<DATE(2028,10,1)),DAY($P34)&" "&CHOOSE(MONTH($P34),"Jan","Feb","Mar","Apr","May","Jun","Jul","Aug","Sep","Oct","Nov","Dec"),"") | K34: =IF(AND($P34>=DATE(2028,10,1),$P34<DATE(2028,13,1)),DAY($P34)&" "&CHOOSE(MONTH($P34),"Jan","Feb","Mar","Apr","May","Jun","Jul","Aug","Sep","Oct","Nov","Dec"),"") | L34: =IF(AND($P34>=DATE(2029,1,1),$P34<DATE(2029,4,1)),DAY($P34)&" "&CHOOSE(MONTH($P34),"Jan","Feb","Mar","Apr","May","Jun","Jul","Aug","Sep","Oct","Nov","Dec"),"") | M34: =IF(AND($P34>=DATE(2029,4,1),$P34<DATE(2029,7,1)),DAY($P34)&" "&CHOOSE(MONTH($P34),"Jan","Feb","Mar","Apr","May","Jun","Jul","Aug","Sep","Oct","Nov","Dec"),"") | N34: =CHOOSE(MONTH(O34),"Jan","Feb","Mar","Apr","May","Jun","Jul","Aug","Sep","Oct","Nov","Dec")&" "&YEAR(O34)&" → "&DAY(P34)&" "&CHOOSE(MONTH(P34),"Jan","Feb","Mar","Apr","May","Jun","Jul","Aug","Sep","Oct","Nov","Dec")&" "&YEAR(P34)&" ("&((YEAR(P34)-YEAR(O34))*12+MONTH(P34)-MONTH(O34))&" months)" -> Nov 2026 → 1 Apr 2027 (5 months) | O34: =F11 -> 46327 | P34: =G11 -> 46478
B35: =B17 -> Fire detection, dust control & safety system | C35: =IF(AND($P35>=DATE(2026,10,1),$P35<DATE(2026,13,1)),DAY($P35)&" "&CHOOSE(MONTH($P35),"Jan","Feb","Mar","Apr","May","Jun","Jul","Aug","Sep","Oct","Nov","Dec"),"") | D35: =IF(AND($P35>=DATE(2027,1,1),$P35<DATE(2027,4,1)),DAY($P35)&" "&CHOOSE(MONTH($P35),"Jan","Feb","Mar","Apr","May","Jun","Jul","Aug","Sep","Oct","Nov","Dec"),"") -> 1 Mar | E35: =IF(AND($P35>=DATE(2027,4,1),$P35<DATE(2027,7,1)),DAY($P35)&" "&CHOOSE(MONTH($P35),"Jan","Feb","Mar","Apr","May","Jun","Jul","Aug","Sep","Oct","Nov","Dec"),"") | F35: =IF(AND($P35>=DATE(2027,7,1),$P35<DATE(2027,10,1)),DAY($P35)&" "&CHOOSE(MONTH($P35),"Jan","Feb","Mar","Apr","May","Jun","Jul","Aug","Sep","Oct","Nov","Dec"),"") | G35: =IF(AND($P35>=DATE(2027,10,1),$P35<DATE(2027,13,1)),DAY($P35)&" "&CHOOSE(MONTH($P35),"Jan","Feb","Mar","Apr","May","Jun","Jul","Aug","Sep","Oct","Nov","Dec"),"") | H35: =IF(AND($P35>=DATE(2028,1,1),$P35<DATE(2028,4,1)),DAY($P35)&" "&CHOOSE(MONTH($P35),"Jan","Feb","Mar","Apr","May","Jun","Jul","Aug","Sep","Oct","Nov","Dec"),"") | I35: =IF(AND($P35>=DATE(2028,4,1),$P35<DATE(2028,7,1)),DAY($P35)&" "&CHOOSE(MONTH($P35),"Jan","Feb","Mar","Apr","May","Jun","Jul","Aug","Sep","Oct","Nov","Dec"),"") | J35: =IF(AND($P35>=DATE(2028,7,1),$P35<DATE(2028,10,1)),DAY($P35)&" "&CHOOSE(MONTH($P35),"Jan","Feb","Mar","Apr","May","Jun","Jul","Aug","Sep","Oct","Nov","Dec"),"") | K35: =IF(AND($P35>=DATE(2028,10,1),$P35<DATE(2028,13,1)),DAY($P35)&" "&CHOOSE(MONTH($P35),"Jan","Feb","Mar","Apr","May","Jun","Jul","Aug","Sep","Oct","Nov","Dec"),"") | L35: =IF(AND($P35>=DATE(2029,1,1),$P35<DATE(2029,4,1)),DAY($P35)&" "&CHOOSE(MONTH($P35),"Jan","Feb","Mar","Apr","May","Jun","Jul","Aug","Sep","Oct","Nov","Dec"),"") | M35: =IF(AND($P35>=DATE(2029,4,1),$P35<DATE(2029,7,1)),DAY($P35)&" "&CHOOSE(MONTH($P35),"Jan","Feb","Mar","Apr","May","Jun","Jul","Aug","Sep","Oct","Nov","Dec"),"") | N35: =CHOOSE(MONTH(O35),"Jan","Feb","Mar","Apr","May","Jun","Jul","Aug","Sep","Oct","Nov","Dec")&" "&YEAR(O35)&" → "&DAY(P35)&" "&CHOOSE(MONTH(P35),"Jan","Feb","Mar","Apr","May","Jun","Jul","Aug","Sep","Oct","Nov","Dec")&" "&YEAR(P35)&" ("&((YEAR(P35)-YEAR(O35))*12+MONTH(P35)-MONTH(O35))&" months)" -> Nov 2026 → 1 Mar 2027 (4 months) | O35: =F17 -> 46327 | P35: =G17 -> 46447
B36: =B20 -> ESG certification/traceability setup | C36: =IF(AND($P36>=DATE(2026,10,1),$P36<DATE(2026,13,1)),DAY($P36)&" "&CHOOSE(MONTH($P36),"Jan","Feb","Mar","Apr","May","Jun","Jul","Aug","Sep","Oct","Nov","Dec"),"") | D36: =IF(AND($P36>=DATE(2027,1,1),$P36<DATE(2027,4,1)),DAY($P36)&" "&CHOOSE(MONTH($P36),"Jan","Feb","Mar","Apr","May","Jun","Jul","Aug","Sep","Oct","Nov","Dec"),"") -> 1 Feb | E36: =IF(AND($P36>=DATE(2027,4,1),$P36<DATE(2027,7,1)),DAY($P36)&" "&CHOOSE(MONTH($P36),"Jan","Feb","Mar","Apr","May","Jun","Jul","Aug","Sep","Oct","Nov","Dec"),"") | F36: =IF(AND($P36>=DATE(2027,7,1),$P36<DATE(2027,10,1)),DAY($P36)&" "&CHOOSE(MONTH($P36),"Jan","Feb","Mar","Apr","May","Jun","Jul","Aug","Sep","Oct","Nov","Dec"),"") | G36: =IF(AND($P36>=DATE(2027,10,1),$P36<DATE(2027,13,1)),DAY($P36)&" "&CHOOSE(MONTH($P36),"Jan","Feb","Mar","Apr","May","Jun","Jul","Aug","Sep","Oct","Nov","Dec"),"") | H36: =IF(AND($P36>=DATE(2028,1,1),$P36<DATE(2028,4,1)),DAY($P36)&" "&CHOOSE(MONTH($P36),"Jan","Feb","Mar","Apr","May","Jun","Jul","Aug","Sep","Oct","Nov","Dec"),"") | I36: =IF(AND($P36>=DATE(2028,4,1),$P36<DATE(2028,7,1)),DAY($P36)&" "&CHOOSE(MONTH($P36),"Jan","Feb","Mar","Apr","May","Jun","Jul","Aug","Sep","Oct","Nov","Dec"),"") | J36: =IF(AND($P36>=DATE(2028,7,1),$P36<DATE(2028,10,1)),DAY($P36)&" "&CHOOSE(MONTH($P36),"Jan","Feb","Mar","Apr","May","Jun","Jul","Aug","Sep","Oct","Nov","Dec"),"") | K36: =IF(AND($P36>=DATE(2028,10,1),$P36<DATE(2028,13,1)),DAY($P36)&" "&CHOOSE(MONTH($P36),"Jan","Feb","Mar","Apr","May","Jun","Jul","Aug","Sep","Oct","Nov","Dec"),"") | L36: =IF(AND($P36>=DATE(2029,1,1),$P36<DATE(2029,4,1)),DAY($P36)&" "&CHOOSE(MONTH($P36),"Jan","Feb","Mar","Apr","May","Jun","Jul","Aug","Sep","Oct","Nov","Dec"),"") | M36: =IF(AND($P36>=DATE(2029,4,1),$P36<DATE(2029,7,1)),DAY($P36)&" "&CHOOSE(MONTH($P36),"Jan","Feb","Mar","Apr","May","Jun","Jul","Aug","Sep","Oct","Nov","Dec"),"") | N36: =CHOOSE(MONTH(O36),"Jan","Feb","Mar","Apr","May","Jun","Jul","Aug","Sep","Oct","Nov","Dec")&" "&YEAR(O36)&" → "&DAY(P36)&" "&CHOOSE(MONTH(P36),"Jan","Feb","Mar","Apr","May","Jun","Jul","Aug","Sep","Oct","Nov","Dec")&" "&YEAR(P36)&" ("&((YEAR(P36)-YEAR(O36))*12+MONTH(P36)-MONTH(O36))&" months)" -> Nov 2026 → 1 Feb 2027 (3 months) | O36: =F20 -> 46327 | P36: =G20 -> 46419
B37: =B10 -> Biomass boiler/furnace retrofit package | C37: =IF(AND($P37>=DATE(2026,10,1),$P37<DATE(2026,13,1)),DAY($P37)&" "&CHOOSE(MONTH($P37),"Jan","Feb","Mar","Apr","May","Jun","Jul","Aug","Sep","Oct","Nov","Dec"),"") | D37: =IF(AND($P37>=DATE(2027,1,1),$P37<DATE(2027,4,1)),DAY($P37)&" "&CHOOSE(MONTH($P37),"Jan","Feb","Mar","Apr","May","Jun","Jul","Aug","Sep","Oct","Nov","Dec"),"") | E37: =IF(AND($P37>=DATE(2027,4,1),$P37<DATE(2027,7,1)),DAY($P37)&" "&CHOOSE(MONTH($P37),"Jan","Feb","Mar","Apr","May","Jun","Jul","Aug","Sep","Oct","Nov","Dec"),"") -> 1 Apr | F37: =IF(AND($P37>=DATE(2027,7,1),$P37<DATE(2027,10,1)),DAY($P37)&" "&CHOOSE(MONTH($P37),"Jan","Feb","Mar","Apr","May","Jun","Jul","Aug","Sep","Oct","Nov","Dec"),"") | G37: =IF(AND($P37>=DATE(2027,10,1),$P37<DATE(2027,13,1)),DAY($P37)&" "&CHOOSE(MONTH($P37),"Jan","Feb","Mar","Apr","May","Jun","Jul","Aug","Sep","Oct","Nov","Dec"),"") | H37: =IF(AND($P37>=DATE(2028,1,1),$P37<DATE(2028,4,1)),DAY($P37)&" "&CHOOSE(MONTH($P37),"Jan","Feb","Mar","Apr","May","Jun","Jul","Aug","Sep","Oct","Nov","Dec"),"") | I37: =IF(AND($P37>=DATE(2028,4,1),$P37<DATE(2028,7,1)),DAY($P37)&" "&CHOOSE(MONTH($P37),"Jan","Feb","Mar","Apr","May","Jun","Jul","Aug","Sep","Oct","Nov","Dec"),"") | J37: =IF(AND($P37>=DATE(2028,7,1),$P37<DATE(2028,10,1)),DAY($P37)&" "&CHOOSE(MONTH($P37),"Jan","Feb","Mar","Apr","May","Jun","Jul","Aug","Sep","Oct","Nov","Dec"),"") | K37: =IF(AND($P37>=DATE(2028,10,1),$P37<DATE(2028,13,1)),DAY($P37)&" "&CHOOSE(MONTH($P37),"Jan","Feb","Mar","Apr","May","Jun","Jul","Aug","Sep","Oct","Nov","Dec"),"") | L37: =IF(AND($P37>=DATE(2029,1,1),$P37<DATE(2029,4,1)),DAY($P37)&" "&CHOOSE(MONTH($P37),"Jan","Feb","Mar","Apr","May","Jun","Jul","Aug","Sep","Oct","Nov","Dec"),"") | M37: =IF(AND($P37>=DATE(2029,4,1),$P37<DATE(2029,7,1)),DAY($P37)&" "&CHOOSE(MONTH($P37),"Jan","Feb","Mar","Apr","May","Jun","Jul","Aug","Sep","Oct","Nov","Dec"),"") | N37: =CHOOSE(MONTH(O37),"Jan","Feb","Mar","Apr","May","Jun","Jul","Aug","Sep","Oct","Nov","Dec")&" "&YEAR(O37)&" → "&DAY(P37)&" "&CHOOSE(MONTH(P37),"Jan","Feb","Mar","Apr","May","Jun","Jul","Aug","Sep","Oct","Nov","Dec")&" "&YEAR(P37)&" ("&((YEAR(P37)-YEAR(O37))*12+MONTH(P37)-MONTH(O37))&" months)" -> Jan 2027 → 1 Apr 2027 (3 months) | O37: =F10 -> 46388 | P37: =G10 -> 46478
B38: =B13 -> Ash extraction & handling system | C38: =IF(AND($P38>=DATE(2026,10,1),$P38<DATE(2026,13,1)),DAY($P38)&" "&CHOOSE(MONTH($P38),"Jan","Feb","Mar","Apr","May","Jun","Jul","Aug","Sep","Oct","Nov","Dec"),"") | D38: =IF(AND($P38>=DATE(2027,1,1),$P38<DATE(2027,4,1)),DAY($P38)&" "&CHOOSE(MONTH($P38),"Jan","Feb","Mar","Apr","May","Jun","Jul","Aug","Sep","Oct","Nov","Dec"),"") | E38: =IF(AND($P38>=DATE(2027,4,1),$P38<DATE(2027,7,1)),DAY($P38)&" "&CHOOSE(MONTH($P38),"Jan","Feb","Mar","Apr","May","Jun","Jul","Aug","Sep","Oct","Nov","Dec"),"") -> 1 Apr | F38: =IF(AND($P38>=DATE(2027,7,1),$P38<DATE(2027,10,1)),DAY($P38)&" "&CHOOSE(MONTH($P38),"Jan","Feb","Mar","Apr","May","Jun","Jul","Aug","Sep","Oct","Nov","Dec"),"") | G38: =IF(AND($P38>=DATE(2027,10,1),$P38<DATE(2027,13,1)),DAY($P38)&" "&CHOOSE(MONTH($P38),"Jan","Feb","Mar","Apr","May","Jun","Jul","Aug","Sep","Oct","Nov","Dec"),"") | H38: =IF(AND($P38>=DATE(2028,1,1),$P38<DATE(2028,4,1)),DAY($P38)&" "&CHOOSE(MONTH($P38),"Jan","Feb","Mar","Apr","May","Jun","Jul","Aug","Sep","Oct","Nov","Dec"),"") | I38: =IF(AND($P38>=DATE(2028,4,1),$P38<DATE(2028,7,1)),DAY($P38)&" "&CHOOSE(MONTH($P38),"Jan","Feb","Mar","Apr","May","Jun","Jul","Aug","Sep","Oct","Nov","Dec"),"") | J38: =IF(AND($P38>=DATE(2028,7,1),$P38<DATE(2028,10,1)),DAY($P38)&" "&CHOOSE(MONTH($P38),"Jan","Feb","Mar","Apr","May","Jun","Jul","Aug","Sep","Oct","Nov","Dec"),"") | K38: =IF(AND($P38>=DATE(2028,10,1),$P38<DATE(2028,13,1)),DAY($P38)&" "&CHOOSE(MONTH($P38),"Jan","Feb","Mar","Apr","May","Jun","Jul","Aug","Sep","Oct","Nov","Dec"),"") | L38: =IF(AND($P38>=DATE(2029,1,1),$P38<DATE(2029,4,1)),DAY($P38)&" "&CHOOSE(MONTH($P38),"Jan","Feb","Mar","Apr","May","Jun","Jul","Aug","Sep","Oct","Nov","Dec"),"") | M38: =IF(AND($P38>=DATE(2029,4,1),$P38<DATE(2029,7,1)),DAY($P38)&" "&CHOOSE(MONTH($P38),"Jan","Feb","Mar","Apr","May","Jun","Jul","Aug","Sep","Oct","Nov","Dec"),"") | N38: =CHOOSE(MONTH(O38),"Jan","Feb","Mar","Apr","May","Jun","Jul","Aug","Sep","Oct","Nov","Dec")&" "&YEAR(O38)&" → "&DAY(P38)&" "&CHOOSE(MONTH(P38),"Jan","Feb","Mar","Apr","May","Jun","Jul","Aug","Sep","Oct","Nov","Dec")&" "&YEAR(P38)&" ("&((YEAR(P38)-YEAR(O38))*12+MONTH(P38)-MONTH(O38))&" months)" -> Jan 2027 → 1 Apr 2027 (3 months) | O38: =F13 -> 46388 | P38: =G13 -> 46478
B39: =B14 -> Multi-cyclone + bag filter upgrade | C39: =IF(AND($P39>=DATE(2026,10,1),$P39<DATE(2026,13,1)),DAY($P39)&" "&CHOOSE(MONTH($P39),"Jan","Feb","Mar","Apr","May","Jun","Jul","Aug","Sep","Oct","Nov","Dec"),"") | D39: =IF(AND($P39>=DATE(2027,1,1),$P39<DATE(2027,4,1)),DAY($P39)&" "&CHOOSE(MONTH($P39),"Jan","Feb","Mar","Apr","May","Jun","Jul","Aug","Sep","Oct","Nov","Dec"),"") | E39: =IF(AND($P39>=DATE(2027,4,1),$P39<DATE(2027,7,1)),DAY($P39)&" "&CHOOSE(MONTH($P39),"Jan","Feb","Mar","Apr","May","Jun","Jul","Aug","Sep","Oct","Nov","Dec"),"") -> 1 Apr | F39: =IF(AND($P39>=DATE(2027,7,1),$P39<DATE(2027,10,1)),DAY($P39)&" "&CHOOSE(MONTH($P39),"Jan","Feb","Mar","Apr","May","Jun","Jul","Aug","Sep","Oct","Nov","Dec"),"") | G39: =IF(AND($P39>=DATE(2027,10,1),$P39<DATE(2027,13,1)),DAY($P39)&" "&CHOOSE(MONTH($P39),"Jan","Feb","Mar","Apr","May","Jun","Jul","Aug","Sep","Oct","Nov","Dec"),"") | H39: =IF(AND($P39>=DATE(2028,1,1),$P39<DATE(2028,4,1)),DAY($P39)&" "&CHOOSE(MONTH($P39),"Jan","Feb","Mar","Apr","May","Jun","Jul","Aug","Sep","Oct","Nov","Dec"),"") | I39: =IF(AND($P39>=DATE(2028,4,1),$P39<DATE(2028,7,1)),DAY($P39)&" "&CHOOSE(MONTH($P39),"Jan","Feb","Mar","Apr","May","Jun","Jul","Aug","Sep","Oct","Nov","Dec"),"") | J39: =IF(AND($P39>=DATE(2028,7,1),$P39<DATE(2028,10,1)),DAY($P39)&" "&CHOOSE(MONTH($P39),"Jan","Feb","Mar","Apr","May","Jun","Jul","Aug","Sep","Oct","Nov","Dec"),"") | K39: =IF(AND($P39>=DATE(2028,10,1),$P39<DATE(2028,13,1)),DAY($P39)&" "&CHOOSE(MONTH($P39),"Jan","Feb","Mar","Apr","May","Jun","Jul","Aug","Sep","Oct","Nov","Dec"),"") | L39: =IF(AND($P39>=DATE(2029,1,1),$P39<DATE(2029,4,1)),DAY($P39)&" "&CHOOSE(MONTH($P39),"Jan","Feb","Mar","Apr","May","Jun","Jul","Aug","Sep","Oct","Nov","Dec"),"") | M39: =IF(AND($P39>=DATE(2029,4,1),$P39<DATE(2029,7,1)),DAY($P39)&" "&CHOOSE(MONTH($P39),"Jan","Feb","Mar","Apr","May","Jun","Jul","Aug","Sep","Oct","Nov","Dec"),"") | N39: =CHOOSE(MONTH(O39),"Jan","Feb","Mar","Apr","May","Jun","Jul","Aug","Sep","Oct","Nov","Dec")&" "&YEAR(O39)&" → "&DAY(P39)&" "&CHOOSE(MONTH(P39),"Jan","Feb","Mar","Apr","May","Jun","Jul","Aug","Sep","Oct","Nov","Dec")&" "&YEAR(P39)&" ("&((YEAR(P39)-YEAR(O39))*12+MONTH(P39)-MONTH(O39))&" months)" -> Jan 2027 → 1 Apr 2027 (3 months) | O39: =F14 -> 46388 | P39: =G14 -> 46478
B40: Tranche 2 (2028): efficiency upgrade, 1 item | C40: =IF(AND($P40>=DATE(2026,10,1),$P40<DATE(2026,13,1)),DAY($P40)&" "&CHOOSE(MONTH($P40),"Jan","Feb","Mar","Apr","May","Jun","Jul","Aug","Sep","Oct","Nov","Dec"),"") | D40: =IF(AND($P40>=DATE(2027,1,1),$P40<DATE(2027,4,1)),DAY($P40)&" "&CHOOSE(MONTH($P40),"Jan","Feb","Mar","Apr","May","Jun","Jul","Aug","Sep","Oct","Nov","Dec"),"") | E40: =IF(AND($P40>=DATE(2027,4,1),$P40<DATE(2027,7,1)),DAY($P40)&" "&CHOOSE(MONTH($P40),"Jan","Feb","Mar","Apr","May","Jun","Jul","Aug","Sep","Oct","Nov","Dec"),"") | F40: =IF(AND($P40>=DATE(2027,7,1),$P40<DATE(2027,10,1)),DAY($P40)&" "&CHOOSE(MONTH($P40),"Jan","Feb","Mar","Apr","May","Jun","Jul","Aug","Sep","Oct","Nov","Dec"),"") | G40: =IF(AND($P40>=DATE(2027,10,1),$P40<DATE(2027,13,1)),DAY($P40)&" "&CHOOSE(MONTH($P40),"Jan","Feb","Mar","Apr","May","Jun","Jul","Aug","Sep","Oct","Nov","Dec"),"") | H40: =IF(AND($P40>=DATE(2028,1,1),$P40<DATE(2028,4,1)),DAY($P40)&" "&CHOOSE(MONTH($P40),"Jan","Feb","Mar","Apr","May","Jun","Jul","Aug","Sep","Oct","Nov","Dec"),"") -> 1 Mar | I40: =IF(AND($P40>=DATE(2028,4,1),$P40<DATE(2028,7,1)),DAY($P40)&" "&CHOOSE(MONTH($P40),"Jan","Feb","Mar","Apr","May","Jun","Jul","Aug","Sep","Oct","Nov","Dec"),"") | J40: =IF(AND($P40>=DATE(2028,7,1),$P40<DATE(2028,10,1)),DAY($P40)&" "&CHOOSE(MONTH($P40),"Jan","Feb","Mar","Apr","May","Jun","Jul","Aug","Sep","Oct","Nov","Dec"),"") | K40: =IF(AND($P40>=DATE(2028,10,1),$P40<DATE(2028,13,1)),DAY($P40)&" "&CHOOSE(MONTH($P40),"Jan","Feb","Mar","Apr","May","Jun","Jul","Aug","Sep","Oct","Nov","Dec"),"") | L40: =IF(AND($P40>=DATE(2029,1,1),$P40<DATE(2029,4,1)),DAY($P40)&" "&CHOOSE(MONTH($P40),"Jan","Feb","Mar","Apr","May","Jun","Jul","Aug","Sep","Oct","Nov","Dec"),"") | M40: =IF(AND($P40>=DATE(2029,4,1),$P40<DATE(2029,7,1)),DAY($P40)&" "&CHOOSE(MONTH($P40),"Jan","Feb","Mar","Apr","May","Jun","Jul","Aug","Sep","Oct","Nov","Dec"),"") | N40: =CHOOSE(MONTH(O40),"Jan","Feb","Mar","Apr","May","Jun","Jul","Aug","Sep","Oct","Nov","Dec")&" "&YEAR(O40)&" → "&DAY(P40)&" "&CHOOSE(MONTH(P40),"Jan","Feb","Mar","Apr","May","Jun","Jul","Aug","Sep","Oct","Nov","Dec")&" "&YEAR(P40)&" ("&((YEAR(P40)-YEAR(O40))*12+MONTH(P40)-MONTH(O40))&" months)" -> Oct 2027 → 1 Mar 2028 (5 months) | O40: =MIN(F16) -> 46661 | P40: =MAX(G16) -> 46813
B41: =B16 -> Water treatment & condensate recovery upgrade | C41: =IF(AND($P41>=DATE(2026,10,1),$P41<DATE(2026,13,1)),DAY($P41)&" "&CHOOSE(MONTH($P41),"Jan","Feb","Mar","Apr","May","Jun","Jul","Aug","Sep","Oct","Nov","Dec"),"") | D41: =IF(AND($P41>=DATE(2027,1,1),$P41<DATE(2027,4,1)),DAY($P41)&" "&CHOOSE(MONTH($P41),"Jan","Feb","Mar","Apr","May","Jun","Jul","Aug","Sep","Oct","Nov","Dec"),"") | E41: =IF(AND($P41>=DATE(2027,4,1),$P41<DATE(2027,7,1)),DAY($P41)&" "&CHOOSE(MONTH($P41),"Jan","Feb","Mar","Apr","May","Jun","Jul","Aug","Sep","Oct","Nov","Dec"),"") | F41: =IF(AND($P41>=DATE(2027,7,1),$P41<DATE(2027,10,1)),DAY($P41)&" "&CHOOSE(MONTH($P41),"Jan","Feb","Mar","Apr","May","Jun","Jul","Aug","Sep","Oct","Nov","Dec"),"") | G41: =IF(AND($P41>=DATE(2027,10,1),$P41<DATE(2027,13,1)),DAY($P41)&" "&CHOOSE(MONTH($P41),"Jan","Feb","Mar","Apr","May","Jun","Jul","Aug","Sep","Oct","Nov","Dec"),"") | H41: =IF(AND($P41>=DATE(2028,1,1),$P41<DATE(2028,4,1)),DAY($P41)&" "&CHOOSE(MONTH($P41),"Jan","Feb","Mar","Apr","May","Jun","Jul","Aug","Sep","Oct","Nov","Dec"),"") -> 1 Mar | I41: =IF(AND($P41>=DATE(2028,4,1),$P41<DATE(2028,7,1)),DAY($P41)&" "&CHOOSE(MONTH($P41),"Jan","Feb","Mar","Apr","May","Jun","Jul","Aug","Sep","Oct","Nov","Dec"),"") | J41: =IF(AND($P41>=DATE(2028,7,1),$P41<DATE(2028,10,1)),DAY($P41)&" "&CHOOSE(MONTH($P41),"Jan","Feb","Mar","Apr","May","Jun","Jul","Aug","Sep","Oct","Nov","Dec"),"") | K41: =IF(AND($P41>=DATE(2028,10,1),$P41<DATE(2028,13,1)),DAY($P41)&" "&CHOOSE(MONTH($P41),"Jan","Feb","Mar","Apr","May","Jun","Jul","Aug","Sep","Oct","Nov","Dec"),"") | L41: =IF(AND($P41>=DATE(2029,1,1),$P41<DATE(2029,4,1)),DAY($P41)&" "&CHOOSE(MONTH($P41),"Jan","Feb","Mar","Apr","May","Jun","Jul","Aug","Sep","Oct","Nov","Dec"),"") | M41: =IF(AND($P41>=DATE(2029,4,1),$P41<DATE(2029,7,1)),DAY($P41)&" "&CHOOSE(MONTH($P41),"Jan","Feb","Mar","Apr","May","Jun","Jul","Aug","Sep","Oct","Nov","Dec"),"") | N41: =CHOOSE(MONTH(O41),"Jan","Feb","Mar","Apr","May","Jun","Jul","Aug","Sep","Oct","Nov","Dec")&" "&YEAR(O41)&" → "&DAY(P41)&" "&CHOOSE(MONTH(P41),"Jan","Feb","Mar","Apr","May","Jun","Jul","Aug","Sep","Oct","Nov","Dec")&" "&YEAR(P41)&" ("&((YEAR(P41)-YEAR(O41))*12+MONTH(P41)-MONTH(O41))&" months)" -> Oct 2027 → 1 Mar 2028 (5 months) | O41: =F16 -> 46661 | P41: =G16 -> 46813
B42: Shutdowns, risk window and buyer gates
B43: LNY 2027 shutdown: boiler tie-in | C43: =IF(AND($O43>=DATE(2026,10,1),$O43<DATE(2026,13,1)),CHOOSE(MONTH($O43),"Jan","Feb","Mar","Apr","May","Jun","Jul","Aug","Sep","Oct","Nov","Dec")&IF($P43-$O43>40,"–"&CHOOSE(MONTH($P43),"Jan","Feb","Mar","Apr","May","Jun","Jul","Aug","Sep","Oct","Nov","Dec"),""),"") | D43: =IF(AND($O43>=DATE(2027,1,1),$O43<DATE(2027,4,1)),CHOOSE(MONTH($O43),"Jan","Feb","Mar","Apr","May","Jun","Jul","Aug","Sep","Oct","Nov","Dec")&IF($P43-$O43>40,"–"&CHOOSE(MONTH($P43),"Jan","Feb","Mar","Apr","May","Jun","Jul","Aug","Sep","Oct","Nov","Dec"),""),"") -> Feb | E43: =IF(AND($O43>=DATE(2027,4,1),$O43<DATE(2027,7,1)),CHOOSE(MONTH($O43),"Jan","Feb","Mar","Apr","May","Jun","Jul","Aug","Sep","Oct","Nov","Dec")&IF($P43-$O43>40,"–"&CHOOSE(MONTH($P43),"Jan","Feb","Mar","Apr","May","Jun","Jul","Aug","Sep","Oct","Nov","Dec"),""),"") | F43: =IF(AND($O43>=DATE(2027,7,1),$O43<DATE(2027,10,1)),CHOOSE(MONTH($O43),"Jan","Feb","Mar","Apr","May","Jun","Jul","Aug","Sep","Oct","Nov","Dec")&IF($P43-$O43>40,"–"&CHOOSE(MONTH($P43),"Jan","Feb","Mar","Apr","May","Jun","Jul","Aug","Sep","Oct","Nov","Dec"),""),"") | G43: =IF(AND($O43>=DATE(2027,10,1),$O43<DATE(2027,13,1)),CHOOSE(MONTH($O43),"Jan","Feb","Mar","Apr","May","Jun","Jul","Aug","Sep","Oct","Nov","Dec")&IF($P43-$O43>40,"–"&CHOOSE(MONTH($P43),"Jan","Feb","Mar","Apr","May","Jun","Jul","Aug","Sep","Oct","Nov","Dec"),""),"") | H43: =IF(AND($O43>=DATE(2028,1,1),$O43<DATE(2028,4,1)),CHOOSE(MONTH($O43),"Jan","Feb","Mar","Apr","May","Jun","Jul","Aug","Sep","Oct","Nov","Dec")&IF($P43-$O43>40,"–"&CHOOSE(MONTH($P43),"Jan","Feb","Mar","Apr","May","Jun","Jul","Aug","Sep","Oct","Nov","Dec"),""),"") | I43: =IF(AND($O43>=DATE(2028,4,1),$O43<DATE(2028,7,1)),CHOOSE(MONTH($O43),"Jan","Feb","Mar","Apr","May","Jun","Jul","Aug","Sep","Oct","Nov","Dec")&IF($P43-$O43>40,"–"&CHOOSE(MONTH($P43),"Jan","Feb","Mar","Apr","May","Jun","Jul","Aug","Sep","Oct","Nov","Dec"),""),"") | J43: =IF(AND($O43>=DATE(2028,7,1),$O43<DATE(2028,10,1)),CHOOSE(MONTH($O43),"Jan","Feb","Mar","Apr","May","Jun","Jul","Aug","Sep","Oct","Nov","Dec")&IF($P43-$O43>40,"–"&CHOOSE(MONTH($P43),"Jan","Feb","Mar","Apr","May","Jun","Jul","Aug","Sep","Oct","Nov","Dec"),""),"") | K43: =IF(AND($O43>=DATE(2028,10,1),$O43<DATE(2028,13,1)),CHOOSE(MONTH($O43),"Jan","Feb","Mar","Apr","May","Jun","Jul","Aug","Sep","Oct","Nov","Dec")&IF($P43-$O43>40,"–"&CHOOSE(MONTH($P43),"Jan","Feb","Mar","Apr","May","Jun","Jul","Aug","Sep","Oct","Nov","Dec"),""),"") | L43: =IF(AND($O43>=DATE(2029,1,1),$O43<DATE(2029,4,1)),CHOOSE(MONTH($O43),"Jan","Feb","Mar","Apr","May","Jun","Jul","Aug","Sep","Oct","Nov","Dec")&IF($P43-$O43>40,"–"&CHOOSE(MONTH($P43),"Jan","Feb","Mar","Apr","May","Jun","Jul","Aug","Sep","Oct","Nov","Dec"),""),"") | M43: =IF(AND($O43>=DATE(2029,4,1),$O43<DATE(2029,7,1)),CHOOSE(MONTH($O43),"Jan","Feb","Mar","Apr","May","Jun","Jul","Aug","Sep","Oct","Nov","Dec")&IF($P43-$O43>40,"–"&CHOOSE(MONTH($P43),"Jan","Feb","Mar","Apr","May","Jun","Jul","Aug","Sep","Oct","Nov","Dec"),""),"") | N43: =CHOOSE(MONTH(O43),"Jan","Feb","Mar","Apr","May","Jun","Jul","Aug","Sep","Oct","Nov","Dec")&" "&YEAR(O43)&IF(OR(MONTH(P43)<>MONTH(O43),YEAR(P43)<>YEAR(O43))," to "&CHOOSE(MONTH(P43),"Jan","Feb","Mar","Apr","May","Jun","Jul","Aug","Sep","Oct","Nov","Dec")&" "&YEAR(P43),"")&" (Logistics Cost 2027, Feb-27)" -> Feb 2027 (Logistics Cost 2027, Feb-27) | O43: 46419 | P43: 46419
B44: Performance test passed: biomass firing starts | C44: =IF(AND($O44>=DATE(2026,10,1),$O44<DATE(2026,13,1)),CHOOSE(MONTH($O44),"Jan","Feb","Mar","Apr","May","Jun","Jul","Aug","Sep","Oct","Nov","Dec")&IF($P44-$O44>40,"–"&CHOOSE(MONTH($P44),"Jan","Feb","Mar","Apr","May","Jun","Jul","Aug","Sep","Oct","Nov","Dec"),""),"") | D44: =IF(AND($O44>=DATE(2027,1,1),$O44<DATE(2027,4,1)),CHOOSE(MONTH($O44),"Jan","Feb","Mar","Apr","May","Jun","Jul","Aug","Sep","Oct","Nov","Dec")&IF($P44-$O44>40,"–"&CHOOSE(MONTH($P44),"Jan","Feb","Mar","Apr","May","Jun","Jul","Aug","Sep","Oct","Nov","Dec"),""),"") | E44: =IF(AND($O44>=DATE(2027,4,1),$O44<DATE(2027,7,1)),CHOOSE(MONTH($O44),"Jan","Feb","Mar","Apr","May","Jun","Jul","Aug","Sep","Oct","Nov","Dec")&IF($P44-$O44>40,"–"&CHOOSE(MONTH($P44),"Jan","Feb","Mar","Apr","May","Jun","Jul","Aug","Sep","Oct","Nov","Dec"),""),"") -> Apr | F44: =IF(AND($O44>=DATE(2027,7,1),$O44<DATE(2027,10,1)),CHOOSE(MONTH($O44),"Jan","Feb","Mar","Apr","May","Jun","Jul","Aug","Sep","Oct","Nov","Dec")&IF($P44-$O44>40,"–"&CHOOSE(MONTH($P44),"Jan","Feb","Mar","Apr","May","Jun","Jul","Aug","Sep","Oct","Nov","Dec"),""),"") | G44: =IF(AND($O44>=DATE(2027,10,1),$O44<DATE(2027,13,1)),CHOOSE(MONTH($O44),"Jan","Feb","Mar","Apr","May","Jun","Jul","Aug","Sep","Oct","Nov","Dec")&IF($P44-$O44>40,"–"&CHOOSE(MONTH($P44),"Jan","Feb","Mar","Apr","May","Jun","Jul","Aug","Sep","Oct","Nov","Dec"),""),"") | H44: =IF(AND($O44>=DATE(2028,1,1),$O44<DATE(2028,4,1)),CHOOSE(MONTH($O44),"Jan","Feb","Mar","Apr","May","Jun","Jul","Aug","Sep","Oct","Nov","Dec")&IF($P44-$O44>40,"–"&CHOOSE(MONTH($P44),"Jan","Feb","Mar","Apr","May","Jun","Jul","Aug","Sep","Oct","Nov","Dec"),""),"") | I44: =IF(AND($O44>=DATE(2028,4,1),$O44<DATE(2028,7,1)),CHOOSE(MONTH($O44),"Jan","Feb","Mar","Apr","May","Jun","Jul","Aug","Sep","Oct","Nov","Dec")&IF($P44-$O44>40,"–"&CHOOSE(MONTH($P44),"Jan","Feb","Mar","Apr","May","Jun","Jul","Aug","Sep","Oct","Nov","Dec"),""),"") | J44: =IF(AND($O44>=DATE(2028,7,1),$O44<DATE(2028,10,1)),CHOOSE(MONTH($O44),"Jan","Feb","Mar","Apr","May","Jun","Jul","Aug","Sep","Oct","Nov","Dec")&IF($P44-$O44>40,"–"&CHOOSE(MONTH($P44),"Jan","Feb","Mar","Apr","May","Jun","Jul","Aug","Sep","Oct","Nov","Dec"),""),"") | K44: =IF(AND($O44>=DATE(2028,10,1),$O44<DATE(2028,13,1)),CHOOSE(MONTH($O44),"Jan","Feb","Mar","Apr","May","Jun","Jul","Aug","Sep","Oct","Nov","Dec")&IF($P44-$O44>40,"–"&CHOOSE(MONTH($P44),"Jan","Feb","Mar","Apr","May","Jun","Jul","Aug","Sep","Oct","Nov","Dec"),""),"") | L44: =IF(AND($O44>=DATE(2029,1,1),$O44<DATE(2029,4,1)),CHOOSE(MONTH($O44),"Jan","Feb","Mar","Apr","May","Jun","Jul","Aug","Sep","Oct","Nov","Dec")&IF($P44-$O44>40,"–"&CHOOSE(MONTH($P44),"Jan","Feb","Mar","Apr","May","Jun","Jul","Aug","Sep","Oct","Nov","Dec"),""),"") | M44: =IF(AND($O44>=DATE(2029,4,1),$O44<DATE(2029,7,1)),CHOOSE(MONTH($O44),"Jan","Feb","Mar","Apr","May","Jun","Jul","Aug","Sep","Oct","Nov","Dec")&IF($P44-$O44>40,"–"&CHOOSE(MONTH($P44),"Jan","Feb","Mar","Apr","May","Jun","Jul","Aug","Sep","Oct","Nov","Dec"),""),"") | N44: =CHOOSE(MONTH(O44),"Jan","Feb","Mar","Apr","May","Jun","Jul","Aug","Sep","Oct","Nov","Dec")&" "&YEAR(O44)&IF(OR(MONTH(P44)<>MONTH(O44),YEAR(P44)<>YEAR(O44))," to "&CHOOSE(MONTH(P44),"Jan","Feb","Mar","Apr","May","Jun","Jul","Aug","Sep","Oct","Nov","Dec")&" "&YEAR(P44),"")&" (Tranche 1 gate, input below)" -> Apr 2027 (Tranche 1 gate, input below) | O44: =$C$117 -> 46478 | P44: =$C$117 -> 46478
B45: Stress window: 8-week commissioning slip (R14) | C45: =IF(AND($O45>=DATE(2026,10,1),$O45<DATE(2026,13,1)),CHOOSE(MONTH($O45),"Jan","Feb","Mar","Apr","May","Jun","Jul","Aug","Sep","Oct","Nov","Dec")&IF($P45-$O45>40,"–"&CHOOSE(MONTH($P45),"Jan","Feb","Mar","Apr","May","Jun","Jul","Aug","Sep","Oct","Nov","Dec"),""),"") | D45: =IF(AND($O45>=DATE(2027,1,1),$O45<DATE(2027,4,1)),CHOOSE(MONTH($O45),"Jan","Feb","Mar","Apr","May","Jun","Jul","Aug","Sep","Oct","Nov","Dec")&IF($P45-$O45>40,"–"&CHOOSE(MONTH($P45),"Jan","Feb","Mar","Apr","May","Jun","Jul","Aug","Sep","Oct","Nov","Dec"),""),"") | E45: =IF(AND($O45>=DATE(2027,4,1),$O45<DATE(2027,7,1)),CHOOSE(MONTH($O45),"Jan","Feb","Mar","Apr","May","Jun","Jul","Aug","Sep","Oct","Nov","Dec")&IF($P45-$O45>40,"–"&CHOOSE(MONTH($P45),"Jan","Feb","Mar","Apr","May","Jun","Jul","Aug","Sep","Oct","Nov","Dec"),""),"") -> Apr–May | F45: =IF(AND($O45>=DATE(2027,7,1),$O45<DATE(2027,10,1)),CHOOSE(MONTH($O45),"Jan","Feb","Mar","Apr","May","Jun","Jul","Aug","Sep","Oct","Nov","Dec")&IF($P45-$O45>40,"–"&CHOOSE(MONTH($P45),"Jan","Feb","Mar","Apr","May","Jun","Jul","Aug","Sep","Oct","Nov","Dec"),""),"") | G45: =IF(AND($O45>=DATE(2027,10,1),$O45<DATE(2027,13,1)),CHOOSE(MONTH($O45),"Jan","Feb","Mar","Apr","May","Jun","Jul","Aug","Sep","Oct","Nov","Dec")&IF($P45-$O45>40,"–"&CHOOSE(MONTH($P45),"Jan","Feb","Mar","Apr","May","Jun","Jul","Aug","Sep","Oct","Nov","Dec"),""),"") | H45: =IF(AND($O45>=DATE(2028,1,1),$O45<DATE(2028,4,1)),CHOOSE(MONTH($O45),"Jan","Feb","Mar","Apr","May","Jun","Jul","Aug","Sep","Oct","Nov","Dec")&IF($P45-$O45>40,"–"&CHOOSE(MONTH($P45),"Jan","Feb","Mar","Apr","May","Jun","Jul","Aug","Sep","Oct","Nov","Dec"),""),"") | I45: =IF(AND($O45>=DATE(2028,4,1),$O45<DATE(2028,7,1)),CHOOSE(MONTH($O45),"Jan","Feb","Mar","Apr","May","Jun","Jul","Aug","Sep","Oct","Nov","Dec")&IF($P45-$O45>40,"–"&CHOOSE(MONTH($P45),"Jan","Feb","Mar","Apr","May","Jun","Jul","Aug","Sep","Oct","Nov","Dec"),""),"") | J45: =IF(AND($O45>=DATE(2028,7,1),$O45<DATE(2028,10,1)),CHOOSE(MONTH($O45),"Jan","Feb","Mar","Apr","May","Jun","Jul","Aug","Sep","Oct","Nov","Dec")&IF($P45-$O45>40,"–"&CHOOSE(MONTH($P45),"Jan","Feb","Mar","Apr","May","Jun","Jul","Aug","Sep","Oct","Nov","Dec"),""),"") | K45: =IF(AND($O45>=DATE(2028,10,1),$O45<DATE(2028,13,1)),CHOOSE(MONTH($O45),"Jan","Feb","Mar","Apr","May","Jun","Jul","Aug","Sep","Oct","Nov","Dec")&IF($P45-$O45>40,"–"&CHOOSE(MONTH($P45),"Jan","Feb","Mar","Apr","May","Jun","Jul","Aug","Sep","Oct","Nov","Dec"),""),"") | L45: =IF(AND($O45>=DATE(2029,1,1),$O45<DATE(2029,4,1)),CHOOSE(MONTH($O45),"Jan","Feb","Mar","Apr","May","Jun","Jul","Aug","Sep","Oct","Nov","Dec")&IF($P45-$O45>40,"–"&CHOOSE(MONTH($P45),"Jan","Feb","Mar","Apr","May","Jun","Jul","Aug","Sep","Oct","Nov","Dec"),""),"") | M45: =IF(AND($O45>=DATE(2029,4,1),$O45<DATE(2029,7,1)),CHOOSE(MONTH($O45),"Jan","Feb","Mar","Apr","May","Jun","Jul","Aug","Sep","Oct","Nov","Dec")&IF($P45-$O45>40,"–"&CHOOSE(MONTH($P45),"Jan","Feb","Mar","Apr","May","Jun","Jul","Aug","Sep","Oct","Nov","Dec"),""),"") | N45: =CHOOSE(MONTH(O45),"Jan","Feb","Mar","Apr","May","Jun","Jul","Aug","Sep","Oct","Nov","Dec")&" "&YEAR(O45)&IF(OR(MONTH(P45)<>MONTH(O45),YEAR(P45)<>YEAR(O45))," to "&CHOOSE(MONTH(P45),"Jan","Feb","Mar","Apr","May","Jun","Jul","Aug","Sep","Oct","Nov","Dec")&" "&YEAR(P45),"")&" (R14; cap still met)" -> Apr 2027 to May 2027 (R14; cap still met) | O45: =$C$117 -> 46478 | P45: =$C$117+7*$C$118 -> 46534
B46: LSC verification of 2027 CO2e | C46: =IF(AND($O46>=DATE(2026,10,1),$O46<DATE(2026,13,1)),CHOOSE(MONTH($O46),"Jan","Feb","Mar","Apr","May","Jun","Jul","Aug","Sep","Oct","Nov","Dec")&IF($P46-$O46>40,"–"&CHOOSE(MONTH($P46),"Jan","Feb","Mar","Apr","May","Jun","Jul","Aug","Sep","Oct","Nov","Dec"),""),"") | D46: =IF(AND($O46>=DATE(2027,1,1),$O46<DATE(2027,4,1)),CHOOSE(MONTH($O46),"Jan","Feb","Mar","Apr","May","Jun","Jul","Aug","Sep","Oct","Nov","Dec")&IF($P46-$O46>40,"–"&CHOOSE(MONTH($P46),"Jan","Feb","Mar","Apr","May","Jun","Jul","Aug","Sep","Oct","Nov","Dec"),""),"") | E46: =IF(AND($O46>=DATE(2027,4,1),$O46<DATE(2027,7,1)),CHOOSE(MONTH($O46),"Jan","Feb","Mar","Apr","May","Jun","Jul","Aug","Sep","Oct","Nov","Dec")&IF($P46-$O46>40,"–"&CHOOSE(MONTH($P46),"Jan","Feb","Mar","Apr","May","Jun","Jul","Aug","Sep","Oct","Nov","Dec"),""),"") | F46: =IF(AND($O46>=DATE(2027,7,1),$O46<DATE(2027,10,1)),CHOOSE(MONTH($O46),"Jan","Feb","Mar","Apr","May","Jun","Jul","Aug","Sep","Oct","Nov","Dec")&IF($P46-$O46>40,"–"&CHOOSE(MONTH($P46),"Jan","Feb","Mar","Apr","May","Jun","Jul","Aug","Sep","Oct","Nov","Dec"),""),"") | G46: =IF(AND($O46>=DATE(2027,10,1),$O46<DATE(2027,13,1)),CHOOSE(MONTH($O46),"Jan","Feb","Mar","Apr","May","Jun","Jul","Aug","Sep","Oct","Nov","Dec")&IF($P46-$O46>40,"–"&CHOOSE(MONTH($P46),"Jan","Feb","Mar","Apr","May","Jun","Jul","Aug","Sep","Oct","Nov","Dec"),""),"") | H46: =IF(AND($O46>=DATE(2028,1,1),$O46<DATE(2028,4,1)),CHOOSE(MONTH($O46),"Jan","Feb","Mar","Apr","May","Jun","Jul","Aug","Sep","Oct","Nov","Dec")&IF($P46-$O46>40,"–"&CHOOSE(MONTH($P46),"Jan","Feb","Mar","Apr","May","Jun","Jul","Aug","Sep","Oct","Nov","Dec"),""),"") -> Jan–Mar | I46: =IF(AND($O46>=DATE(2028,4,1),$O46<DATE(2028,7,1)),CHOOSE(MONTH($O46),"Jan","Feb","Mar","Apr","May","Jun","Jul","Aug","Sep","Oct","Nov","Dec")&IF($P46-$O46>40,"–"&CHOOSE(MONTH($P46),"Jan","Feb","Mar","Apr","May","Jun","Jul","Aug","Sep","Oct","Nov","Dec"),""),"") | J46: =IF(AND($O46>=DATE(2028,7,1),$O46<DATE(2028,10,1)),CHOOSE(MONTH($O46),"Jan","Feb","Mar","Apr","May","Jun","Jul","Aug","Sep","Oct","Nov","Dec")&IF($P46-$O46>40,"–"&CHOOSE(MONTH($P46),"Jan","Feb","Mar","Apr","May","Jun","Jul","Aug","Sep","Oct","Nov","Dec"),""),"") | K46: =IF(AND($O46>=DATE(2028,10,1),$O46<DATE(2028,13,1)),CHOOSE(MONTH($O46),"Jan","Feb","Mar","Apr","May","Jun","Jul","Aug","Sep","Oct","Nov","Dec")&IF($P46-$O46>40,"–"&CHOOSE(MONTH($P46),"Jan","Feb","Mar","Apr","May","Jun","Jul","Aug","Sep","Oct","Nov","Dec"),""),"") | L46: =IF(AND($O46>=DATE(2029,1,1),$O46<DATE(2029,4,1)),CHOOSE(MONTH($O46),"Jan","Feb","Mar","Apr","May","Jun","Jul","Aug","Sep","Oct","Nov","Dec")&IF($P46-$O46>40,"–"&CHOOSE(MONTH($P46),"Jan","Feb","Mar","Apr","May","Jun","Jul","Aug","Sep","Oct","Nov","Dec"),""),"") | M46: =IF(AND($O46>=DATE(2029,4,1),$O46<DATE(2029,7,1)),CHOOSE(MONTH($O46),"Jan","Feb","Mar","Apr","May","Jun","Jul","Aug","Sep","Oct","Nov","Dec")&IF($P46-$O46>40,"–"&CHOOSE(MONTH($P46),"Jan","Feb","Mar","Apr","May","Jun","Jul","Aug","Sep","Oct","Nov","Dec"),""),"") | N46: =CHOOSE(MONTH(O46),"Jan","Feb","Mar","Apr","May","Jun","Jul","Aug","Sep","Oct","Nov","Dec")&" "&YEAR(O46)&IF(OR(MONTH(P46)<>MONTH(O46),YEAR(P46)<>YEAR(O46))," to "&CHOOSE(MONTH(P46),"Jan","Feb","Mar","Apr","May","Jun","Jul","Aug","Sep","Oct","Nov","Dec")&" "&YEAR(P46),"")&" (Emission Target B18–B19)" -> Jan 2028 to Mar 2028 (Emission Target B18–B19) | O46: 46753 | P46: 46813
B47: LNY 2028 shutdown: condensate recovery tie-in | C47: =IF(AND($O47>=DATE(2026,10,1),$O47<DATE(2026,13,1)),CHOOSE(MONTH($O47),"Jan","Feb","Mar","Apr","May","Jun","Jul","Aug","Sep","Oct","Nov","Dec")&IF($P47-$O47>40,"–"&CHOOSE(MONTH($P47),"Jan","Feb","Mar","Apr","May","Jun","Jul","Aug","Sep","Oct","Nov","Dec"),""),"") | D47: =IF(AND($O47>=DATE(2027,1,1),$O47<DATE(2027,4,1)),CHOOSE(MONTH($O47),"Jan","Feb","Mar","Apr","May","Jun","Jul","Aug","Sep","Oct","Nov","Dec")&IF($P47-$O47>40,"–"&CHOOSE(MONTH($P47),"Jan","Feb","Mar","Apr","May","Jun","Jul","Aug","Sep","Oct","Nov","Dec"),""),"") | E47: =IF(AND($O47>=DATE(2027,4,1),$O47<DATE(2027,7,1)),CHOOSE(MONTH($O47),"Jan","Feb","Mar","Apr","May","Jun","Jul","Aug","Sep","Oct","Nov","Dec")&IF($P47-$O47>40,"–"&CHOOSE(MONTH($P47),"Jan","Feb","Mar","Apr","May","Jun","Jul","Aug","Sep","Oct","Nov","Dec"),""),"") | F47: =IF(AND($O47>=DATE(2027,7,1),$O47<DATE(2027,10,1)),CHOOSE(MONTH($O47),"Jan","Feb","Mar","Apr","May","Jun","Jul","Aug","Sep","Oct","Nov","Dec")&IF($P47-$O47>40,"–"&CHOOSE(MONTH($P47),"Jan","Feb","Mar","Apr","May","Jun","Jul","Aug","Sep","Oct","Nov","Dec"),""),"") | G47: =IF(AND($O47>=DATE(2027,10,1),$O47<DATE(2027,13,1)),CHOOSE(MONTH($O47),"Jan","Feb","Mar","Apr","May","Jun","Jul","Aug","Sep","Oct","Nov","Dec")&IF($P47-$O47>40,"–"&CHOOSE(MONTH($P47),"Jan","Feb","Mar","Apr","May","Jun","Jul","Aug","Sep","Oct","Nov","Dec"),""),"") | H47: =IF(AND($O47>=DATE(2028,1,1),$O47<DATE(2028,4,1)),CHOOSE(MONTH($O47),"Jan","Feb","Mar","Apr","May","Jun","Jul","Aug","Sep","Oct","Nov","Dec")&IF($P47-$O47>40,"–"&CHOOSE(MONTH($P47),"Jan","Feb","Mar","Apr","May","Jun","Jul","Aug","Sep","Oct","Nov","Dec"),""),"") -> Feb | I47: =IF(AND($O47>=DATE(2028,4,1),$O47<DATE(2028,7,1)),CHOOSE(MONTH($O47),"Jan","Feb","Mar","Apr","May","Jun","Jul","Aug","Sep","Oct","Nov","Dec")&IF($P47-$O47>40,"–"&CHOOSE(MONTH($P47),"Jan","Feb","Mar","Apr","May","Jun","Jul","Aug","Sep","Oct","Nov","Dec"),""),"") | J47: =IF(AND($O47>=DATE(2028,7,1),$O47<DATE(2028,10,1)),CHOOSE(MONTH($O47),"Jan","Feb","Mar","Apr","May","Jun","Jul","Aug","Sep","Oct","Nov","Dec")&IF($P47-$O47>40,"–"&CHOOSE(MONTH($P47),"Jan","Feb","Mar","Apr","May","Jun","Jul","Aug","Sep","Oct","Nov","Dec"),""),"") | K47: =IF(AND($O47>=DATE(2028,10,1),$O47<DATE(2028,13,1)),CHOOSE(MONTH($O47),"Jan","Feb","Mar","Apr","May","Jun","Jul","Aug","Sep","Oct","Nov","Dec")&IF($P47-$O47>40,"–"&CHOOSE(MONTH($P47),"Jan","Feb","Mar","Apr","May","Jun","Jul","Aug","Sep","Oct","Nov","Dec"),""),"") | L47: =IF(AND($O47>=DATE(2029,1,1),$O47<DATE(2029,4,1)),CHOOSE(MONTH($O47),"Jan","Feb","Mar","Apr","May","Jun","Jul","Aug","Sep","Oct","Nov","Dec")&IF($P47-$O47>40,"–"&CHOOSE(MONTH($P47),"Jan","Feb","Mar","Apr","May","Jun","Jul","Aug","Sep","Oct","Nov","Dec"),""),"") | M47: =IF(AND($O47>=DATE(2029,4,1),$O47<DATE(2029,7,1)),CHOOSE(MONTH($O47),"Jan","Feb","Mar","Apr","May","Jun","Jul","Aug","Sep","Oct","Nov","Dec")&IF($P47-$O47>40,"–"&CHOOSE(MONTH($P47),"Jan","Feb","Mar","Apr","May","Jun","Jul","Aug","Sep","Oct","Nov","Dec"),""),"") | N47: =CHOOSE(MONTH(O47),"Jan","Feb","Mar","Apr","May","Jun","Jul","Aug","Sep","Oct","Nov","Dec")&" "&YEAR(O47)&IF(OR(MONTH(P47)<>MONTH(O47),YEAR(P47)<>YEAR(O47))," to "&CHOOSE(MONTH(P47),"Jan","Feb","Mar","Apr","May","Jun","Jul","Aug","Sep","Oct","Nov","Dec")&" "&YEAR(P47),"")&" (Tranche 2 gate)" -> Feb 2028 (Tranche 2 gate) | O47: 46784 | P47: 46784
B48: LSC verification of 2028 CO2e | C48: =IF(AND($O48>=DATE(2026,10,1),$O48<DATE(2026,13,1)),CHOOSE(MONTH($O48),"Jan","Feb","Mar","Apr","May","Jun","Jul","Aug","Sep","Oct","Nov","Dec")&IF($P48-$O48>40,"–"&CHOOSE(MONTH($P48),"Jan","Feb","Mar","Apr","May","Jun","Jul","Aug","Sep","Oct","Nov","Dec"),""),"") | D48: =IF(AND($O48>=DATE(2027,1,1),$O48<DATE(2027,4,1)),CHOOSE(MONTH($O48),"Jan","Feb","Mar","Apr","May","Jun","Jul","Aug","Sep","Oct","Nov","Dec")&IF($P48-$O48>40,"–"&CHOOSE(MONTH($P48),"Jan","Feb","Mar","Apr","May","Jun","Jul","Aug","Sep","Oct","Nov","Dec"),""),"") | E48: =IF(AND($O48>=DATE(2027,4,1),$O48<DATE(2027,7,1)),CHOOSE(MONTH($O48),"Jan","Feb","Mar","Apr","May","Jun","Jul","Aug","Sep","Oct","Nov","Dec")&IF($P48-$O48>40,"–"&CHOOSE(MONTH($P48),"Jan","Feb","Mar","Apr","May","Jun","Jul","Aug","Sep","Oct","Nov","Dec"),""),"") | F48: =IF(AND($O48>=DATE(2027,7,1),$O48<DATE(2027,10,1)),CHOOSE(MONTH($O48),"Jan","Feb","Mar","Apr","May","Jun","Jul","Aug","Sep","Oct","Nov","Dec")&IF($P48-$O48>40,"–"&CHOOSE(MONTH($P48),"Jan","Feb","Mar","Apr","May","Jun","Jul","Aug","Sep","Oct","Nov","Dec"),""),"") | G48: =IF(AND($O48>=DATE(2027,10,1),$O48<DATE(2027,13,1)),CHOOSE(MONTH($O48),"Jan","Feb","Mar","Apr","May","Jun","Jul","Aug","Sep","Oct","Nov","Dec")&IF($P48-$O48>40,"–"&CHOOSE(MONTH($P48),"Jan","Feb","Mar","Apr","May","Jun","Jul","Aug","Sep","Oct","Nov","Dec"),""),"") | H48: =IF(AND($O48>=DATE(2028,1,1),$O48<DATE(2028,4,1)),CHOOSE(MONTH($O48),"Jan","Feb","Mar","Apr","May","Jun","Jul","Aug","Sep","Oct","Nov","Dec")&IF($P48-$O48>40,"–"&CHOOSE(MONTH($P48),"Jan","Feb","Mar","Apr","May","Jun","Jul","Aug","Sep","Oct","Nov","Dec"),""),"") | I48: =IF(AND($O48>=DATE(2028,4,1),$O48<DATE(2028,7,1)),CHOOSE(MONTH($O48),"Jan","Feb","Mar","Apr","May","Jun","Jul","Aug","Sep","Oct","Nov","Dec")&IF($P48-$O48>40,"–"&CHOOSE(MONTH($P48),"Jan","Feb","Mar","Apr","May","Jun","Jul","Aug","Sep","Oct","Nov","Dec"),""),"") | J48: =IF(AND($O48>=DATE(2028,7,1),$O48<DATE(2028,10,1)),CHOOSE(MONTH($O48),"Jan","Feb","Mar","Apr","May","Jun","Jul","Aug","Sep","Oct","Nov","Dec")&IF($P48-$O48>40,"–"&CHOOSE(MONTH($P48),"Jan","Feb","Mar","Apr","May","Jun","Jul","Aug","Sep","Oct","Nov","Dec"),""),"") | K48: =IF(AND($O48>=DATE(2028,10,1),$O48<DATE(2028,13,1)),CHOOSE(MONTH($O48),"Jan","Feb","Mar","Apr","May","Jun","Jul","Aug","Sep","Oct","Nov","Dec")&IF($P48-$O48>40,"–"&CHOOSE(MONTH($P48),"Jan","Feb","Mar","Apr","May","Jun","Jul","Aug","Sep","Oct","Nov","Dec"),""),"") | L48: =IF(AND($O48>=DATE(2029,1,1),$O48<DATE(2029,4,1)),CHOOSE(MONTH($O48),"Jan","Feb","Mar","Apr","May","Jun","Jul","Aug","Sep","Oct","Nov","Dec")&IF($P48-$O48>40,"–"&CHOOSE(MONTH($P48),"Jan","Feb","Mar","Apr","May","Jun","Jul","Aug","Sep","Oct","Nov","Dec"),""),"") -> Jan–Mar | M48: =IF(AND($O48>=DATE(2029,4,1),$O48<DATE(2029,7,1)),CHOOSE(MONTH($O48),"Jan","Feb","Mar","Apr","May","Jun","Jul","Aug","Sep","Oct","Nov","Dec")&IF($P48-$O48>40,"–"&CHOOSE(MONTH($P48),"Jan","Feb","Mar","Apr","May","Jun","Jul","Aug","Sep","Oct","Nov","Dec"),""),"") | N48: =CHOOSE(MONTH(O48),"Jan","Feb","Mar","Apr","May","Jun","Jul","Aug","Sep","Oct","Nov","Dec")&" "&YEAR(O48)&IF(OR(MONTH(P48)<>MONTH(O48),YEAR(P48)<>YEAR(O48))," to "&CHOOSE(MONTH(P48),"Jan","Feb","Mar","Apr","May","Jun","Jul","Aug","Sep","Oct","Nov","Dec")&" "&YEAR(P48),"")&" (Emission Target B18–B19)" -> Jan 2029 to Mar 2029 (Emission Target B18–B19) | O48: 47119 | P48: 47178
B49: Legend | D49: Works window (contracting, delivery, installation, tie-in) | G49: Commissioning quarter (label = in-service date) | J49: In service (continues to 2031) | M49: Shutdown, risk window or buyer gate (label = months)
B51: Operating fuel mix and CO2e compliance against both buyer caps (absolute tCO2e and kgCO2e/GJ)
B52: Metric | C52: 2026 | D52: 2027 | E52: 2028 | F52: 2029 | G52: 2030 | H52: 2031
B53: Volume and heat
B54: Realized sales volume (pcs) | C54: ='Sales Forecast & Case 2A KPI'!C21 -> 5020000 | D54: ='Task 2_Conversion & Forecast'!D19 -> 5622400 | E54: ='Task 2_Conversion & Forecast'!E19 -> 6920572 | F54: ='Task 2_Conversion & Forecast'!F19 -> 8650715 | G54: ='Task 2_Conversion & Forecast'!G19 -> 7656804 | H54: ='Task 2_Conversion & Forecast'!H19 -> 6125443.2
B55: Useful heat demand (GJ) | C55: =C54*$C$111 -> 300000 | D55: =D54*$C$111 -> 336000 | E55: =E54*$C$111 -> 413580 | F55: =F54*$C$111 -> 516975 | G55: =G54*$C$111 -> 457577.93 | H55: =H54*$C$111 -> 366062.34
B56: Heat index vs 2026 (hand-off to Task 3) | C56: =C55/$C$109 -> 1 | D56: =D55/$C$109 -> 1.12 | E56: =E55/$C$109 -> 1.3786 | F56: =F55/$C$109 -> 1.72325 | G56: =G55/$C$109 -> 1.5252598 | H56: =H55/$C$109 -> 1.2202078
B57: Buyer caps (Emission Target)
B58: Maximum annual CO2e (t) | C58: ='Emission Target'!D6 -> 28380 | D58: ='Emission Target'!D7 -> 24123 | E58: ='Emission Target'!D8 -> 19866 | F58: ='Emission Target'!D9 -> 15609 | G58: ='Emission Target'!D10 -> 12771 | H58: ='Emission Target'!D11 -> 10216.8
B59: Maximum CO2e intensity (kg/GJ) | C59: ='Emission Target'!E6 -> 94.6 | D59: ='Emission Target'!E7 -> 80.41 | E59: ='Emission Target'!E8 -> 66.22 | F59: ='Emission Target'!E9 -> 52.03 | G59: ='Emission Target'!E10 -> 42.57 | H59: ='Emission Target'!E11 -> 34.056
B60: Operating mix decision
B61: Share of year biomass system in service | C61: 0 | D61: =MAX(0,MIN(1,(DATE(2028,1,1)-$C$117)/365)) -> 0.75342466 | E61: 1 | F61: 1 | G61: 1 | H61: 1
B62: Same, under an 8-week slip (R14) | D62: =MAX(0,MIN(1,(DATE(2028,1,1)-($C$117+7*$C$118))/365)) -> 0.6
B63: Minimum annual biomass share (cap with 5% buffer) | D63: =MAX(0,($C$112-(1-$C$119)*MIN(D58*1000/D55,D59))/($C$112-$C$116)) -> 0.30871449 | E63: =MAX(0,($C$112-(1-$C$119)*MIN(E58*1000/E55,E59))/($C$112-$C$116)) -> 0.572719 | F63: =MAX(0,($C$112-(1-$C$119)*MIN(F58*1000/F55,F59))/($C$112-$C$116)) -> 0.77095553 | G63: =MAX(0,($C$112-(1-$C$119)*MIN(G58*1000/G55,G59))/($C$112-$C$116)) -> 0.79632164 | H63: =MAX(0,($C$112-(1-$C$119)*MIN(H58*1000/H55,H59))/($C$112-$C$116)) -> 0.79632164
B64: Operating biomass share while in service (decision) | C64: 0 | D64: =MIN(1,CEILING(ROUND(MAX(D63/D61,MAX(0,($C$112-D58*1000/D55)/($C$112-$C$116))/D62),6),$C$120)) -> 0.45 | E64: =MIN(1,CEILING(ROUND(E63/E61,6),$C$120)) -> 0.6 | F64: =MIN(1,CEILING(ROUND(F63/F61,6),$C$120)) -> 0.8 | G64: =MIN(1,CEILING(ROUND(G63/G61,6),$C$120)) -> 0.8 | H64: =MIN(1,CEILING(ROUND(H63/H61,6),$C$120)) -> 0.8
B65: Annual average biomass share of heat | C65: =C64*C61 -> 0 | D65: =D64*D61 -> 0.3390411 | E65: =E64*E61 -> 0.6 | F65: =F64*F61 -> 0.8 | G65: =G64*G61 -> 0.8 | H65: =H64*H61 -> 0.8
B66: Fuel burned
B67: Biomass heat (GJ) | C67: =C55*C65 -> 0 | D67: =D55*D65 -> 113917.81 | E67: =E55*E65 -> 248148 | F67: =F55*F65 -> 413580 | G67: =G55*G65 -> 366062.34 | H67: =H55*H65 -> 292849.87
B68: Coal heat (GJ) | C68: =C55-C67 -> 300000 | D68: =D55-D67 -> 222082.19 | E68: =E55-E67 -> 165432 | F68: =F55-F67 -> 103395 | G68: =G55-G67 -> 91515.586 | H68: =H55-H67 -> 73212.469
B69: Coal burned (t) | C69: =C68/'ESG_CAPEX OPEX'!$B$7 -> 12000 | D69: =D68/'ESG_CAPEX OPEX'!$B$7 -> 8883.2877 | E69: =E68/'ESG_CAPEX OPEX'!$B$7 -> 6617.28 | F69: =F68/'ESG_CAPEX OPEX'!$B$7 -> 4135.8 | G69: =G68/'ESG_CAPEX OPEX'!$B$7 -> 3660.6234 | H69: =H68/'ESG_CAPEX OPEX'!$B$7 -> 2928.4987
B70: Rice husk pellet burned (t) | C70: =C67*'ESG_CAPEX OPEX'!$B$10/'ESG_CAPEX OPEX'!$B$8 -> 0 | D70: =D67*'ESG_CAPEX OPEX'!$B$10/'ESG_CAPEX OPEX'!$B$8 -> 4983.9041 | E70: =E67*'ESG_CAPEX OPEX'!$B$10/'ESG_CAPEX OPEX'!$B$8 -> 10856.475 | F70: =F67*'ESG_CAPEX OPEX'!$B$10/'ESG_CAPEX OPEX'!$B$8 -> 18094.125 | G70: =G67*'ESG_CAPEX OPEX'!$B$10/'ESG_CAPEX OPEX'!$B$8 -> 16015.228 | H70: =H67*'ESG_CAPEX OPEX'!$B$10/'ESG_CAPEX OPEX'!$B$8 -> 12812.182
B71: Wood pellet burned (t) | C71: =C67*'ESG_CAPEX OPEX'!$B$11/'ESG_CAPEX OPEX'!$B$9 -> 0 | D71: =D67*'ESG_CAPEX OPEX'!$B$11/'ESG_CAPEX OPEX'!$B$9 -> 1898.6301 | E71: =E67*'ESG_CAPEX OPEX'!$B$11/'ESG_CAPEX OPEX'!$B$9 -> 4135.8 | F71: =F67*'ESG_CAPEX OPEX'!$B$11/'ESG_CAPEX OPEX'!$B$9 -> 6893 | G71: =G67*'ESG_CAPEX OPEX'!$B$11/'ESG_CAPEX OPEX'!$B$9 -> 6101.0391 | H71: =H67*'ESG_CAPEX OPEX'!$B$11/'ESG_CAPEX OPEX'!$B$9 -> 4880.8312
B72: Emissions and compliance
B73: Annual CO2e, thermal energy (t) | C73: =(C68*$C$112+C67*$C$116)/1000 -> 28380 | D73: =(D68*$C$112+D67*$C$116)/1000 -> 22045.627 | E73: =(E68*$C$112+E67*$C$116)/1000 -> 17908.014 | F73: =(F68*$C$112+F67*$C$116)/1000 -> 13544.745 | G73: =(G68*$C$112+G67*$C$116)/1000 -> 11988.542 | H73: =(H68*$C$112+H67*$C$116)/1000 -> 9590.8334
B74: CO2e intensity (kg/GJ) | C74: =C73*1000/C55 -> 94.6 | D74: =D73*1000/D55 -> 65.611986 | E74: =E73*1000/E55 -> 43.3 | F74: =F73*1000/F55 -> 26.2 | G74: =G73*1000/G55 -> 26.2 | H74: =H73*1000/H55 -> 26.2
B75: Headroom below the absolute cap | C75: =1-C73/C58 -> 0 | D75: =1-D73/D58 -> 0.086115848 | E75: =1-E73/E58 -> 0.09855965 | F75: =1-F73/F58 -> 0.13224774 | G75: =1-G73/G58 -> 0.061268363 | H75: =1-H73/H58 -> 0.061268363
B76: Emission index (2026 = 100) | C76: =C73/C$73*100 -> 100 | D76: =D73/C$73*100 -> 77.680153 | E76: =E73/C$73*100 -> 63.100825 | F76: =F73/C$73*100 -> 47.726374 | G76: =G73/C$73*100 -> 42.242924 | H76: =H73/C$73*100 -> 33.794339
B77: Reduction vs 2026 baseline | C77: =1-C73/C$73 -> 0 | D77: =1-D73/C$73 -> 0.22319847 | E77: =1-E73/C$73 -> 0.36899175 | F77: =1-F73/C$73 -> 0.52273626 | G77: =1-G73/C$73 -> 0.57757076 | H77: =1-H73/C$73 -> 0.66205661
B78: Compliance (absolute and intensity) | C78: Baseline | D78: =IF(AND(D73<=D58+0.5,D74<=D59+0.05),"Compliant","NOT compliant") -> Compliant | E78: =IF(AND(E73<=E58+0.5,E74<=E59+0.05),"Compliant","NOT compliant") -> Compliant | F78: =IF(AND(F73<=F58+0.5,F74<=F59+0.05),"Compliant","NOT compliant") -> Compliant | G78: =IF(AND(G73<=G58+0.5,G74<=G59+0.05),"Compliant","NOT compliant") -> Compliant | H78: =IF(AND(H73<=H58+0.5,H74<=H59+0.05),"Compliant","NOT compliant") -> Compliant
B79: Stress: CO2e with the 8-week slip (t) | D79: =D55*((1-D64*D62)*$C$112+D64*D62*$C$116)/1000 -> 24029.04
B80: Stress: compliance with the slip | D80: =IF(D79<=D58+0.5,"Compliant","NOT compliant") -> Compliant | E80: n/a | F80: n/a | G80: n/a | H80: n/a
B81: How it is calculated
B82: Heat = realized sales × heat intensity (heat scales with volume). Caps are read from Emission Target D6:E11.
B83: Minimum share = (EF coal − 95% × tighter cap) ÷ (EF coal − EF biomass); the operating share is the lowest 5% step above it ÷ share of year in service. 2027 must also pass the 8-week slip test (R14).
B84: Coal t = coal heat ÷ 25 GJ/t; rice husk t = biomass heat × 70% ÷ 16 GJ/t; wood pellet t = biomass heat × 30% ÷ 18 GJ/t.
B85: CO2e = (coal heat × 94.6 + biomass heat × 9.1) ÷ 1,000. Compliant only when both the absolute and the intensity cap hold.
B87: Straight-line depreciation by tranche and ESG completion (USD)
B88: Tranche (commissioning year) | C88: Cost | D88: 2027 | E88: 2028 | F88: 2029 | G88: 2030 | H88: 2031 | I88: Beyond 2031
B89: T1 (2027) | C89: =SUMPRODUCT((YEAR($G$10:$G$20)=2027)*$E$10:$E$20) -> 896500 | D89: =IF(AND(2027>=2027,2027<2027+$C$121),$C89/$C$121,0) -> 179300 | E89: =IF(AND(2028>=2027,2028<2027+$C$121),$C89/$C$121,0) -> 179300 | F89: =IF(AND(2029>=2027,2029<2027+$C$121),$C89/$C$121,0) -> 179300 | G89: =IF(AND(2030>=2027,2030<2027+$C$121),$C89/$C$121,0) -> 179300 | H89: =IF(AND(2031>=2027,2031<2027+$C$121),$C89/$C$121,0) -> 179300 | I89: =C89-SUM(D89:H89) -> 0
B90: T2 (2028) | C90: =SUMPRODUCT((YEAR($G$10:$G$20)=2028)*$E$10:$E$20) -> 44000 | D90: =IF(AND(2027>=2028,2027<2028+$C$121),$C90/$C$121,0) -> 0 | E90: =IF(AND(2028>=2028,2028<2028+$C$121),$C90/$C$121,0) -> 8800 | F90: =IF(AND(2029>=2028,2029<2028+$C$121),$C90/$C$121,0) -> 8800 | G90: =IF(AND(2030>=2028,2030<2028+$C$121),$C90/$C$121,0) -> 8800 | H90: =IF(AND(2031>=2028,2031<2028+$C$121),$C90/$C$121,0) -> 8800 | I90: =C90-SUM(D90:H90) -> 8800
B91: T3 (2029) | C91: =SUMPRODUCT((YEAR($G$10:$G$20)=2029)*$E$10:$E$20) -> 0 | D91: =IF(AND(2027>=2029,2027<2029+$C$121),$C91/$C$121,0) -> 0 | E91: =IF(AND(2028>=2029,2028<2029+$C$121),$C91/$C$121,0) -> 0 | F91: =IF(AND(2029>=2029,2029<2029+$C$121),$C91/$C$121,0) -> 0 | G91: =IF(AND(2030>=2029,2030<2029+$C$121),$C91/$C$121,0) -> 0 | H91: =IF(AND(2031>=2029,2031<2029+$C$121),$C91/$C$121,0) -> 0 | I91: =C91-SUM(D91:H91) -> 0
B92: T4 (2030) | C92: =SUMPRODUCT((YEAR($G$10:$G$20)=2030)*$E$10:$E$20) -> 0 | D92: =IF(AND(2027>=2030,2027<2030+$C$121),$C92/$C$121,0) -> 0 | E92: =IF(AND(2028>=2030,2028<2030+$C$121),$C92/$C$121,0) -> 0 | F92: =IF(AND(2029>=2030,2029<2030+$C$121),$C92/$C$121,0) -> 0 | G92: =IF(AND(2030>=2030,2030<2030+$C$121),$C92/$C$121,0) -> 0 | H92: =IF(AND(2031>=2030,2031<2030+$C$121),$C92/$C$121,0) -> 0 | I92: =C92-SUM(D92:H92) -> 0
B93: T5 (2031) | C93: =SUMPRODUCT((YEAR($G$10:$G$20)=2031)*$E$10:$E$20) -> 0 | D93: =IF(AND(2027>=2031,2027<2031+$C$121),$C93/$C$121,0) -> 0 | E93: =IF(AND(2028>=2031,2028<2031+$C$121),$C93/$C$121,0) -> 0 | F93: =IF(AND(2029>=2031,2029<2031+$C$121),$C93/$C$121,0) -> 0 | G93: =IF(AND(2030>=2031,2030<2031+$C$121),$C93/$C$121,0) -> 0 | H93: =IF(AND(2031>=2031,2031<2031+$C$121),$C93/$C$121,0) -> 0 | I93: =C93-SUM(D93:H93) -> 0
B94: Total depreciation expense | C94: =SUM(C89:C93) -> 940500 | D94: =SUM(D89:D93) -> 179300 | E94: =SUM(E89:E93) -> 188100 | F94: =SUM(F89:F93) -> 188100 | G94: =SUM(G89:G93) -> 188100 | H94: =SUM(H89:H93) -> 188100 | I94: =SUM(I89:I93) -> 8800
B95: Cumulative ESG completion (% of CAPEX in service) | D95: =I23 -> 0.95321637 | E95: =J23 -> 1 | F95: =K23 -> 1 | G95: =L23 -> 1 | H95: =M23 -> 1
B96: Decarbonisation progress (reduction ÷ 64% target) | D96: =D77/'Emission Target'!$C$11 -> 0.34874761 | E96: =E77/'Emission Target'!$C$11 -> 0.57654962 | F96: =F77/'Emission Target'!$C$11 -> 0.8167754 | G96: =G77/'Emission Target'!$C$11 -> 0.90245432 | H96: =H77/'Emission Target'!$C$11 -> 1.0344635
B97: Rule (Table 03): each tranche ÷ 5 years, full year from its commissioning year, no salvage. Tranche 2 keeps one year of depreciation beyond 2031. The second line shows how far the operating mix has moved toward the 2031 target state (Emission Target C11).
B105: Model inputs and their basis
B106: Parameter | C106: Value | D106: Unit | E106: Basis / source
B107: Total project CAPEX (incl. contingency) | C107: ='ESG_CAPEX OPEX'!E30 -> 940500 | D107: USD | E107: ESG_CAPEX OPEX E30. Full scope kept; no reduction.
B108: Contingency rate | C108: ='ESG_CAPEX OPEX'!B29 -> 0.1 | D108: % | E108: ESG_CAPEX OPEX B29; allocated pro rata to each item.
B109: 2026 useful heat demand | C109: ='ESG_CAPEX OPEX'!B6 -> 300000 | D109: GJ | E109: ESG_CAPEX OPEX B6.
B110: 2026 sales volume | C110: ='Sales Forecast & Case 2A KPI'!C21 -> 5020000 | D110: pcs | E110: Sales Forecast C21.
B111: Heat intensity | C111: =C109/C110 -> 0.059760956 | D111: GJ/pc | E111: Heat demand scales with output (steam is used per kg of fabric dyed/finished, ESG_CAPEX OPEX D6). Held at the 2026 level.
B112: Emission factor: coal | C112: ='CO2 Emission Calculation'!C4 -> 94.6 | D112: kgCO2e/GJ | E112: CO2 Emission Calculation C4.
...

Sheet Task 2_Conversion & Forecast
B1: TASK 2 - SALES CONVERSION 2027-2029 AND VOLUME FORECAST 2030-2031
B2: Requirement 2: a justified conversion rate turns LSC potential orders into realized sales, and 2030-2031 volumes are forecast independently. Realized sales = MIN(risk-adjusted demand after the ESG gate, carbon-allowed capacity).
B4: RISK-ADJUSTED CR 2027 · 2028 · 2029 | C4: REALIZED SALES 2027 | E4: REALIZED SALES 2029 | G4: ORDER GROWTH 2030-2031 | J4: REALIZED SALES 2031 | L4: UNSERVED DEMAND 2030-2031 | N4: PEAK BOILER LOAD
B5: =TEXT(D42,"0.0%")&" · "&TEXT(E42,"0.0%")&" · "&TEXT(F42,"0.0%") -> 91.8% · 90.4% · 88.3% | C5: =D19 -> 5622400 | E5: =F19 -> 8650715 | G5: =G49 -> 0.063333333 | J5: =H19 -> 6125443.2 | L5: =G25+H25 -> 5197517.6 | N5: =MAX(C27:H27) -> 1.72325
B6: CR = (1 + g ESG − |g Traditional|) ÷ (1 + g ESG) | C6: ="+"&TEXT(D19/C19-1,"0%")&" vs 2026" -> +12% vs 2026 | E6: ="+"&TEXT(F19/C19-1,"0%")&" vs 2026 (peak)" -> +72% vs 2026 (peak) | G6: Market component only (shift-share) | J6: ="Bound by "&LOWER(H21) -> Bound by carbon capacity | L6: Declined, not subcontracted | N6: × 2026 heat (2029); no boiler rating in the case
B8: Sales conversion funnel 2026-2031: orders → risk-adjusted demand → ESG gate → carbon capacity → realized sales (pcs)
B9: Metric | C9: 2026 | D9: 2027 | E9: 2028 | F9: 2029 | G9: 2030F | H9: 2031F
B10: Orders and commercial risk
B11: Potential orders (2027-2029) / forecast orders (2030-2031) | C11: =C50 -> 5020000 | D11: =D50 -> 6124400 | E11: =E50 -> 7655500 | F11: =F50 -> 9799040 | G11: =G50 -> 10419646 | H11: =H50 -> 11079557
B12: Conversion rate applied | C12: =C51 -> 1 | D12: =D51 -> 0.91803279 | E12: =E51 -> 0.904 | F12: =F51 -> 0.8828125 | G12: =G51 -> 0.8828125 | H12: =H51 -> 0.8828125
B13: Risk-adjusted demand | C13: =C11*C12 -> 5020000 | D13: =D11*D12 -> 5622400 | E13: =E11*E12 -> 6920572 | F13: =F11*F12 -> 8650715 | G13: =G11*G12 -> 9198593.6 | H13: =H11*H12 -> 9781171.2
B14: ESG gate
B15: TEXIN emission compliance (Task 1) | C15: Baseline | D15: ='Task 1_ESG Roadmap'!D78 -> Compliant | E15: ='Task 1_ESG Roadmap'!E78 -> Compliant | F15: ='Task 1_ESG Roadmap'!F78 -> Compliant | G15: ='Task 1_ESG Roadmap'!G78 -> Compliant | H15: ='Task 1_ESG Roadmap'!H78 -> Compliant
B16: Demand after the ESG gate | C16: =C13 -> 5020000 | D16: =D13 -> 5622400 | E16: =IF(LEFT(D15,9)="Compliant",E13,MIN(E13,D19)) -> 6920572 | F16: =IF(LEFT(E15,9)="Compliant",F13,MIN(F13,E19)) -> 8650715 | G16: =IF(LEFT(F15,9)="Compliant",G13,MIN(G13,F19)) -> 9198593.6 | H16: =IF(LEFT(G15,9)="Compliant",H13,MIN(H13,G19)) -> 9781171.2
B17: Capacity and realized sales
B18: Carbon-allowed capacity | C18: ='Carbon-Allowed Capacity'!C36 -> 5020000 | D18: ='Carbon-Allowed Capacity'!D36 -> 9100807.2 | E18: ='Carbon-Allowed Capacity'!E36 -> 11910584 | F18: ='Carbon-Allowed Capacity'!F36 -> 9358316 | G18: ='Carbon-Allowed Capacity'!G36 -> 7656804 | H18: ='Carbon-Allowed Capacity'!H36 -> 6125443.2
B19: Realized sales volume | C19: ='Sales Forecast & Case 2A KPI'!C21 -> 5020000 | D19: =MIN(D16,D18) -> 5622400 | E19: =MIN(E16,E18) -> 6920572 | F19: =MIN(F16,F18) -> 8650715 | G19: =MIN(G16,G18) -> 7656804 | H19: =MIN(H16,H18) -> 6125443.2
B20: Effective sales conversion rate (realized ÷ orders) | C20: =C19/C11 -> 1 | D20: =D19/D11 -> 0.91803279 | E20: =E19/E11 -> 0.904 | F20: =F19/F11 -> 0.8828125 | G20: =G19/G11 -> 0.73484302 | H20: =H19/H11 -> 0.55285995
B21: Binding constraint | C21: Actual | D21: =IF(D19<D16-0.5,"Carbon capacity",IF(D16<D13-0.5,"ESG gate","Demand")) -> Demand | E21: =IF(E19<E16-0.5,"Carbon capacity",IF(E16<E13-0.5,"ESG gate","Demand")) -> Demand | F21: =IF(F19<F16-0.5,"Carbon capacity",IF(F16<F13-0.5,"ESG gate","Demand")) -> Demand | G21: =IF(G19<G16-0.5,"Carbon capacity",IF(G16<G13-0.5,"ESG gate","Demand")) -> Carbon capacity | H21: =IF(H19<H16-0.5,"Carbon capacity",IF(H16<H13-0.5,"ESG gate","Demand")) -> Carbon capacity
B22: Use of carbon-allowed capacity | C22: =C19/C18 -> 1 | D22: =D19/D18 -> 0.61779135 | E22: =E19/E18 -> 0.58104388 | F22: =F19/F18 -> 0.924388 | G22: =G19/G18 -> 1 | H22: =H19/H18 -> 1
B23: Leakage and load
B24: Orders not converted: commercial risk | C24: =C11-C13 -> 0 | D24: =D11-D13 -> 502000 | E24: =E11-E13 -> 734928 | F24: =F11-F13 -> 1148325 | G24: =G11-G13 -> 1221052.2 | H24: =H11-H13 -> 1298385.6
B25: Orders not served: above carbon capacity | C25: =C16-C19 -> 0 | D25: =D16-D19 -> 0 | E25: =E16-E19 -> 0 | F25: =F16-F19 -> 0 | G25: =G16-G19 -> 1541789.6 | H25: =H16-H19 -> 3655728
B26: Realized volume growth YoY | D26: =D19/C19-1 -> 0.12 | E26: =E19/D19-1 -> 0.23089286 | F26: =F19/E19-1 -> 0.25 | G26: =G19/F19-1 -> -0.11489351 | H26: =H19/G19-1 -> -0.2
B27: Heat demand vs 2026 (×) | C27: =C19/'Sales Forecast & Case 2A KPI'!$C$21 -> 1 | D27: =D19/'Sales Forecast & Case 2A KPI'!$C$21 -> 1.12 | E27: =E19/'Sales Forecast & Case 2A KPI'!$C$21 -> 1.3786 | F27: =F19/'Sales Forecast & Case 2A KPI'!$C$21 -> 1.72325 | G27: =G19/'Sales Forecast & Case 2A KPI'!$C$21 -> 1.5252598 | H27: =H19/'Sales Forecast & Case 2A KPI'!$C$21 -> 1.2202078
B29: Case commercial signals and the risk-adjusted conversion rate
B30: Metric | C30: 2026 | D30: 2027 | E30: 2028 | F30: 2029 | G30: 2030F | H30: 2031F | J30: Why these conversion rates
B31: Case signals (Sales Forecast, Emission Target) | J31: ="1. ESG milestones and commercial risk. Potential orders are released only as TEXIN delivers its roadmap (Sales Forecast D7-D9), and compliance is verified after each year (Emission Target B18-B19). The share at risk is set by the case's own"&" erosion rate, giving CR of "&TEXT(D42,"0.00%")&", "&TEXT(E42,"0.00%")&" and "&TEXT(F42,"0.00%")&" for 2027-2029; the haircut grows as targets become harder (Moderate, Challenging, High)." -> 1. ESG milestones and commercial risk. Potential orders are released only as TEXIN delivers its roadmap (Sales Forecast D7-D9), and compliance is verified after each year (Emission Target B18-B19). The share at risk is set by the case's own erosion rate, giving CR of 91.80%, 90.40% and 88.28% for 2027-2029; the haircut grows as targets become harder (Moderate, Challenging, High).
B32: LSC potential orders, ESG scenario (pcs) | C32: ='Sales Forecast & Case 2A KPI'!C21 -> 5020000 | D32: ='Sales Forecast & Case 2A KPI'!D21 -> 6124400 | E32: ='Sales Forecast & Case 2A KPI'!E21 -> 7655500 | F32: ='Sales Forecast & Case 2A KPI'!F21 -> 9799040 | G32: n/a | H32: n/a
B33: ESG scenario growth (g ESG) | D33: ='Sales Forecast & Case 2A KPI'!B7 -> 0.22 | E33: ='Sales Forecast & Case 2A KPI'!B8 -> 0.25 | F33: ='Sales Forecast & Case 2A KPI'!B9 -> 0.28
B34: Traditional scenario change (g Traditional) | D34: ='Sales Forecast & Case 2A KPI'!B10 -> -0.1 | E34: ='Sales Forecast & Case 2A KPI'!B11 -> -0.12 | F34: ='Sales Forecast & Case 2A KPI'!B12 -> -0.15 | J34: ="2. Capacity. The carbon-allowed capacity at the case design mix (~78% biomass) exceeds risk-adjusted demand in 2027-2029, so realized sales equal risk-adjusted demand: "&TEXT(D19/1000000,"0.00")&"M, "&TEXT(E19/1000000,"0.00")&"M and "&TEXT(F19/1000000,"0.00")&"M pcs. Task 1 confirms CO2e stays below both caps, including an 8-week commissioning slip in 2027 (R14)." -> 2. Capacity. The carbon-allowed capacity at the case design mix (~78% biomass) exceeds risk-adjusted demand in 2027-2029, so realized sales equal risk-adjusted demand: 5.62M, 6.92M and 8.65M pcs. Task 1 confirms CO2e stays below both caps, including an 8-week commissioning slip in 2027 (R14).
B35: Traditional / No-ESG order volume (pcs) | C35: ='Sales Forecast & Case 2A KPI'!C21 -> 5020000 | D35: ='Sales Forecast & Case 2A KPI'!G21 -> 4518000 | E35: ='Sales Forecast & Case 2A KPI'!H21 -> 3975840 | F35: ='Sales Forecast & Case 2A KPI'!I21 -> 3379464
B36: Buyer challenge level | C36: ='Emission Target'!I6 -> Baseline | D36: ='Emission Target'!I7 -> Moderate | E36: ='Emission Target'!I8 -> Challenging | F36: ='Emission Target'!I9 -> High | G36: ='Emission Target'!I10 -> High | H36: ='Emission Target'!I11 -> Stretch/target state
B37: Commercial consequence if the year's target is missed | C37: ='Emission Target'!H6 -> Baseline year | D37: ='Emission Target'!H7 -> Corrective action plan; new allocation may be held | E37: ='Emission Target'!H8 -> Buyer may freeze incremental order allocation | F37: ='Emission Target'!H9 -> Risk of sourcing reallocation to compliant suppliers | G37: ='Emission Target'!H10 -> Reduced preferred-supplier status/allocation | H37: ='Emission Target'!H11 -> Roadmap failure; material risk of order reallocation | J37: ="3. 2030-2031 forecast. Orders grow with the market component only ("&TEXT(G49,"0.00%")&" a year), not with the 22-28% reallocation phase (Sales Forecast B34), and CR is held at the 2029 level. Forecast demand is "&TEXT(G13/1000000,"0.00")&"M and "&TEXT(H13/1000000,"0.00")&"M pcs." -> 3. 2030-2031 forecast. Orders grow with the market component only (6.33% a year), not with the 22-28% reallocation phase (Sales Forecast B34), and CR is held at the 2029 level. Forecast demand is 9.20M and 9.78M pcs.
B38: Risk-adjusted conversion rate
B39: Growth factor (1 + g ESG) | D39: =1+D33 -> 1.22 | E39: =1+E33 -> 1.25 | F39: =1+F33 -> 1.28 | J39: ="4. Carbon limit after 2029. The caps tighten faster than the fuel mix improves, so carbon capacity binds: realized sales are "&TEXT(G19/1000000,"0.00")&"M (2030F) and "&TEXT(H19/1000000,"0.00")&"M pcs (2031F), leaving "&TEXT((G25+H25)/1000000,"0.00")&"M pcs of demand unserved. Raising biomass above the design mix or cutting heat per piece are the growth levers for Task 5." -> 4. Carbon limit after 2029. The caps tighten faster than the fuel mix improves, so carbon capacity binds: realized sales are 7.66M (2030F) and 6.13M pcs (2031F), leaving 5.20M pcs of demand unserved. Raising biomass above the design mix or cutting heat per piece are the growth levers for Task 5.
B40: Commercial-risk haircut |g Traditional| | D40: =ABS(D34) -> 0.1 | E40: =ABS(E34) -> 0.12 | F40: =ABS(F34) -> 0.15
B41: Adjusted growth factor (1 + g ESG − |g Traditional|) | D41: =D39-D40 -> 1.12 | E41: =E39-E40 -> 1.13 | F41: =F39-F40 -> 1.13
B42: Risk-adjusted conversion rate (CR) | C42: 1 | D42: =D41/D39 -> 0.91803279 | E42: =E41/E39 -> 0.904 | F42: =F41/F39 -> 0.8828125
B43: Share of potential orders at risk (1 − CR) | C43: =1-C42 -> 0 | D43: =1-D42 -> 0.081967213 | E43: =1-E42 -> 0.096 | F43: =1-F42 -> 0.1171875
B45: Independent volume forecast 2030-2031: shift-share decomposition of the two case scenarios
B46: Metric | C46: 2026 | D46: 2027 | E46: 2028 | F46: 2029 | G46: 2030F | H46: 2031F | J46: Method (Dunn, 1960)
B47: Market component = (g ESG + g Traditional) ÷ 2 | D47: =(D33+D34)/2 -> 0.06 | E47: =(E33+E34)/2 -> 0.065 | F47: =(F33+F34)/2 -> 0.065 | G47: =AVERAGE($D$47:$F$47) -> 0.063333333 | H47: =AVERAGE($D$47:$F$47) -> 0.063333333 | J47: Each case scenario = market growth ± reallocation between suppliers. The mean of the ESG and Traditional rates isolates market growth (6.0%, 6.5%, 6.5%; average applied to 2030-2031).
B48: Competitive shift = (g ESG − g Traditional) ÷ 2 | D48: =(D33-D34)/2 -> 0.16 | E48: =(E33-E34)/2 -> 0.185 | F48: =(F33-F34)/2 -> 0.215 | G48: 0 | H48: 0
B49: Order growth applied 2030-2031 | G49: =G47+G48 -> 0.063333333 | H49: =H47+H48 -> 0.063333333
B50: Forecast order volume (pcs) | C50: =C32 -> 5020000 | D50: =D32 -> 6124400 | E50: =E32 -> 7655500 | F50: =F32 -> 9799040 | G50: =F50*(1+G49) -> 10419646 | H50: =G50*(1+H49) -> 11079557 | J50: After the 2029 strategic checkpoint (Emission Target G9, B19) the reallocation toward compliant suppliers is complete, so the competitive shift is set to 0. This avoids extending the 22-28% growth mechanically (Sales Forecast B34).
B51: Conversion rate applied | C51: =C42 -> 1 | D51: =D42 -> 0.91803279 | E51: =E42 -> 0.904 | F51: =F42 -> 0.8828125 | G51: =$F$42 -> 0.8828125 | H51: =$F$42 -> 0.8828125
B53: Assumptions and how conflicts with the case constraints are resolved
B54: Issue | C54: Assumption adopted | J54: Basis
B55: Heat demand vs volume | C55: Heat demand scales with output; heat per piece held at the 2026 level (0.0598 GJ/pc). | J55: ESG_CAPEX OPEX D6: heat sized for dyeing/finishing steam, which is used per kg of fabric. Team decision.
B56: Conversion of potential orders | C56: CR = (1 + g ESG − |g Traditional|) ÷ (1 + g ESG): the Traditional erosion rate is the share of each year's potential orders at risk until that year's milestone is verified. | J56: Sales Forecast B33 (orders are not guaranteed), D10-D12 (erosion rates); Emission Target B18-B19 (annual verification).
B57: CR falls while ESG completion rises | C57: Risk is tied to the difficulty of the current-year milestone, which rises each year. | J57: Emission Target I7:I9 (Moderate, Challenging, High); Sales Forecast D12 ('accelerated order loss').
B58: No customer data for 2030-2031 | C58: Orders grow with the market component (shift-share mean of the two scenarios, 6.33%); no further reallocation gain; CR held at 2029. | J58: Sales Forecast B34 (no mechanical extension); Emission Target G9, B19 (2029 checkpoint), I10:I11 (High/Stretch).
B59: Production capacity | C59: Carbon-allowed capacity at the design mix is the binding volume limit; sewing labour is variable and costed per piece through COGS. | J59: Emission Target F11 (~78% biomass); case template row 46 (COGS = volume × COGS/pc); no line or boiler rating is given in the case.
B60: Zero headroom at the carbon limit | C60: Capacity is planned at the 78% design mix; Task 1 operates the boiler at the next 5% step above the requirement (80% when capacity binds), keeping CO2e ≥5% below the cap. | J60: R01 (coal fallback), R02 (moisture); ESG_CAPEX OPEX A2 (full biomass-capable system), Emission Target F11 ('~78%').
B61: Demand above carbon capacity (2030-2031) | C61: Declined, not subcontracted, so emissions are not moved outside the reporting boundary. | J61: Emission Target B17 (scope boundary); R07 (reporting credibility). Growth levers assessed in Task 5.
B62: Boiler heat load | C62: The retrofitted system is assumed able to supply up to 1.72x the 2026 heat (2029 peak). | J62: No boiler rating in the case (ESG_CAPEX OPEX J17: retrofit). Flagged with R08 (steam pressure) for Task 5.
B64: Sources
B65: Case workbook: Sales Forecast & Case 2A KPI (A-C, B33-B34), Emission Target (A-B), ESG_CAPEX OPEX (A2, B6, D6, J17), COGS, Supply Chain Risks (R01, R02, R07, R08, R14), sheet 'Carbon-Allowed Capacity'.
B66: Team working file 'Sales Conversion Rate Forecast (2027-2029)': risk-adjusted conversion rate formula.
B67: Dunn, E. S. (1960). A statistical and analytical technique for regional analysis. Papers of the Regional Science Association, 6(1), 97-112 (shift-share analysis).

Sheet Task 3_P&L
B1: TASK 3 - FIVE-YEAR P&L AND THE PROFITABILITY CONSTRAINTS
B2: Requirement 3: annual P&L 2027–2031 of the ESG pathway (Task 1 roadmap, Task 2 sales) and proof that every year meets the case floors. Base COGS already carries coal-based thermal energy, so only the biomass cost above the coal-equivalent is added (no double counting).
B4: PROFITABILITY TEST | C4: LOWEST NET PROFIT MARGIN | E4: NET PROFIT 2027–2031 | G4: ESG COST BURDEN | J4: FREE CASH FLOW 2027–2031 | L4: PRICE CUT TO BREACH A FLOOR
B5: =COUNTIF(D34:H34,"PASS")&" / 5 years PASS" -> 5 / 5 years PASS | C5: =MIN(D30:H30) -> 0.085829879 | E5: =SUM(D29:H29) -> 12255574 | G5: =TEXT(MIN(D36:H36),"0.0%")&" to "&TEXT(MAX(D36:H36),"0.0%") -> 1.9% to 3.2% | J5: =H78 -> 11584556 | L5: =MIN(D37:H37) -> 0.11263764
B6: Floors: −10% (2027), −8% (2028), > 0% (2029–2031) | C6: {="in "&INDEX(D9:H9,MATCH(MIN(D30:H30),D30:H30,0))&"; 2026 actual "&TEXT(C30,"0.0%")} -> in 2031; 2026 actual 10.8% | E6: ="Peak "&TEXT(MAX(D29:H29)/1000000,"0.00")&"M in 2029" -> Peak 3.06M in 2029 | G6: of revenue: ESG OPEX + depreciation | J6: Self-funded; no new debt | L6: vs a 1.5–2.5% ESG premium at stake
B8: Income statement 2026A–2031 and the case profitability test
B9: USD unless stated | C9: 2026A | D9: 2027 | E9: 2028 | F9: 2029 | G9: 2030 | H9: 2031 | J9: Reading the result
B10: Drivers | J10: {="1. All five years pass. NPM is "&TEXT(D30,"0.0%")&", "&TEXT(E30,"0.0%")&", "&TEXT(F30,"0.0%")&", "&TEXT(G30,"0.0%")&" and "&TEXT(H30,"0.0%")&" for 2027–2031 against floors of −10%, −8% and >0%; the thinnest headroom is "&TEXT(MIN(D35:H35),"0.0%")&" in "&INDEX($D$9:$H$9,MATCH(MIN(D35:H35),D35:H35,0))&"."} -> 1. All five years pass. NPM is 9.5%, 9.3%, 9.2%, 9.0% and 8.6% for 2027–2031 against floors of −10%, −8% and >0%; the thinnest headroom is 8.6% in 2031.
B11: Realized sales volume (pcs) | C11: ='Sales Forecast & Case 2A KPI'!C21 -> 5020000 | D11: ='Sales Forecast & Case 2A KPI'!B42 -> 5622400 | E11: ='Sales Forecast & Case 2A KPI'!C42 -> 6920572 | F11: ='Sales Forecast & Case 2A KPI'!D42 -> 8650715 | G11: ='Sales Forecast & Case 2A KPI'!E42 -> 7656804 | H11: ='Sales Forecast & Case 2A KPI'!F42 -> 6125443.2
B12: Weighted EXW price incl. ESG premium (USD/pc) | C12: ='Sales Forecast & Case 2A KPI'!B43 -> 3.8414868 | D12: ='Sales Forecast & Case 2A KPI'!B43 -> 3.8414868 | E12: ='Sales Forecast & Case 2A KPI'!C43 -> 3.8414868 | F12: ='Sales Forecast & Case 2A KPI'!D43 -> 3.8414868 | G12: ='Sales Forecast & Case 2A KPI'!E43 -> 3.8414868 | H12: ='Sales Forecast & Case 2A KPI'!F43 -> 3.8414868
B13: Base manufacturing COGS per piece (USD/pc) | C13: ='Sales Forecast & Case 2A KPI'!B45 -> 3.0524813 | D13: ='Sales Forecast & Case 2A KPI'!B45 -> 3.0524813 | E13: ='Sales Forecast & Case 2A KPI'!C45 -> 3.0524813 | F13: ='Sales Forecast & Case 2A KPI'!D45 -> 3.0524813 | G13: ='Sales Forecast & Case 2A KPI'!E45 -> 3.0524813 | H13: ='Sales Forecast & Case 2A KPI'!F45 -> 3.0524813
B14: Income statement
B15: Revenue | C15: ='EXW Price'!B13 -> 19284264 | D15: =D11*D12 -> 21598376 | E15: =E11*E12 -> 26585286 | F15: =F11*F12 -> 33231608 | G15: =G11*G12 -> 29413512 | H15: =H11*H12 -> 23530809
B16: Base manufacturing COGS | C16: =SUM(COGS!M14:M18) -> 15323456 | D16: =D11*D13 -> 17162271 | E16: =E11*E13 -> 21124917 | F16: =F11*F13 -> 26406146 | G16: =G11*G13 -> 23372251 | H16: =H11*H13 -> 18697801
B17: Gross profit before ESG costs | C17: =C15-C16 -> 3960807.7 | D17: =D15-D16 -> 4436104.6 | E17: =E15-E16 -> 5460369.5 | F17: =F15-F16 -> 6825461.8 | G17: =G15-G16 -> 6041260.6 | H17: =H15-H16 -> 4833008.5 | J17: ="2. The roadmap costs "&TEXT(MIN(D36:H36),"0.0%")&" to "&TEXT(MAX(D36:H36),"0.0%")&" of revenue a year against a base gross margin of "&TEXT(D18,"0.0%")&". Volume growth pays for it: net profit rises from USD "&TEXT(C29/1000000,"0.00")&"M (2026) to USD "&TEXT(F29/1000000,"0.00")&"M (2029); NPM dips by about "&TEXT((C30-D30)*100,"0.0")&" points in the conversion year." -> 2. The roadmap costs 1.9% to 3.2% of revenue a year against a base gross margin of 20.5%. Volume growth pays for it: net profit rises from USD 2.09M (2026) to USD 3.06M (2029); NPM dips by about 1.3 points in the conversion year.
B18: Gross margin | C18: =C17/C15 -> 0.20539066 | D18: =D17/D15 -> 0.20539066 | E18: =E17/E15 -> 0.20539066 | F18: =F17/F15 -> 0.20539066 | G18: =G17/G15 -> 0.20539066 | H18: =H17/H15 -> 0.20539066
B19: Incremental ESG OPEX (build-up below) | C19: =C67 -> 0 | D19: =D67 -> 231580.27 | E19: =E67 -> 487729.73 | F19: =F67 -> 798515.08 | G19: =G67 -> 706910.78 | H19: =H67 -> 568740.92
B20: Depreciation of ESG CAPEX (Task 1) | C20: 0 | D20: ='Task 1_ESG Roadmap'!D94 -> 179300 | E20: ='Task 1_ESG Roadmap'!E94 -> 188100 | F20: ='Task 1_ESG Roadmap'!F94 -> 188100 | G20: ='Task 1_ESG Roadmap'!G94 -> 188100 | H20: ='Task 1_ESG Roadmap'!H94 -> 188100
B21: Gross profit after ESG costs | C21: =C17-C19-C20 -> 3960807.7 | D21: =D17-D19-D20 -> 4025224.3 | E21: =E17-E19-E20 -> 4784539.7 | F21: =F17-F19-F20 -> 5838846.8 | G21: =G17-G19-G20 -> 5146249.8 | H21: =H17-H19-H20 -> 4076167.5
B22: Selling & commercial cost | C22: =$C$95*C15 -> 482106.6 | D22: =$C$95*D15 -> 539959.39 | E22: =$C$95*E15 -> 664632.15 | F22: =$C$95*F15 -> 830790.19 | G22: =$C$95*G15 -> 735337.79 | H22: =$C$95*H15 -> 588270.24
B23: General & administrative cost | C23: =$C$96*$C$15*($C$97+(1-$C$97)*C15/$C$15) -> 867791.87 | D23: =$C$96*$C$15*($C$97+(1-$C$97)*D15/$C$15) -> 919859.39 | E23: =$C$96*$C$15*($C$97+(1-$C$97)*E15/$C$15) -> 1032064.9 | F23: =$C$96*$C$15*($C$97+(1-$C$97)*F15/$C$15) -> 1181607.1 | G23: =$C$96*$C$15*($C$97+(1-$C$97)*G15/$C$15) -> 1095700 | H23: =$C$96*$C$15*($C$97+(1-$C$97)*H15/$C$15) -> 963339.15
B24: Total SG&A | C24: =C22+C23 -> 1349898.5 | D24: =D22+D23 -> 1459818.8 | E24: =E22+E23 -> 1696697 | F24: =F22+F23 -> 2012397.3 | G24: =G22+G23 -> 1831037.7 | H24: =H22+H23 -> 1551609.4 | J24: ="3. Margin of safety: the EXW price would have to fall at least "&TEXT(MIN(D37:H37),"0.0%")&" before any floor is breached, several times the 1.5–2.5% ESG premium (EXW Price F6:F10). The P&L floors do not bind; carbon and capacity do (Tasks 1–2)." -> 3. Margin of safety: the EXW price would have to fall at least 11.3% before any floor is breached, several times the 1.5–2.5% ESG premium (EXW Price F6:F10). The P&L floors do not bind; carbon and capacity do (Tasks 1–2).
B25: EBIT | C25: =C21-C24 -> 2610909.2 | D25: =D21-D24 -> 2565405.5 | E25: =E21-E24 -> 3087842.7 | F25: =F21-F24 -> 3826449.5 | G25: =G21-G24 -> 3315212.1 | H25: =H21-H24 -> 2524558.2
B26: Interest on ESG funding | C26: =$C$99 -> 0 | D26: =$C$99 -> 0 | E26: =$C$99 -> 0 | F26: =$C$99 -> 0 | G26: =$C$99 -> 0 | H26: =$C$99 -> 0
B27: Profit before tax | C27: =C25-C26 -> 2610909.2 | D27: =D25-D26 -> 2565405.5 | E27: =E25-E26 -> 3087842.7 | F27: =F25-F26 -> 3826449.5 | G27: =G25-G26 -> 3315212.1 | H27: =H25-H26 -> 2524558.2
B28: Corporate income tax (20%) | C28: =MAX(0,C27)*$C$98 -> 522181.84 | D28: =MAX(0,D27)*$C$98 -> 513081.11 | E28: =MAX(0,E27)*$C$98 -> 617568.54 | F28: =MAX(0,F27)*$C$98 -> 765289.89 | G28: =MAX(0,G27)*$C$98 -> 663042.41 | H28: =MAX(0,H27)*$C$98 -> 504911.63
B29: Net profit | C29: =C27-C28 -> 2088727.4 | D29: =D27-D28 -> 2052324.4 | E29: =E27-E28 -> 2470274.2 | F29: =F27-F28 -> 3061159.6 | G29: =G27-G28 -> 2652169.6 | H29: =H27-H28 -> 2019646.5
B30: Net profit margin (NPM) | C30: =C29/C15 -> 0.10831253 | D30: =D29/D15 -> 0.095022167 | E30: =E29/E15 -> 0.092918848 | F30: =F29/F15 -> 0.092115903 | G30: =G29/G15 -> 0.090168412 | H30: =H29/H15 -> 0.085829879
B31: Case profitability constraint (Table 03) | J31: ="4. Revenue falls in 2030–2031 (USD "&TEXT(G15/1000000,"0.0")&"M and "&TEXT(H15/1000000,"0.0")&"M) because Task 2 caps output at the carbon-allowed capacity of the 78% design mix; Task 5 tests a higher biomass share to hold the 2029 volume." -> 4. Revenue falls in 2030–2031 (USD 29.4M and 23.5M) because Task 2 caps output at the carbon-allowed capacity of the 78% design mix; Task 5 tests a higher biomass share to hold the 2029 volume.
B32: NPM floor | C32: n/a | D32: -0.1 | E32: -0.08 | F32: 0 | G32: 0 | H32: 0
B33: Test ('≥' no worse than; '>' strictly positive, net profit > 0) | D33: ≥ | E33: ≥ | F33: > | G33: > | H33: >
B34: Constraint met? | D34: =IF(D33="≥",IF(D30>=D32,"PASS","FAIL"),IF(AND(D30>D32,D29>0),"PASS","FAIL")) -> PASS | E34: =IF(E33="≥",IF(E30>=E32,"PASS","FAIL"),IF(AND(E30>E32,E29>0),"PASS","FAIL")) -> PASS | F34: =IF(F33="≥",IF(F30>=F32,"PASS","FAIL"),IF(AND(F30>F32,F29>0),"PASS","FAIL")) -> PASS | G34: =IF(G33="≥",IF(G30>=G32,"PASS","FAIL"),IF(AND(G30>G32,G29>0),"PASS","FAIL")) -> PASS | H34: =IF(H33="≥",IF(H30>=H32,"PASS","FAIL"),IF(AND(H30>H32,H29>0),"PASS","FAIL")) -> PASS
B35: Headroom above the floor (percentage points) | D35: =D30-D32 -> 0.19502217 | E35: =E30-E32 -> 0.17291885 | F35: =F30-F32 -> 0.092115903 | G35: =G30-G32 -> 0.090168412 | H35: =H30-H32 -> 0.085829879
B36: ESG cost burden: (ESG OPEX + depreciation) ÷ revenue | C36: =(C19+C20)/C15 -> 0 | D36: =(D19+D20)/D15 -> 0.019023666 | E36: =(E19+E20)/E15 -> 0.025421195 | F36: =(F19+F20)/F15 -> 0.029689056 | G36: =(G19+G20)/G15 -> 0.030428559 | H36: =(H19+H20)/H15 -> 0.032163829
B37: EXW price cut that would bring NPM down to the floor | D37: =(D27-D32*D15)/(D11*(1-$C$95-$C$96*(1-$C$97)-D32))/D12 -> 0.20786481 | E37: =(E27-E32*E15)/(E11*(1-$C$95-$C$96*(1-$C$97)-E32))/E12 -> 0.18997439 | F37: =(F27-F32*F15)/(F11*(1-$C$95-$C$96*(1-$C$97)-F32))/F12 -> 0.12088701 | G37: =(G27-G32*G15)/(G11*(1-$C$95-$C$96*(1-$C$97)-G32))/G12 -> 0.11833125 | H37: =(H27-H32*H15)/(H11*(1-$C$95-$C$96*(1-$C$97)-H32))/H12 -> 0.11263764
B38: Check: case template rows 50–55 equal this P&L | D38: =IF(AND(ABS('Sales Forecast & Case 2A KPI'!B54-D29)<1,ABS('Sales Forecast & Case 2A KPI'!B55-D30)<0.0001),"OK","CHECK") -> OK | E38: =IF(AND(ABS('Sales Forecast & Case 2A KPI'!C54-E29)<1,ABS('Sales Forecast & Case 2A KPI'!C55-E30)<0.0001),"OK","CHECK") -> OK | F38: =IF(AND(ABS('Sales Forecast & Case 2A KPI'!D54-F29)<1,ABS('Sales Forecast & Case 2A KPI'!D55-F30)<0.0001),"OK","CHECK") -> OK | G38: =IF(AND(ABS('Sales Forecast & Case 2A KPI'!E54-G29)<1,ABS('Sales Forecast & Case 2A KPI'!E55-G30)<0.0001),"OK","CHECK") -> OK | H38: =IF(AND(ABS('Sales Forecast & Case 2A KPI'!F54-H29)<1,ABS('Sales Forecast & Case 2A KPI'!F55-H30)<0.0001),"OK","CHECK") -> OK
B40: Incremental ESG OPEX build-up: biomass operation minus the coal-equivalent already inside COGS (VND unless stated)
B41: USD unless stated | C41: 2026A | D41: 2027 | E41: 2028 | F41: 2029 | G41: 2030 | H41: 2031 | J41: Unit costs behind the build-up
B42: Heat and fuel (Task 1) | J42: Coal: VND per GJ of heat (price ÷ 25 GJ/t) | N42: =$C$84/'ESG_CAPEX OPEX'!$B$7 -> 110000
B43: Useful heat demand (GJ) | C43: ='Task 1_ESG Roadmap'!C55 -> 300000 | D43: ='Task 1_ESG Roadmap'!D55 -> 336000 | E43: ='Task 1_ESG Roadmap'!E55 -> 413580 | F43: ='Task 1_ESG Roadmap'!F55 -> 516975 | G43: ='Task 1_ESG Roadmap'!G55 -> 457577.93 | H43: ='Task 1_ESG Roadmap'!H55 -> 366062.34 | J43: Biomass blend: VND per GJ (70% rice husk, 30% wood) | N43: ='ESG_CAPEX OPEX'!B10/'ESG_CAPEX OPEX'!B8*$C$85+'ESG_CAPEX OPEX'!B11/'ESG_CAPEX OPEX'!B9*$C$86 -> 145312.5
B44: Share of year biomass system in service | C44: ='Task 1_ESG Roadmap'!C61 -> 0 | D44: ='Task 1_ESG Roadmap'!D61 -> 0.75342466 | E44: ='Task 1_ESG Roadmap'!E61 -> 1 | F44: ='Task 1_ESG Roadmap'!F61 -> 1 | G44: ='Task 1_ESG Roadmap'!G61 -> 1 | H44: ='Task 1_ESG Roadmap'!H61 -> 1 | J44: Biomass tonnes per GJ of heat (0.7 ÷ 16 + 0.3 ÷ 18) | N44: ='ESG_CAPEX OPEX'!B10/'ESG_CAPEX OPEX'!B8+'ESG_CAPEX OPEX'!B11/'ESG_CAPEX OPEX'!B9 -> 0.060416667
B45: Annual average biomass share of heat | C45: ='Task 1_ESG Roadmap'!C65 -> 0 | D45: ='Task 1_ESG Roadmap'!D65 -> 0.3390411 | E45: ='Task 1_ESG Roadmap'!E65 -> 0.6 | F45: ='Task 1_ESG Roadmap'!F65 -> 0.8 | G45: ='Task 1_ESG Roadmap'!G65 -> 0.8 | H45: ='Task 1_ESG Roadmap'!H65 -> 0.8 | J45: Fuel-handling labour per FTE, VND/yr (B39 ÷ 3) | N45: ='ESG_CAPEX OPEX'!B39/$C$89 -> 140000000
B46: Coal burned (t) | C46: ='Task 1_ESG Roadmap'!C69 -> 12000 | D46: ='Task 1_ESG Roadmap'!D69 -> 8883.2877 | E46: ='Task 1_ESG Roadmap'!E69 -> 6617.28 | F46: ='Task 1_ESG Roadmap'!F69 -> 4135.8 | G46: ='Task 1_ESG Roadmap'!G69 -> 3660.6234 | H46: ='Task 1_ESG Roadmap'!H69 -> 2928.4987 | J46: Tonnes handled by 3 FTE per year (E35 + E36) | N46: ='ESG_CAPEX OPEX'!E35+'ESG_CAPEX OPEX'!E36 -> 18125
B47: Rice husk pellet burned (t) | C47: ='Task 1_ESG Roadmap'!C70 -> 0 | D47: ='Task 1_ESG Roadmap'!D70 -> 4983.9041 | E47: ='Task 1_ESG Roadmap'!E70 -> 10856.475 | F47: ='Task 1_ESG Roadmap'!F70 -> 18094.125 | G47: ='Task 1_ESG Roadmap'!G70 -> 16015.228 | H47: ='Task 1_ESG Roadmap'!H70 -> 12812.182
B48: Wood pellet burned (t) | C48: ='Task 1_ESG Roadmap'!C71 -> 0 | D48: ='Task 1_ESG Roadmap'!D71 -> 1898.6301 | E48: ='Task 1_ESG Roadmap'!E71 -> 4135.8 | F48: ='Task 1_ESG Roadmap'!F71 -> 6893 | G48: ='Task 1_ESG Roadmap'!G71 -> 6101.0391 | H48: ='Task 1_ESG Roadmap'!H71 -> 4880.8312 | J48: Reconciliation with the case OPEX table
B49: Coal-equivalent for the same heat (t), cost already in COGS | C49: =C43/'ESG_CAPEX OPEX'!$B$7 -> 12000 | D49: =D43/'ESG_CAPEX OPEX'!$B$7 -> 13440 | E49: =E43/'ESG_CAPEX OPEX'!$B$7 -> 16543.2 | F49: =F43/'ESG_CAPEX OPEX'!$B$7 -> 20679 | G49: =G43/'ESG_CAPEX OPEX'!$B$7 -> 18303.117 | H49: =H43/'ESG_CAPEX OPEX'!$B$7 -> 14642.494 | J49: Same build-up at the case basis (300,000 GJ, 100% biomass, full CAPEX, 3 FTE), VND | N49: ='ESG_CAPEX OPEX'!$B$6*($N$43-$N$42)+'ESG_CAPEX OPEX'!$B$6*$N$44*$C$87+('ESG_CAPEX OPEX'!$B$6*$N$44-'ESG_CAPEX OPEX'!$B$6/'ESG_CAPEX OPEX'!$B$7)*$C$88+$C$89*$N$45+('Task 1_ESG Roadmap'!$C$107*$C$90*$C$83-$C$91)+$C$92+$C$93+$C$94 -> 14833318750
B50: Variable cost | J50: Equals ESG_CAPEX OPEX F45? | N50: =IF(ABS(N49-'ESG_CAPEX OPEX'!F45)<1,"OK","CHECK") -> OK
B51: Fuel cost at the actual mix | C51: =C46*$C$84+C47*$C$85+C48*$C$86 -> 33000000000 | D51: =D46*$C$84+D47*$C$85+D48*$C$86 -> 40982722603 | E51: =E46*$C$84+E47*$C$85+E48*$C$86 -> 54256526250 | F51: =F46*$C$84+F47*$C$85+F48*$C$86 -> 71471793750 | G51: =G46*$C$84+G47*$C$85+G48*$C$86 -> 63260148692 | H51: =H46*$C$84+H47*$C$85+H48*$C$86 -> 50608118954 | J51: ESG_CAPEX OPEX F45 = 14,833,318,750 VND. The same delta logic (biomass minus coal for the same heat) is applied year by year with the Task 1 fuel mix.
B52: Fuel cost at the coal-equivalent (inside base COGS) | C52: =C49*$C$84 -> 33000000000 | D52: =D49*$C$84 -> 36960000000 | E52: =E49*$C$84 -> 45493800000 | F52: =F49*$C$84 -> 56867250000 | G52: =G49*$C$84 -> 50333572196 | H52: =H49*$C$84 -> 40266857757
B53: Incremental fuel cost | C53: =C51-C52 -> 0 | D53: =D51-D52 -> 4022722603 | E53: =E51-E52 -> 8762726250 | F53: =F51-F52 -> 14604543750 | G53: =G51-G52 -> 12926576496 | H53: =H51-H52 -> 10341261197
B54: Inbound biomass logistics | C54: =(C47+C48)*$C$87 -> 0 | D54: =(D47+D48)*$C$87 -> 1032380137 | E54: =(E47+E48)*$C$87 -> 2248841250 | F54: =(F47+F48)*$C$87 -> 3748068750 | G54: =(G47+G48)*$C$87 -> 3317439986 | H54: =(H47+H48)*$C$87 -> 2653951989
B55: Incremental ash disposal | C55: =(C46+C47+C48-C49)*$C$88 -> 0 | D55: =(D46+D47+D48-D49)*$C$88 -> 2.0932397e+08 | E55: =(E46+E47+E48-E49)*$C$88 -> 455971950 | F55: =(F46+F47+F48-F49)*$C$88 -> 759953250 | G55: =(G46+G47+G48-G49)*$C$88 -> 6.7263956e+08 | H55: =(H46+H47+H48-H49)*$C$88 -> 5.3811164e+08
B56: Variable incremental OPEX | C56: =C53+C54+C55 -> 0 | D56: =D53+D54+D55 -> 5264426712 | E56: =E53+E54+E55 -> 11467539450 | F56: =F53+F54+F55 -> 19112565750 | G56: =G53+G54+G55 -> 16916656037 | H56: =H53+H54+H55 -> 13533324830
B57: Fixed cost
B58: Fuel-handling crew (FTE) | C58: =IF(C44=0,0,ROUNDUP($C$89*(C47+C48)/C44/$N$46,0)) -> 0 | D58: =IF(D44=0,0,ROUNDUP($C$89*(D47+D48)/D44/$N$46,0)) -> 2 | E58: =IF(E44=0,0,ROUNDUP($C$89*(E47+E48)/E44/$N$46,0)) -> 3 | F58: =IF(F44=0,0,ROUNDUP($C$89*(F47+F48)/F44/$N$46,0)) -> 5 | G58: =IF(G44=0,0,ROUNDUP($C$89*(G47+G48)/G44/$N$46,0)) -> 4 | H58: =IF(H44=0,0,ROUNDUP($C$89*(H47+H48)/H44/$N$46,0)) -> 3
B59: Fuel-handling labour | C59: =C58*$N$45*C44 -> 0 | D59: =D58*$N$45*D44 -> 2.109589e+08 | E59: =E58*$N$45*E44 -> 420000000 | F59: =F58*$N$45*F44 -> 700000000 | G59: =G58*$N$45*G44 -> 560000000 | H59: =H58*$N$45*H44 -> 420000000
B60: Boiler maintenance above the coal baseline | C60: =0 -> 0 | D60: =IF(D44=0,0,('Task 1_ESG Roadmap'!I22*$C$90*$C$83-$C$91)*D44) -> 2.4224015e+08 | E60: =IF(E44=0,0,('Task 1_ESG Roadmap'!J22*$C$90*$C$83-$C$91)*E44) -> 349568750 | F60: =IF(F44=0,0,('Task 1_ESG Roadmap'!K22*$C$90*$C$83-$C$91)*F44) -> 349568750 | G60: =IF(G44=0,0,('Task 1_ESG Roadmap'!L22*$C$90*$C$83-$C$91)*G44) -> 349568750 | H60: =IF(H44=0,0,('Task 1_ESG Roadmap'!M22*$C$90*$C$83-$C$91)*H44) -> 349568750
B61: Emission monitoring/lab tests | C61: =0 -> 0 | D61: =$C$92 -> 60000000 | E61: =$C$92 -> 60000000 | F61: =$C$92 -> 60000000 | G61: =$C$92 -> 60000000 | H61: =$C$92 -> 60000000
B62: Insurance/safety inspection | C62: =$C$93*C44 -> 0 | D62: =$C$93*D44 -> 37671233 | E62: =$C$93*E44 -> 50000000 | F62: =$C$93*F44 -> 50000000 | G62: =$C$93*G44 -> 50000000 | H62: =$C$93*H44 -> 50000000
B63: Training/ESG audit | C63: =0 -> 0 | D63: =$C$94 -> 90000000 | E63: =$C$94 -> 90000000 | F63: =$C$94 -> 90000000 | G63: =$C$94 -> 90000000 | H63: =$C$94 -> 90000000
B64: Fixed incremental OPEX | C64: =SUM(C59:C63) -> 0 | D64: =SUM(D59:D63) -> 6.4087029e+08 | E64: =SUM(E59:E63) -> 969568750 | F64: =SUM(F59:F63) -> 1249568750 | G64: =SUM(G59:G63) -> 1109568750 | H64: =SUM(H59:H63) -> 969568750
B65: Total
B66: Total incremental ESG OPEX (VND) | C66: =C56+C64 -> 0 | D66: =D56+D64 -> 5905297003 | E66: =E56+E64 -> 12437108200 | F66: =F56+F64 -> 20362134500 | G66: =G56+G64 -> 18026224787 | H66: =H56+H64 -> 14502893580
B67: Total incremental ESG OPEX (USD) → template row 50 | C67: =C66/$C$83 -> 0 | D67: =D66/$C$83 -> 231580.27 | E67: =E66/$C$83 -> 487729.73 | F67: =F66/$C$83 -> 798515.08 | G67: =G66/$C$83 -> 706910.78 | H67: =H66/$C$83 -> 568740.92
B68: Incremental ESG OPEX per piece (USD/pc) | C68: =C67/C11 -> 0 | D68: =D67/D11 -> 0.041188865 | E68: =E67/E11 -> 0.07047535 | F68: =F67/F11 -> 0.092306252 | G68: =G67/G11 -> 0.092324523 | H68: =H67/H11 -> 0.092848943
B70: Cash flow and funding of the roadmap (USD)
B71: USD unless stated | C71: 2026A | D71: 2027 | E71: 2028 | F71: 2029 | G71: 2030 | H71: 2031 | J71: Funding view
B72: Net profit | C72: =C29 -> 2088727.4 | D72: =D29 -> 2052324.4 | E72: =E29 -> 2470274.2 | F72: =F29 -> 3061159.6 | G72: =G29 -> 2652169.6 | H72: =H29 -> 2019646.5 | J72: ="Funding: the 2027 tranche (USD "&TEXT(D74,"#,##0")&") is covered "&TEXT(D79,"0.0")&"x by 2027 net profit plus depreciation, so no new debt is needed. Free cash flow is positive every year (lowest USD "&TEXT(MIN(D77:H77)/1000000,"0.00")&"M) and reaches USD "&TEXT(H78/1000000,"0.00")&"M by 2031 after funding the working capital that growth needs. Existing plant depreciation inside COGS is assumed reinvested as sustaining CAPEX." -> Funding: the 2027 tranche (USD 896,500) is covered 2.5x by 2027 net profit plus depreciation, so no new debt is needed. Free cash flow is positive every year (lowest USD 0.97M) and reaches USD 11.58M by 2031 after funding the working capital that growth needs. Existing plant depreciation inside COGS is assumed reinvested as sustaining CAPEX.
B73: Add back: ESG depreciation (non-cash) | C73: =C20 -> 0 | D73: =D20 -> 179300 | E73: =E20 -> 188100 | F73: =F20 -> 188100 | G73: =G20 -> 188100 | H73: =H20 -> 188100
B74: Less: ESG CAPEX paid (Task 1) | C74: =0 -> 0 | D74: ='Task 1_ESG Roadmap'!I21 -> 896500 | E74: ='Task 1_ESG Roadmap'!J21 -> 44000 | F74: ='Task 1_ESG Roadmap'!K21 -> 0 | G74: ='Task 1_ESG Roadmap'!L21 -> 0 | H74: ='Task 1_ESG Roadmap'!M21 -> 0
B75: Net working capital | C75: =$C$100/365*C15+($C$101-$C$102)/365*C16 -> 3007243.1 | D75: =$C$100/365*D15+($C$101-$C$102)/365*D16 -> 3368112.2 | E75: =$C$100/365*E15+($C$101-$C$102)/365*E16 -> 4145785.3 | F75: =$C$100/365*F15+($C$101-$C$102)/365*F16 -> 5182231.6 | G75: =$C$100/365*G15+($C$101-$C$102)/365*G16 -> 4586826.8 | H75: =$C$100/365*H15+($C$101-$C$102)/365*H16 -> 3669461.5
B76: Less: increase in net working capital | D76: =D75-C75 -> 360869.17 | E76: =E75-D75 -> 777673.06 | F76: =F75-E75 -> 1036446.3 | G76: =G75-F75 -> -595404.76 | H76: =H75-G75 -> -917365.37
B77: Free cash flow | D77: =D72+D73-D74-D76 -> 974255.27 | E77: =E72+E73-E74-E76 -> 1836701.1 | F77: =F72+F73-F74-F76 -> 2212813.2 | G77: =G72+G73-G74-G76 -> 3435674.4 | H77: =H72+H73-H74-H76 -> 3125111.9
B78: Cumulative free cash flow from 2027 | D78: =D77 -> 974255.27 | E78: =D78+E77 -> 2810956.4 | F78: =E78+F77 -> 5023769.6 | G78: =F78+G77 -> 8459444 | H78: =G78+H77 -> 11584556
B79: Cash cover: (net profit + depreciation) ÷ CAPEX | D79: =IF(D74=0,"n/a",(D72+D73)/D74) -> 2.4892632 | E79: =IF(E74=0,"n/a",(E72+E73)/E74) -> 60.417595 | F79: =IF(F74=0,"n/a",(F72+F73)/F74) -> n/a | G79: =IF(G74=0,"n/a",(G72+G73)/G74) -> n/a | H79: =IF(H74=0,"n/a",(H72+H73)/H74) -> n/a
B81: Inputs and their basis
B82: Parameter | C82: Value | D82: Unit | E82: Basis / source
B83: FX rate | C83: 25500 | D83: VND/USD | E83: Case rate embedded in ESG_CAPEX OPEX E40 (CAPEX × 2.5% × 25,500) and Logistics Cost 2027 F8 ('~25,500 VND/USD'). Held flat; ±5% tested in Task 5 (R13).
B84: Coal price | C84: 2750000 | D84: VND/t | E84: ESG_CAPEX OPEX D37 (coal t × 2,750,000), the midpoint of the 2.5–3.0M VND/t range in Fuel comparison B5.
B85: Rice husk pellet price | C85: ='ESG_CAPEX OPEX'!B12 -> 1950000 | D85: VND/t | E85: ESG_CAPEX OPEX B12.
B86: Wood pellet price | C86: ='ESG_CAPEX OPEX'!B13 -> 3600000 | D86: VND/t | E86: ESG_CAPEX OPEX B13.
B87: Inbound biomass logistics | C87: ='ESG_CAPEX OPEX'!B38 -> 150000 | D87: VND/t biomass | E87: ESG_CAPEX OPEX B38.
B88: Ash disposal | C88: ='ESG_CAPEX OPEX'!B42 -> 90000 | D88: VND/t fuel | E88: ESG_CAPEX OPEX B42.
B89: Fuel-handling crew in the case basis | C89: 3 | D89: FTE | E89: ESG_CAPEX OPEX H39 ('3 FTE equivalent'); crew grows in whole FTE with run-rate tonnage.
B90: Biomass boiler maintenance & refractory | C90: ='ESG_CAPEX OPEX'!B40 -> 0.025 | D90: % of CAPEX/yr | E90: ESG_CAPEX OPEX B40, applied to the CAPEX in service (Task 1).
B91: Coal boiler maintenance replaced by it | C91: ='ESG_CAPEX OPEX'!D40 -> 250000000 | D91: VND/yr | E91: ESG_CAPEX OPEX D40: today inside base COGS, so only the excess is incremental.
B92: Incremental emission monitoring/lab tests | C92: ='ESG_CAPEX OPEX'!E41-'ESG_CAPEX OPEX'!D41 -> 60000000 | D92: VND/yr | E92: E41 − D41; full year from 2027 (metering in service 1 Jan 2027, Task 1).
B93: Incremental insurance/safety inspection | C93: ='ESG_CAPEX OPEX'!E43-'ESG_CAPEX OPEX'!D43 -> 50000000 | D93: VND/yr | E93: E43 − D43; pro rata from the biomass in-service date.
B94: Incremental training/ESG audit | C94: ='ESG_CAPEX OPEX'!E44-'ESG_CAPEX OPEX'!D44 -> 90000000 | D94: VND/yr | E94: E44 − D44; full year from 2027 (traceability set-up Feb 2027; annual buyer audit).
B95: Selling & commercial cost | C95: 0.025 | D95: % of revenue | E95: Peer benchmark: May Sông Hồng (MSH) selling expenses 2.7–3.1% of net revenue, H1-2023 to H1-2024 (FireAnt, 28/06/2024). Set slightly lower because under EXW the buyer pays the main freight (EXW Price D18).
B96: General & administrative cost (2026 base) | C96: 0.045 | D96: % of 2026 revenue | E96: MSH G&A 4.8–5.6% of revenue (same source); TNG total SG&A 5.4% of revenue in Q4-2025 (BSC, 21/01/2026). Selling + G&A = 7.0%, inside the 5.4–8.5% peer range.
B97: Fixed share of G&A | C97: 0.5 | D97: % of G&A | E97: Team assumption: management and compliance overhead does not move with volume in the short run; half is fixed, half scales with revenue.
B98: Corporate income tax rate | C98: 0.2 | D98: % of profit | E98: Law on CIT No. 67/2025/QH15, Art. 10(1), in force from 1 Oct 2025. No ESG tax incentive assumed (conservative).
B99: Interest on ESG funding | C99: 0 | D99: USD/yr | E99: Internal cash: 2026 gross profit USD 3.96M (EXW Price B14) is 4.2x the USD 0.94M envelope ('Can it fund ESG investment?', EXW Price E14).
B100: Receivable days | C100: 45 | D100: days of revenue | E100: Team assumption: apparel buyers commonly pay by T/T 30–60 days after pickup; midpoint used.
B101: Inventory days | C101: 45 | D101: days of COGS | E101: Team assumption: about 1.5 months of fabric, WIP and finished goods for a 5-SKU programme.
B102: Payable days | C102: 30 | D102: days of COGS | E102: Team assumption: 30-day supplier credit on fabric, trims and fuel (biomass priced quarterly, R03).
B104: Assumptions and how conflicts or missing data are resolved
B105: Issue | C105: Assumption adopted | J105: Basis / why it is reasonable
B106: Energy cost already in COGS | C106: COGS F13 'ESG energy allocation' is read as today’s thermal-energy cost per piece (coal basis). The project adds only its cost above the coal-equivalent fuel for the same heat. | J106: COGS B22 ('energy allocation is embedded in product COGS'); Table 03 OPEX rule; ESG_CAPEX OPEX F37:F45 uses the same delta logic and is reconciled above.
...

Sheet Task 4_ESG vs Traditional
B1: TASK 4 - ESG PATHWAY VS TRADITIONAL AND THE REVENUE AT RISK FROM DELAY
B2: Requirement 4: compare the ESG pathway with the Traditional / No-ESG trajectory and quantify the revenue at risk if the investment is delayed. Each path is valued at its own price: the ESG/traceability premium applies only while the roadmap is active.
B4: REVENUE AT RISK WITHOUT ESG | C4: DELAY 1 YEAR | E4: DELAY 2 YEARS | G4: EXTRA NET PROFIT ON THE ESG PATHWAY | J4: PAYBACK VS STAYING ON COAL | M4: TRADITIONAL ORDERS 2031
B5: =I20 -> 69566894 | C5: =I58 -> 21018223 | E5: =I59 -> 40647630 | G5: =I35 -> 6590768.2 | J5: =C41 -> 2030 | M5: =H14/C14-1 -> -0.513613
B6: 2027–2031 vs the ESG pathway | C6: ="Revenue at risk; gross profit "&TEXT(I62/1000000,"0.0")&"M" -> Revenue at risk; gross profit 4.6M | E6: ="Revenue at risk; gross profit "&TEXT(I63/1000000,"0.0")&"M" -> Revenue at risk; gross profit 8.8M | G6: After all ESG OPEX and depreciation, 2027–2031 | J6: Cumulative incremental free cash flow ≥ 0 | M6: vs 2026; coal plant breaches the caps every year
B8: Head-to-head: ESG pathway vs Traditional / No-ESG, 2026–2031
B9: Metric | C9: 2026 | D9: 2027 | E9: 2028 | F9: 2029 | G9: 2030 | H9: 2031 | I9: Total 2027–2031 | J9: Reading the result
B10: Sales volume (pcs) | J10: ="1. Without ESG, LSC orders fall to "&TEXT(H14/1000000,"0.00")&"M pcs by 2031 ("&TEXT(H14/C14-1,"0%")&" vs 2026), and the coal plant breaches the buyer intensity cap in every year from 2027, so even that volume is exposed to reallocation (Emission Target H7:H11)." -> 1. Without ESG, LSC orders fall to 2.44M pcs by 2031 (-51% vs 2026), and the coal plant breaches the buyer intensity cap in every year from 2027, so even that volume is exposed to reallocation (Emission Target H7:H11).
B11: ESG: LSC orders (potential 2027–2029, forecast 2030–2031) | C11: ='Task 2_Conversion & Forecast'!C11 -> 5020000 | D11: ='Task 2_Conversion & Forecast'!D11 -> 6124400 | E11: ='Task 2_Conversion & Forecast'!E11 -> 7655500 | F11: ='Task 2_Conversion & Forecast'!F11 -> 9799040 | G11: ='Task 2_Conversion & Forecast'!G11 -> 10419646 | H11: ='Task 2_Conversion & Forecast'!H11 -> 11079557
B12: ESG: realized sales | C12: ='Task 2_Conversion & Forecast'!C19 -> 5020000 | D12: ='Task 2_Conversion & Forecast'!D19 -> 5622400 | E12: ='Task 2_Conversion & Forecast'!E19 -> 6920572 | F12: ='Task 2_Conversion & Forecast'!F19 -> 8650715 | G12: ='Task 2_Conversion & Forecast'!G19 -> 7656804 | H12: ='Task 2_Conversion & Forecast'!H19 -> 6125443.2 | I12: =SUM(D12:H12) -> 34975934
B13: Traditional: order change vs prior year | D13: ='Sales Forecast & Case 2A KPI'!B10 -> -0.1 | E13: ='Sales Forecast & Case 2A KPI'!B11 -> -0.12 | F13: ='Sales Forecast & Case 2A KPI'!B12 -> -0.15 | G13: =$C$98 -> -0.15 | H13: =$C$98 -> -0.15
B14: Traditional: order volume | C14: ='Sales Forecast & Case 2A KPI'!C21 -> 5020000 | D14: ='Sales Forecast & Case 2A KPI'!G21 -> 4518000 | E14: ='Sales Forecast & Case 2A KPI'!H21 -> 3975840 | F14: ='Sales Forecast & Case 2A KPI'!I21 -> 3379464 | G14: =F14*(1+G13) -> 2872544.4 | H14: =G14*(1+H13) -> 2441662.7 | I14: =SUM(D14:H14) -> 17187511
B15: Volume gap: ESG − Traditional | C15: =C12-C14 -> 0 | D15: =D12-D14 -> 1104400 | E15: =E12-E14 -> 2944732 | F15: =F12-F14 -> 5271251 | G15: =G12-G14 -> 4784259.6 | H15: =H12-H14 -> 3683780.5 | I15: =SUM(D15:H15) -> 17788423
B16: ESG ÷ Traditional (×) | C16: =C12/C14 -> 1 | D16: =D12/D14 -> 1.2444444 | E16: =E12/E14 -> 1.7406566 | F16: =F12/F14 -> 2.5597891 | G16: =G12/G14 -> 2.6655129 | H16: =H12/H14 -> 2.508718
B17: Revenue (USD) | J17: ="2. Revenue at risk without ESG is USD "&TEXT(I20/1000000,"0.0")&"M over 2027–2031; "&TEXT(I22/I20,"0%")&" is the lost ESG premium and the rest lost volume. In 2029 alone it is USD "&TEXT(F20/1000000,"0.0")&"M, "&TEXT(F23,"0%")&" of ESG-pathway revenue." -> 2. Revenue at risk without ESG is USD 69.6M over 2027–2031; 4% is the lost ESG premium and the rest lost volume. In 2029 alone it is USD 20.5M, 62% of ESG-pathway revenue.
B18: ESG pathway revenue (Task 3) | C18: ='Task 3_P&L'!C15 -> 19284264 | D18: ='Task 3_P&L'!D15 -> 21598376 | E18: ='Task 3_P&L'!E15 -> 26585286 | F18: ='Task 3_P&L'!F15 -> 33231608 | G18: ='Task 3_P&L'!G15 -> 29413512 | H18: ='Task 3_P&L'!H15 -> 23530809 | I18: =SUM(D18:H18) -> 1.3435959e+08
B19: Traditional revenue (base EXW price, no premium) | C19: ='Task 3_P&L'!C15 -> 19284264 | D19: =D14*$C$95 -> 17031751 | E19: =E14*$C$95 -> 14987941 | F19: =F14*$C$95 -> 12739750 | G19: =G14*$C$95 -> 10828787 | H19: =H14*$C$95 -> 9204469 | I19: =SUM(D19:H19) -> 64792697
B20: Revenue at risk without ESG | C20: =C18-C19 -> 0 | D20: =D18-D19 -> 4566624.8 | E20: =E18-E19 -> 11597346 | F20: =F18-F19 -> 20491858 | G20: =G18-G19 -> 18584725 | H20: =H18-H19 -> 14326340 | I20: =SUM(D20:H20) -> 69566894
B21: of which lost volume | D21: =(D12-D14)*$C$95 -> 4163316.8 | E21: =(E12-E14)*$C$95 -> 11100917 | F21: =(F12-F14)*$C$95 -> 19871322 | G21: =(G12-G14)*$C$95 -> 18035484 | H21: =(H12-H14)*$C$95 -> 13886948 | I21: =SUM(D21:H21) -> 67057988
B22: of which lost ESG premium | D22: =D12*($C$94-$C$95) -> 403307.99 | E22: =E12*($C$94-$C$95) -> 496428.92 | F22: =F12*($C$94-$C$95) -> 620536.15 | G22: =G12*($C$94-$C$95) -> 549240.57 | H22: =H12*($C$94-$C$95) -> 439392.46 | I22: =SUM(D22:H22) -> 2508906.1
B23: Revenue at risk as % of ESG revenue | C23: =C20/C18 -> 0 | D23: =D20/D18 -> 0.21143372 | E23: =E20/E18 -> 0.43623174 | F23: =F20/F18 -> 0.61663758 | G23: =G20/G18 -> 0.63184311 | H23: =H20/H18 -> 0.6088333
B24: ESG revenue vs 2026 (×) | C24: =C18/C$18 -> 1 | D24: =D18/C$18 -> 1.12 | E24: =E18/C$18 -> 1.3786 | F24: =F18/C$18 -> 1.72325 | G24: =G18/C$18 -> 1.5252598 | H24: =H18/C$18 -> 1.2202078 | J24: ="3. After all ESG OPEX and depreciation the ESG pathway earns USD "&TEXT(I35/1000000,"0.0")&"M more net profit than Traditional, and the investment (CAPEX plus the working capital that growth needs) pays back in "&C41&" on incremental free cash flow." -> 3. After all ESG OPEX and depreciation the ESG pathway earns USD 6.6M more net profit than Traditional, and the investment (CAPEX plus the working capital that growth needs) pays back in 2030 on incremental free cash flow.
B25: Traditional revenue vs 2026 (×) | C25: =C19/C$19 -> 1 | D25: =D19/C$19 -> 0.88319424 | E25: =E19/C$19 -> 0.77721093 | F25: =F19/C$19 -> 0.66062929 | G25: =G19/C$19 -> 0.5615349 | H25: =H19/C$19 -> 0.47730466
B26: Profit and cash (USD)
B27: ESG pathway net profit (Task 3) | C27: ='Task 3_P&L'!C29 -> 2088727.4 | D27: ='Task 3_P&L'!D29 -> 2052324.4 | E27: ='Task 3_P&L'!E29 -> 2470274.2 | F27: ='Task 3_P&L'!F29 -> 3061159.6 | G27: ='Task 3_P&L'!G29 -> 2652169.6 | H27: ='Task 3_P&L'!H29 -> 2019646.5 | I27: =SUM(D27:H27) -> 12255574
B28: ESG pathway NPM | C28: ='Task 3_P&L'!C30 -> 0.10831253 | D28: ='Task 3_P&L'!D30 -> 0.095022167 | E28: ='Task 3_P&L'!E30 -> 0.092918848 | F28: ='Task 3_P&L'!F30 -> 0.092115903 | G28: ='Task 3_P&L'!G30 -> 0.090168412 | H28: ='Task 3_P&L'!H30 -> 0.085829879
B29: Traditional gross profit | C29: =C19-C14*$C$97 -> 3960807.7 | D29: =D19-D14*$C$97 -> 3240640.1 | E29: =E19-E14*$C$97 -> 2851763.3 | F29: =F19-F14*$C$97 -> 2423998.8 | G29: =G19-G14*$C$97 -> 2060399 | H29: =H19-H14*$C$97 -> 1751339.1
B30: Traditional SG&A (same rule as Task 3) | C30: ='Task 3_P&L'!$C$95*C19+'Task 3_P&L'!$C$96*'Task 3_P&L'!$C$15*('Task 3_P&L'!$C$97+(1-'Task 3_P&L'!$C$97)*C19/'Task 3_P&L'!$C$15) -> 1349898.5 | D30: ='Task 3_P&L'!$C$95*D19+'Task 3_P&L'!$C$96*'Task 3_P&L'!$C$15*('Task 3_P&L'!$C$97+(1-'Task 3_P&L'!$C$97)*D19/'Task 3_P&L'!$C$15) -> 1242904.1 | E30: ='Task 3_P&L'!$C$95*E19+'Task 3_P&L'!$C$96*'Task 3_P&L'!$C$15*('Task 3_P&L'!$C$97+(1-'Task 3_P&L'!$C$97)*E19/'Task 3_P&L'!$C$15) -> 1145823.1 | F30: ='Task 3_P&L'!$C$95*F19+'Task 3_P&L'!$C$96*'Task 3_P&L'!$C$15*('Task 3_P&L'!$C$97+(1-'Task 3_P&L'!$C$97)*F19/'Task 3_P&L'!$C$15) -> 1039034 | G30: ='Task 3_P&L'!$C$95*G19+'Task 3_P&L'!$C$96*'Task 3_P&L'!$C$15*('Task 3_P&L'!$C$97+(1-'Task 3_P&L'!$C$97)*G19/'Task 3_P&L'!$C$15) -> 948263.32 | H30: ='Task 3_P&L'!$C$95*H19+'Task 3_P&L'!$C$96*'Task 3_P&L'!$C$15*('Task 3_P&L'!$C$97+(1-'Task 3_P&L'!$C$97)*H19/'Task 3_P&L'!$C$15) -> 871108.22
B31: Traditional EBIT | C31: =C29-C30 -> 2610909.2 | D31: =D29-D30 -> 1997736 | E31: =E29-E30 -> 1705940.2 | F31: =F29-F30 -> 1384964.8 | G31: =G29-G30 -> 1112135.7 | H31: =H29-H30 -> 880230.93 | J31: ="4. Delay: one year puts USD "&TEXT(I58/1000000,"0.0")&"M of revenue at risk ("&TEXT(I62/1000000,"0.0")&"M gross profit); two years, USD "&TEXT(I59/1000000,"0.0")&"M ("&TEXT(I63/1000000,"0.0")&"M). The loss almost doubles with the second year because orders erode first and the ramp then restarts from a lower base." -> 4. Delay: one year puts USD 21.0M of revenue at risk (4.6M gross profit); two years, USD 40.6M (8.8M). The loss almost doubles with the second year because orders erode first and the ramp then restarts from a lower base.
B32: Traditional CIT | C32: =MAX(0,C31)*'Task 3_P&L'!$C$98 -> 522181.84 | D32: =MAX(0,D31)*'Task 3_P&L'!$C$98 -> 399547.21 | E32: =MAX(0,E31)*'Task 3_P&L'!$C$98 -> 341188.04 | F32: =MAX(0,F31)*'Task 3_P&L'!$C$98 -> 276992.96 | G32: =MAX(0,G31)*'Task 3_P&L'!$C$98 -> 222427.13 | H32: =MAX(0,H31)*'Task 3_P&L'!$C$98 -> 176046.19
B33: Traditional net profit | C33: =C31-C32 -> 2088727.4 | D33: =D31-D32 -> 1598188.8 | E33: =E31-E32 -> 1364752.2 | F33: =F31-F32 -> 1107971.8 | G33: =G31-G32 -> 889708.54 | H33: =H31-H32 -> 704184.75 | I33: =SUM(D33:H33) -> 5664806.1
B34: Traditional NPM | C34: =C33/C19 -> 0.10831253 | D34: =D33/D19 -> 0.093835852 | E34: =E33/E19 -> 0.091056683 | F34: =F33/F19 -> 0.086969671 | G34: =G33/G19 -> 0.082161421 | H34: =H33/H19 -> 0.076504657
B35: Net profit gained on the ESG pathway | C35: =C27-C33 -> 0 | D35: =D27-D33 -> 454135.61 | E35: =E27-E33 -> 1105522 | F35: =F27-F33 -> 1953187.7 | G35: =G27-G33 -> 1762461.1 | H35: =H27-H33 -> 1315461.8 | I35: =SUM(D35:H35) -> 6590768.2
B36: Traditional net working capital | C36: ='Task 3_P&L'!$C$100/365*C19+('Task 3_P&L'!$C$101-'Task 3_P&L'!$C$102)/365*C14*$C$97 -> 3007243.1 | D36: ='Task 3_P&L'!$C$100/365*D19+('Task 3_P&L'!$C$101-'Task 3_P&L'!$C$102)/365*D14*$C$97 -> 2666562.9 | E36: ='Task 3_P&L'!$C$100/365*E19+('Task 3_P&L'!$C$101-'Task 3_P&L'!$C$102)/365*E14*$C$97 -> 2346575.3 | F36: ='Task 3_P&L'!$C$100/365*F19+('Task 3_P&L'!$C$101-'Task 3_P&L'!$C$102)/365*F14*$C$97 -> 1994589 | G36: ='Task 3_P&L'!$C$100/365*G19+('Task 3_P&L'!$C$101-'Task 3_P&L'!$C$102)/365*G14*$C$97 -> 1695400.7 | H36: ='Task 3_P&L'!$C$100/365*H19+('Task 3_P&L'!$C$101-'Task 3_P&L'!$C$102)/365*H14*$C$97 -> 1441090.6
B37: Traditional free cash flow | D37: =D33-(D36-C36) -> 1938869 | E37: =E33-(E36-D36) -> 1684739.7 | F37: =F33-(F36-E36) -> 1459958.1 | G37: =G33-(G36-F36) -> 1188896.9 | H37: =H33-(H36-G36) -> 958494.85 | I37: =SUM(D37:H37) -> 7230958.6
B38: ESG pathway free cash flow (Task 3) | D38: ='Task 3_P&L'!D77 -> 974255.27 | E38: ='Task 3_P&L'!E77 -> 1836701.1 | F38: ='Task 3_P&L'!F77 -> 2212813.2 | G38: ='Task 3_P&L'!G77 -> 3435674.4 | H38: ='Task 3_P&L'!H77 -> 3125111.9 | I38: =SUM(D38:H38) -> 11584556 | J38: 5. The delay loss sits in the ramp years: by 2031 every converting path reaches the same carbon-allowed capacity (Task 2), so a delay destroys the 2027–2030 allocation that LSC decides at its annual reviews and the 2029 strategic checkpoint (Emission Target G9, B19).
B39: Incremental free cash flow of the ESG pathway | D39: =D38-D37 -> -964613.77 | E39: =E38-E37 -> 151961.4 | F39: =F38-F37 -> 752855.12 | G39: =G38-G37 -> 2246777.5 | H39: =H38-H37 -> 2166617 | I39: =SUM(D39:H39) -> 4353597.3
B40: Cumulative incremental free cash flow | D40: =D39 -> -964613.77 | E40: =D40+E39 -> -812652.37 | F40: =E40+F39 -> -59797.253 | G40: =F40+G39 -> 2186980.3 | H40: =G40+H39 -> 4353597.3
B41: Payback year (cumulative incremental FCF turns positive) | C41: =IF(D40>=0,$D$9,IF(E40>=0,$E$9,IF(F40>=0,$F$9,IF(G40>=0,$G$9,IF(H40>=0,$H$9,"After 2031"))))) -> 2030
B42: Buyer compliance
B43: Traditional: heat demand (GJ) | C43: =C14*$C$99 -> 300000 | D43: =D14*$C$99 -> 270000 | E43: =E14*$C$99 -> 237600 | F43: =F14*$C$99 -> 201960 | G43: =G14*$C$99 -> 171666 | H43: =H14*$C$99 -> 145916.1
B44: Traditional: CO2e on 100% coal (t) | C44: =C43*$C$100/1000 -> 28380 | D44: =D43*$C$100/1000 -> 25542 | E44: =E43*$C$100/1000 -> 22476.96 | F44: =F43*$C$100/1000 -> 19105.416 | G44: =G43*$C$100/1000 -> 16239.604 | H44: =H43*$C$100/1000 -> 13803.663
B45: Buyer cap: maximum annual CO2e (t) | C45: ='Emission Target'!D6 -> 28380 | D45: ='Emission Target'!D7 -> 24123 | E45: ='Emission Target'!D8 -> 19866 | F45: ='Emission Target'!D9 -> 15609 | G45: ='Emission Target'!D10 -> 12771 | H45: ='Emission Target'!D11 -> 10216.8
B46: Buyer cap: maximum CO2e intensity (kg/GJ) | C46: ='Emission Target'!E6 -> 94.6 | D46: ='Emission Target'!E7 -> 80.41 | E46: ='Emission Target'!E8 -> 66.22 | F46: ='Emission Target'!E9 -> 52.03 | G46: ='Emission Target'!E10 -> 42.57 | H46: ='Emission Target'!E11 -> 34.056
B47: Traditional: buyer compliance | C47: Baseline | D47: =IF(AND(D44<=D45+0.5,$C$100<=D46+0.05),"Compliant","NOT compliant") -> NOT compliant | E47: =IF(AND(E44<=E45+0.5,$C$100<=E46+0.05),"Compliant","NOT compliant") -> NOT compliant | F47: =IF(AND(F44<=F45+0.5,$C$100<=F46+0.05),"Compliant","NOT compliant") -> NOT compliant | G47: =IF(AND(G44<=G45+0.5,$C$100<=G46+0.05),"Compliant","NOT compliant") -> NOT compliant | H47: =IF(AND(H44<=H45+0.5,$C$100<=H46+0.05),"Compliant","NOT compliant") -> NOT compliant
B48: ESG pathway: buyer compliance (Task 1) | C48: ='Task 1_ESG Roadmap'!C78 -> Baseline | D48: ='Task 1_ESG Roadmap'!D78 -> Compliant | E48: ='Task 1_ESG Roadmap'!E78 -> Compliant | F48: ='Task 1_ESG Roadmap'!F78 -> Compliant | G48: ='Task 1_ESG Roadmap'!G78 -> Compliant | H48: ='Task 1_ESG Roadmap'!H78 -> Compliant
B50: Revenue at risk from delaying the investment (the whole roadmap shifted right by one or two years)
B51: Metric | C51: 2026 | D51: 2027 | E51: 2028 | F51: 2029 | G51: 2030 | H51: 2031 | I51: Total 2027–2031 | J51: Delay mechanism
B52: Revenue by path (USD) | J52: Before conversion TEXIN stays on coal, misses the caps and its orders follow the Traditional erosion from the prior year. From the conversion year the ESG ramp restarts from that lower base (orders +22%, +25%, +28%, then the market rate, each discounted by the Task 2 conversion rate), capped by the carbon-allowed capacity at the 78% design mix. Each path is valued at its own price: the ESG premium applies only once the roadmap is active.
B53: No delay: conversion 2027 (= ESG pathway) | C53: =L72 -> 19284264 | D53: =L73 -> 21598376 | E53: =L74 -> 26585286 | F53: =L75 -> 33231608 | G53: =L76 -> 29413512 | H53: =L77 -> 23530809 | I53: =SUM(D53:H53) -> 1.3435959e+08
B54: Delay 1 year: conversion 2028 | C54: =L78 -> 19284264 | D54: =L79 -> 17031751 | E54: =L80 -> 19438538 | F54: =L81 -> 23926758 | G54: =L82 -> 29413512 | H54: =L83 -> 23530809 | I54: =SUM(D54:H54) -> 1.1334137e+08
B55: Delay 2 years: conversion 2029 | C55: =L84 -> 19284264 | D55: =L85 -> 17031751 | E55: =L86 -> 14987941 | F55: =L87 -> 17105913 | G55: =L88 -> 21055547 | H55: =L89 -> 23530809 | I55: =SUM(D55:H55) -> 93711961
B56: No ESG (Traditional) | C56: =C19 -> 19284264 | D56: =D19 -> 17031751 | E56: =E19 -> 14987941 | F56: =F19 -> 12739750 | G56: =G19 -> 10828787 | H56: =H19 -> 9204469 | I56: =SUM(D56:H56) -> 64792697
B57: Revenue at risk vs no delay (USD)
B58: Delay 1 year | C58: =C53-C54 -> 0 | D58: =D53-D54 -> 4566624.8 | E58: =E53-E54 -> 7146748.2 | F58: =F53-F54 -> 9304850.2 | G58: =G53-G54 -> 0 | H58: =H53-H54 -> 0 | I58: =SUM(D58:H58) -> 21018223
B59: Delay 2 years | C59: =C53-C55 -> 0 | D59: =D53-D55 -> 4566624.8 | E59: =E53-E55 -> 11597346 | F59: =F53-F55 -> 16125694 | G59: =G53-G55 -> 8357965.1 | H59: =H53-H55 -> 0 | I59: =SUM(D59:H59) -> 40647630
B60: No ESG | C60: =C53-C56 -> 0 | D60: =D53-D56 -> 4566624.8 | E60: =E53-E56 -> 11597346 | F60: =F53-F56 -> 20491858 | G60: =G53-G56 -> 18584725 | H60: =H53-H56 -> 14326340 | I60: =SUM(D60:H60) -> 69566894
B61: Gross profit at risk before ESG costs (USD)
B62: Delay 1 year | D62: =M73-M79 -> 1195464.5 | E62: =M74-M80 -> 1467875.3 | F62: =M75-M81 -> 1911129.3 | G62: =M76-M82 -> 0 | H62: =M77-M83 -> 0 | I62: =SUM(D62:H62) -> 4574469.1
B63: Delay 2 years | D63: =M73-M85 -> 1195464.5 | E63: =M74-M86 -> 2608606.1 | F63: =M75-M87 -> 3312067 | G63: =M76-M88 -> 1716648 | H63: =M77-M89 -> 0 | I63: =SUM(D63:H63) -> 8832785.6
B65: ESG ramp by roadmap year (from Task 2) | C65: Year 1 | D65: Year 2 | E65: Year 3 | F65: Year 4+ | J65: Scenario | M65: Conversion year | O65: Delay (years)
B66: Order growth (g ESG; market rate from year 4) | C66: ='Task 2_Conversion & Forecast'!D33 -> 0.22 | D66: ='Task 2_Conversion & Forecast'!E33 -> 0.25 | E66: ='Task 2_Conversion & Forecast'!F33 -> 0.28 | F66: ='Task 2_Conversion & Forecast'!G49 -> 0.063333333 | J66: No delay | M66: =2027+O66 -> 2027 | O66: 0
B67: Risk-adjusted conversion rate | C67: ='Task 2_Conversion & Forecast'!D42 -> 0.91803279 | D67: ='Task 2_Conversion & Forecast'!E42 -> 0.904 | E67: ='Task 2_Conversion & Forecast'!F42 -> 0.8828125 | F67: ='Task 2_Conversion & Forecast'!G51 -> 0.8828125 | J67: Delay 1 year | M67: =2027+O67 -> 2028 | O67: 1
J68: Delay 2 years | M68: =2027+O68 -> 2029 | O68: 2
B70: Delay engine: one block per scenario, years down the rows
B71: Scenario | C71: Year | D71: Roadmap year (0 = coal) | E71: Status | F71: LSC orders (pcs) | G71: Risk-adjusted demand (pcs) | H71: Share of year on biomass | I71: Carbon-allowed capacity (pcs) | J71: Realized sales (pcs) | K71: EXW price (USD/pc) | L71: Revenue (USD) | M71: Gross profit before ESG costs (USD) | N71: Buyer compliance
B72: No delay: conversion in 2027 (ESG pathway, Option A) | C72: 2026 | E72: Coal (actual) | F72: =C12 -> 5020000 | H72: 0 | J72: =C14 -> 5020000 | K72: ='Task 3_P&L'!C12 -> 3.8414868 | L72: =C18 -> 19284264 | M72: =L72-J72*$C$97 -> 3960807.7 | N72: Baseline
C73: 2027 | D73: =MAX(0,C73-2026-$O$66) -> 1 | E73: =IF(D73=0,"Coal, no ESG",IF(D73=1,"Converting","Biomass in service")) -> Converting | F73: =IF(D73=0,"",IF(D73=1,J72*(1+$C$66),F72*(1+INDEX($C$66:$F$66,MIN(D73,4))))) -> 6124400 | G73: =IF(D73=0,"",F73*INDEX($C$67:$F$67,MIN(D73,4))) -> 5622400 | H73: =IF(D73=0,0,IF(D73=1,$C$103,1)) -> 0.75342466 | I73: =IF(D73=0,"",D45*1000/($C$99*($C$100-$C$102*H73*($C$100-$C$101)))) -> 9100807.2 | J73: =IF(D73=0,J72*(1+D13),MIN(G73,I73)) -> 5622400 | K73: =IF(D73=0,$C$95,$C$94) -> 3.8414868 | L73: =J73*K73 -> 21598376 | M73: =L73-J73*$C$97 -> 4436104.6 | N73: =IF(D73=0,"NOT compliant",IF($C$100-$C$102*H73*($C$100-$C$101)<=D46+0.05,"Compliant","NOT compliant")) -> Compliant
C74: 2028 | D74: =MAX(0,C74-2026-$O$66) -> 2 | E74: =IF(D74=0,"Coal, no ESG",IF(D74=1,"Converting","Biomass in service")) -> Biomass in service | F74: =IF(D74=0,"",IF(D74=1,J73*(1+$C$66),F73*(1+INDEX($C$66:$F$66,MIN(D74,4))))) -> 7655500 | G74: =IF(D74=0,"",F74*INDEX($C$67:$F$67,MIN(D74,4))) -> 6920572 | H74: =IF(D74=0,0,IF(D74=1,$C$103,1)) -> 1 | I74: =IF(D74=0,"",E45*1000/($C$99*($C$100-$C$102*H74*($C$100-$C$101)))) -> 11910584 | J74: =IF(D74=0,J73*(1+E13),MIN(G74,I74)) -> 6920572 | K74: =IF(D74=0,$C$95,$C$94) -> 3.8414868 | L74: =J74*K74 -> 26585286 | M74: =L74-J74*$C$97 -> 5460369.5 | N74: =IF(D74=0,"NOT compliant",IF($C$100-$C$102*H74*($C$100-$C$101)<=E46+0.05,"Compliant","NOT compliant")) -> Compliant
C75: 2029 | D75: =MAX(0,C75-2026-$O$66) -> 3 | E75: =IF(D75=0,"Coal, no ESG",IF(D75=1,"Converting","Biomass in service")) -> Biomass in service | F75: =IF(D75=0,"",IF(D75=1,J74*(1+$C$66),F74*(1+INDEX($C$66:$F$66,MIN(D75,4))))) -> 9799040 | G75: =IF(D75=0,"",F75*INDEX($C$67:$F$67,MIN(D75,4))) -> 8650715 | H75: =IF(D75=0,0,IF(D75=1,$C$103,1)) -> 1 | I75: =IF(D75=0,"",F45*1000/($C$99*($C$100-$C$102*H75*($C$100-$C$101)))) -> 9358316 | J75: =IF(D75=0,J74*(1+F13),MIN(G75,I75)) -> 8650715 | K75: =IF(D75=0,$C$95,$C$94) -> 3.8414868 | L75: =J75*K75 -> 33231608 | M75: =L75-J75*$C$97 -> 6825461.8 | N75: =IF(D75=0,"NOT compliant",IF($C$100-$C$102*H75*($C$100-$C$101)<=F46+0.05,"Compliant","NOT compliant")) -> Compliant
C76: 2030 | D76: =MAX(0,C76-2026-$O$66) -> 4 | E76: =IF(D76=0,"Coal, no ESG",IF(D76=1,"Converting","Biomass in service")) -> Biomass in service | F76: =IF(D76=0,"",IF(D76=1,J75*(1+$C$66),F75*(1+INDEX($C$66:$F$66,MIN(D76,4))))) -> 10419646 | G76: =IF(D76=0,"",F76*INDEX($C$67:$F$67,MIN(D76,4))) -> 9198593.6 | H76: =IF(D76=0,0,IF(D76=1,$C$103,1)) -> 1 | I76: =IF(D76=0,"",G45*1000/($C$99*($C$100-$C$102*H76*($C$100-$C$101)))) -> 7656804 | J76: =IF(D76=0,J75*(1+G13),MIN(G76,I76)) -> 7656804 | K76: =IF(D76=0,$C$95,$C$94) -> 3.8414868 | L76: =J76*K76 -> 29413512 | M76: =L76-J76*$C$97 -> 6041260.6 | N76: =IF(D76=0,"NOT compliant",IF($C$100-$C$102*H76*($C$100-$C$101)<=G46+0.05,"Compliant","NOT compliant")) -> Compliant
C77: 2031 | D77: =MAX(0,C77-2026-$O$66) -> 5 | E77: =IF(D77=0,"Coal, no ESG",IF(D77=1,"Converting","Biomass in service")) -> Biomass in service | F77: =IF(D77=0,"",IF(D77=1,J76*(1+$C$66),F76*(1+INDEX($C$66:$F$66,MIN(D77,4))))) -> 11079557 | G77: =IF(D77=0,"",F77*INDEX($C$67:$F$67,MIN(D77,4))) -> 9781171.2 | H77: =IF(D77=0,0,IF(D77=1,$C$103,1)) -> 1 | I77: =IF(D77=0,"",H45*1000/($C$99*($C$100-$C$102*H77*($C$100-$C$101)))) -> 6125443.2 | J77: =IF(D77=0,J76*(1+H13),MIN(G77,I77)) -> 6125443.2 | K77: =IF(D77=0,$C$95,$C$94) -> 3.8414868 | L77: =J77*K77 -> 23530809 | M77: =L77-J77*$C$97 -> 4833008.5 | N77: =IF(D77=0,"NOT compliant",IF($C$100-$C$102*H77*($C$100-$C$101)<=H46+0.05,"Compliant","NOT compliant")) -> Compliant
B78: Delay 1 year: conversion in 2028 | C78: 2026 | E78: Coal (actual) | F78: =C12 -> 5020000 | H78: 0 | J78: =C14 -> 5020000 | K78: ='Task 3_P&L'!C12 -> 3.8414868 | L78: =C18 -> 19284264 | M78: =L78-J78*$C$97 -> 3960807.7 | N78: Baseline
C79: 2027 | D79: =MAX(0,C79-2026-$O$67) -> 0 | E79: =IF(D79=0,"Coal, no ESG",IF(D79=1,"Converting","Biomass in service")) -> Coal, no ESG | F79: =IF(D79=0,"",IF(D79=1,J78*(1+$C$66),F78*(1+INDEX($C$66:$F$66,MIN(D79,4))))) | G79: =IF(D79=0,"",F79*INDEX($C$67:$F$67,MIN(D79,4))) | H79: =IF(D79=0,0,IF(D79=1,$C$103,1)) -> 0 | I79: =IF(D79=0,"",D45*1000/($C$99*($C$100-$C$102*H79*($C$100-$C$101)))) | J79: =IF(D79=0,J78*(1+D13),MIN(G79,I79)) -> 4518000 | K79: =IF(D79=0,$C$95,$C$94) -> 3.7697545 | L79: =J79*K79 -> 17031751 | M79: =L79-J79*$C$97 -> 3240640.1 | N79: =IF(D79=0,"NOT compliant",IF($C$100-$C$102*H79*($C$100-$C$101)<=D46+0.05,"Compliant","NOT compliant")) -> NOT compliant
C80: 2028 | D80: =MAX(0,C80-2026-$O$67) -> 1 | E80: =IF(D80=0,"Coal, no ESG",IF(D80=1,"Converting","Biomass in service")) -> Converting | F80: =IF(D80=0,"",IF(D80=1,J79*(1+$C$66),F79*(1+INDEX($C$66:$F$66,MIN(D80,4))))) -> 5511960 | G80: =IF(D80=0,"",F80*INDEX($C$67:$F$67,MIN(D80,4))) -> 5060160 | H80: =IF(D80=0,0,IF(D80=1,$C$103,1)) -> 0.75342466 | I80: =IF(D80=0,"",E45*1000/($C$99*($C$100-$C$102*H80*($C$100-$C$101)))) -> 7494782.4 | J80: =IF(D80=0,J79*(1+E13),MIN(G80,I80)) -> 5060160 | K80: =IF(D80=0,$C$95,$C$94) -> 3.8414868 | L80: =J80*K80 -> 19438538 | M80: =L80-J80*$C$97 -> 3992494.1 | N80: =IF(D80=0,"NOT compliant",IF($C$100-$C$102*H80*($C$100-$C$101)<=E46+0.05,"Compliant","NOT compliant")) -> Compliant
C81: 2029 | D81: =MAX(0,C81-2026-$O$67) -> 2 | E81: =IF(D81=0,"Coal, no ESG",IF(D81=1,"Converting","Biomass in service")) -> Biomass in service | F81: =IF(D81=0,"",IF(D81=1,J80*(1+$C$66),F80*(1+INDEX($C$66:$F$66,MIN(D81,4))))) -> 6889950 | G81: =IF(D81=0,"",F81*INDEX($C$67:$F$67,MIN(D81,4))) -> 6228514.8 | H81: =IF(D81=0,0,IF(D81=1,$C$103,1)) -> 1 | I81: =IF(D81=0,"",F45*1000/($C$99*($C$100-$C$102*H81*($C$100-$C$101)))) -> 9358316 | J81: =IF(D81=0,J80*(1+F13),MIN(G81,I81)) -> 6228514.8 | K81: =IF(D81=0,$C$95,$C$94) -> 3.8414868 | L81: =J81*K81 -> 23926758 | M81: =L81-J81*$C$97 -> 4914332.5 | N81: =IF(D81=0,"NOT compliant",IF($C$100-$C$102*H81*($C$100-$C$101)<=F46+0.05,"Compliant","NOT compliant")) -> Compliant
C82: 2030 | D82: =MAX(0,C82-2026-$O$67) -> 3 | E82: =IF(D82=0,"Coal, no ESG",IF(D82=1,"Converting","Biomass in service")) -> Biomass in service | F82: =IF(D82=0,"",IF(D82=1,J81*(1+$C$66),F81*(1+INDEX($C$66:$F$66,MIN(D82,4))))) -> 8819136 | G82: =IF(D82=0,"",F82*INDEX($C$67:$F$67,MIN(D82,4))) -> 7785643.5 | H82: =IF(D82=0,0,IF(D82=1,$C$103,1)) -> 1 | I82: =IF(D82=0,"",G45*1000/($C$99*($C$100-$C$102*H82*($C$100-$C$101)))) -> 7656804 | J82: =IF(D82=0,J81*(1+G13),MIN(G82,I82)) -> 7656804 | K82: =IF(D82=0,$C$95,$C$94) -> 3.8414868 | L82: =J82*K82 -> 29413512 | M82: =L82-J82*$C$97 -> 6041260.6 | N82: =IF(D82=0,"NOT compliant",IF($C$100-$C$102*H82*($C$100-$C$101)<=G46+0.05,"Compliant","NOT compliant")) -> Compliant
C83: 2031 | D83: =MAX(0,C83-2026-$O$67) -> 4 | E83: =IF(D83=0,"Coal, no ESG",IF(D83=1,"Converting","Biomass in service")) -> Biomass in service | F83: =IF(D83=0,"",IF(D83=1,J82*(1+$C$66),F82*(1+INDEX($C$66:$F$66,MIN(D83,4))))) -> 9377681.3 | G83: =IF(D83=0,"",F83*INDEX($C$67:$F$67,MIN(D83,4))) -> 8278734.3 | H83: =IF(D83=0,0,IF(D83=1,$C$103,1)) -> 1 | I83: =IF(D83=0,"",H45*1000/($C$99*($C$100-$C$102*H83*($C$100-$C$101)))) -> 6125443.2 | J83: =IF(D83=0,J82*(1+H13),MIN(G83,I83)) -> 6125443.2 | K83: =IF(D83=0,$C$95,$C$94) -> 3.8414868 | L83: =J83*K83 -> 23530809 | M83: =L83-J83*$C$97 -> 4833008.5 | N83: =IF(D83=0,"NOT compliant",IF($C$100-$C$102*H83*($C$100-$C$101)<=H46+0.05,"Compliant","NOT compliant")) -> Compliant
B84: Delay 2 years: conversion in 2029 | C84: 2026 | E84: Coal (actual) | F84: =C12 -> 5020000 | H84: 0 | J84: =C14 -> 5020000 | K84: ='Task 3_P&L'!C12 -> 3.8414868 | L84: =C18 -> 19284264 | M84: =L84-J84*$C$97 -> 3960807.7 | N84: Baseline
C85: 2027 | D85: =MAX(0,C85-2026-$O$68) -> 0 | E85: =IF(D85=0,"Coal, no ESG",IF(D85=1,"Converting","Biomass in service")) -> Coal, no ESG | F85: =IF(D85=0,"",IF(D85=1,J84*(1+$C$66),F84*(1+INDEX($C$66:$F$66,MIN(D85,4))))) | G85: =IF(D85=0,"",F85*INDEX($C$67:$F$67,MIN(D85,4))) | H85: =IF(D85=0,0,IF(D85=1,$C$103,1)) -> 0 | I85: =IF(D85=0,"",D45*1000/($C$99*($C$100-$C$102*H85*($C$100-$C$101)))) | J85: =IF(D85=0,J84*(1+D13),MIN(G85,I85)) -> 4518000 | K85: =IF(D85=0,$C$95,$C$94) -> 3.7697545 | L85: =J85*K85 -> 17031751 | M85: =L85-J85*$C$97 -> 3240640.1 | N85: =IF(D85=0,"NOT compliant",IF($C$100-$C$102*H85*($C$100-$C$101)<=D46+0.05,"Compliant","NOT compliant")) -> NOT compliant
C86: 2028 | D86: =MAX(0,C86-2026-$O$68) -> 0 | E86: =IF(D86=0,"Coal, no ESG",IF(D86=1,"Converting","Biomass in service")) -> Coal, no ESG | F86: =IF(D86=0,"",IF(D86=1,J85*(1+$C$66),F85*(1+INDEX($C$66:$F$66,MIN(D86,4))))) | G86: =IF(D86=0,"",F86*INDEX($C$67:$F$67,MIN(D86,4))) | H86: =IF(D86=0,0,IF(D86=1,$C$103,1)) -> 0 | I86: =IF(D86=0,"",E45*1000/($C$99*($C$100-$C$102*H86*($C$100-$C$101)))) | J86: =IF(D86=0,J85*(1+E13),MIN(G86,I86)) -> 3975840 | K86: =IF(D86=0,$C$95,$C$94) -> 3.7697545 | L86: =J86*K86 -> 14987941 | M86: =L86-J86*$C$97 -> 2851763.3 | N86: =IF(D86=0,"NOT compliant",IF($C$100-$C$102*H86*($C$100-$C$101)<=E46+0.05,"Compliant","NOT compliant")) -> NOT compliant
C87: 2029 | D87: =MAX(0,C87-2026-$O$68) -> 1 | E87: =IF(D87=0,"Coal, no ESG",IF(D87=1,"Converting","Biomass in service")) -> Converting | F87: =IF(D87=0,"",IF(D87=1,J86*(1+$C$66),F86*(1+INDEX($C$66:$F$66,MIN(D87,4))))) -> 4850524.8 | G87: =IF(D87=0,"",F87*INDEX($C$67:$F$67,MIN(D87,4))) -> 4452940.8 | H87: =IF(D87=0,0,IF(D87=1,$C$103,1)) -> 0.75342466 | I87: =IF(D87=0,"",F45*1000/($C$99*($C$100-$C$102*H87*($C$100-$C$101)))) -> 5888757.6 | J87: =IF(D87=0,J86*(1+F13),MIN(G87,I87)) -> 4452940.8 | K87: =IF(D87=0,$C$95,$C$94) -> 3.8414868 | L87: =J87*K87 -> 17105913 | M87: =L87-J87*$C$97 -> 3513394.8 | N87: =IF(D87=0,"NOT compliant",IF($C$100-$C$102*H87*($C$100-$C$101)<=F46+0.05,"Compliant","NOT compliant")) -> Compliant
C88: 2030 | D88: =MAX(0,C88-2026-$O$68) -> 2 | E88: =IF(D88=0,"Coal, no ESG",IF(D88=1,"Converting","Biomass in service")) -> Biomass in service | F88: =IF(D88=0,"",IF(D88=1,J87*(1+$C$66),F87*(1+INDEX($C$66:$F$66,MIN(D88,4))))) -> 6063156 | G88: =IF(D88=0,"",F88*INDEX($C$67:$F$67,MIN(D88,4))) -> 5481093 | H88: =IF(D88=0,0,IF(D88=1,$C$103,1)) -> 1 | I88: =IF(D88=0,"",G45*1000/($C$99*($C$100-$C$102*H88*($C$100-$C$101)))) -> 7656804 | J88: =IF(D88=0,J87*(1+G13),MIN(G88,I88)) -> 5481093 | K88: =IF(D88=0,$C$95,$C$94) -> 3.8414868 | L88: =J88*K88 -> 21055547 | M88: =L88-J88*$C$97 -> 4324612.6 | N88: =IF(D88=0,"NOT compliant",IF($C$100-$C$102*H88*($C$100-$C$101)<=G46+0.05,"Compliant","NOT compliant")) -> Compliant
C89: 2031 | D89: =MAX(0,C89-2026-$O$68) -> 3 | E89: =IF(D89=0,"Coal, no ESG",IF(D89=1,"Converting","Biomass in service")) -> Biomass in service | F89: =IF(D89=0,"",IF(D89=1,J88*(1+$C$66),F88*(1+INDEX($C$66:$F$66,MIN(D89,4))))) -> 7760839.7 | G89: =IF(D89=0,"",F89*INDEX($C$67:$F$67,MIN(D89,4))) -> 6851366.3 | H89: =IF(D89=0,0,IF(D89=1,$C$103,1)) -> 1 | I89: =IF(D89=0,"",H45*1000/($C$99*($C$100-$C$102*H89*($C$100-$C$101)))) -> 6125443.2 | J89: =IF(D89=0,J88*(1+H13),MIN(G89,I89)) -> 6125443.2 | K89: =IF(D89=0,$C$95,$C$94) -> 3.8414868 | L89: =J89*K89 -> 23530809 | M89: =L89-J89*$C$97 -> 4833008.5 | N89: =IF(D89=0,"NOT compliant",IF($C$100-$C$102*H89*($C$100-$C$101)<=H46+0.05,"Compliant","NOT compliant")) -> Compliant
B90: Check: no-delay block equals Task 2 realized sales | C90: =IF(ABS(SUM(J73:J77)-SUM(D12:H12))<5,"OK","CHECK") -> OK
B92: Inputs and their basis
B93: Parameter | C93: Value | D93: Unit | E93: Basis / source
B94: EXW price, ESG pathway (incl. ESG/traceability premium) | C94: ='Sales Forecast & Case 2A KPI'!B43 -> 3.8414868 | D94: USD/pc | E94: Template row 43 (EXW Price G6:G10, 2026 SKU mix).
B95: EXW price, Traditional (no ESG premium) | C95: =SUMPRODUCT('EXW Price'!E6:E10,'EXW Price'!H6:H10)/SUM('EXW Price'!H6:H10) -> 3.7697545 | D95: USD/pc | E95: EXW Price E6:E10 = base EXW before the 1.5–2.5% ESG/traceability premium (F6:F10), same SKU mix. A coal-based supplier cannot claim the premium.
B96: ESG premium in the weighted price | C96: =$C$94/$C$95-1 -> 0.019028389 | D96: % | E96: Formula.
B97: Base COGS per piece (both pathways) | C97: ='Sales Forecast & Case 2A KPI'!B45 -> 3.0524813 | D97: USD/pc | E97: Template row 45; ESG costs are added only on the ESG pathway (Task 3).
B98: Traditional order change 2030–2031 | C98: ='Sales Forecast & Case 2A KPI'!B12 -> -0.15 | D98: % a year | E98: Held at the 2029 rate (Sales Forecast B12, D12 'accelerated order loss as requirements tighten'); the buyer gate keeps tightening to the 2031 full-roadmap gate (Emission Target G11, H11).
B99: Heat intensity | C99: ='Task 1_ESG Roadmap'!$C$111 -> 0.059760956 | D99: GJ/pc | E99: Task 1 (held at the 2026 level).
B100: Emission factor: coal | C100: ='Task 1_ESG Roadmap'!$C$112 -> 94.6 | D100: kgCO2e/GJ | E100: Task 1.
B101: Emission factor: biomass blend | C101: ='Task 1_ESG Roadmap'!$C$116 -> 9.1 | D101: kgCO2e/GJ | E101: Task 1.
B102: Design biomass mix used for carbon-allowed capacity | C102: ='Carbon-Allowed Capacity'!$C$21 -> 0.78 | D102: % of heat | E102: Carbon-Allowed Capacity (case target mix ~78%), as in Task 2.
B103: Share of the conversion year on biomass | C103: ='Task 1_ESG Roadmap'!$D$61 -> 0.75342466 | D103: % of year | E103: Task 1: biomass from 1 April of the conversion year.
B105: Assumptions and how conflicts or missing data are resolved
B106: Issue | C106: Assumption adopted | J106: Basis
B107: Traditional orders 2030–2031 | C107: Erosion held at the 2029 rate (−15% a year): not accelerated and not reversed. | J107: Sales Forecast B12, D12; Emission Target H10:H11; Table 03 2030–2031 rule (no mechanical extension of growth).
...

Sheet Task 5_Phasing Decision
B1: TASK 5 - RECOMMENDED INVESTMENT PHASING
B2: Requirement 5: the phasing that best balances Growth, Profitability, Cash Flow, ESG Compliance and Execution Risk. Four front-loaded options run through one engine with the rules of Tasks 1-4: two ways to run the plant in 2030-2031 (A, A+) and two ways to replace part or all of the A+ biomass step-up with carbon credits (A+C, A+H). They are ranked on five criteria and nine sub-criteria with objective CRITIC weights and TOPSIS (cross-checked by VIKOR and SAW), and the leader is stress-tested against the risk register.
B4: RECOMMENDED PHASING | C4: TOP-SCORED OPTION | E4: ="REVENUE 2027-2031 · "&$C$5 -> REVENUE 2027-2031 · A+H | G4: ="NET PROFIT 2027-2031 · "&$C$5 -> NET PROFIT 2027-2031 · A+H | J4: LOWEST NPM, ALL SHOCKS · A+H | L4: ="FREE CASH FLOW · "&$C$5 -> FREE CASH FLOW · A+H | N4: ="BUYER CAPS MET, NET · "&$C$5 -> BUYER CAPS MET, NET · A+H
B5: Front-load 2027 | C5: =C101 -> A+H | E5: {=INDEX($C$41:$F$41,MATCH($C$5,$C$39:$F$39,0))} -> 1.4787848e+08 | G5: {=INDEX($C$44:$F$44,MATCH($C$5,$C$39:$F$39,0))} -> 13610613 | J5: =MIN(C249:G249) -> 0.053514565 | L5: {=INDEX($C$47:$F$47,MATCH($C$5,$C$39:$F$39,0))} -> 11426824 | N5: {=INDEX($C$56:$F$56,MATCH($C$5,$C$39:$F$39,0))&" / 5 years"} -> 5 / 5 years
B6: ="Tranche 1 = "&TEXT('Task 1_ESG Roadmap'!C89/'Task 1_ESG Roadmap'!$C$107,"0%")&" of CAPEX, in service 1 Apr 2027; Tranche 2 in 2028" -> Tranche 1 = 95% of CAPEX, in service 1 Apr 2027; Tranche 2 in 2028 | C6: ="TOPSIS CC "&TEXT(MAX(C98:F98),"0.0000")&" (CRITIC weights)" -> TOPSIS CC 0.5750 (CRITIC weights) | E6: {="+"&TEXT((INDEX($C$41:$F$41,MATCH($C$5,$C$39:$F$39,0))-C41)/1000000,"0.0")&"M vs Option A"} -> +13.5M vs Option A | G6: {="+"&TEXT((INDEX($C$44:$F$44,MATCH($C$5,$C$39:$F$39,0))-C44)/1000000,"0.00")&"M vs Option A"} -> +1.36M vs Option A | J6: S1-S6 combined; every floor still met | L6: 2027-2031; no new debt | N6: {="Net of counted credits; in-boundary 2031 cut "&TEXT(INDEX($C$51:$F$51,MATCH($C$5,$C$39:$F$39,0)),"0.0%")} -> Net of counted credits; in-boundary 2031 cut 60.1%
B8: Why the CAPEX envelope cannot be spread evenly: the minimum viable biomass bundle
B9: Item group (Task 1 roadmap) | C9: Cost incl. contingency (USD) | D9: % of envelope | E9: Needed before first firing? | F9: Basis | J9: Test: spread the envelope evenly (20% a year)?
B10: Firing core: boiler retrofit, feeding, storage, ash handling, filters, fire safety, civil/electrical, engineering | C10: ='Task 1_ESG Roadmap'!E10+'Task 1_ESG Roadmap'!E11+'Task 1_ESG Roadmap'!E12+'Task 1_ESG Roadmap'!E13+'Task 1_ESG Roadmap'!E14+'Task 1_ESG Roadmap'!E17+'Task 1_ESG Roadmap'!E18+'Task 1_ESG Roadmap'!E19 -> 830500 | D10: =C10/'Task 1_ESG Roadmap'!$C$107 -> 0.88304094 | E10: Yes | F10: Critical/High items; each is a precondition of safe, legal biomass combustion and none fires biomass on its own. | J10: Share of the envelope available in 2027 | O10: 0.2 | P10: %
B11: Verification: stack & energy metering, ESG traceability set-up | C11: ='Task 1_ESG Roadmap'!E15+'Task 1_ESG Roadmap'!E20 -> 66000 | D11: =C11/'Task 1_ESG Roadmap'!$C$107 -> 0.070175439 | E11: Yes | F11: Only measured, verified reductions count (Emission Target B15:B19, F18); traceability avoids greenwashing claims (R06). | J11: 2027 budget minus the firing core | O11: =O10*'Task 1_ESG Roadmap'!$C$107-C10 -> -642400 | P11: USD
B12: Efficiency: water treatment & condensate recovery | C12: ='Task 1_ESG Roadmap'!E16 -> 44000 | D12: =C12/'Task 1_ESG Roadmap'!$C$107 -> 0.046783626 | E12: No | F12: The only item that can move without delaying conversion (Task 1 tranche T2, 2028). | J12: 2027 CO2e if the plant stays on coal at the Task 2 volume | O12: ='Task 1_ESG Roadmap'!D55*'Task 1_ESG Roadmap'!$C$112/1000 -> 31785.6 | P12: tCO2e
B13: Total = TOTAL PROJECT CAPEX | C13: =SUM(C10:C12) -> 940500 | D13: =C13/'Task 1_ESG Roadmap'!$C$107 -> 1 | E13: =IF(ABS(C13-'Task 1_ESG Roadmap'!$C$107)<1,"OK","CHECK") -> OK | F13: Scope unchanged (Table 03 CAPEX envelope). | J13: 2027 buyer cap | O13: ='Emission Target'!D7 -> 24123 | P13: tCO2e
J14: ="The firing core alone is "&TEXT(C10/'Task 1_ESG Roadmap'!$C$107,"0.0%")&" of the envelope and must be in service before the 2027 cap applies. An even 20% a year schedule leaves TEXIN on coal in 2027 at "&TEXT(O12,"#,##0")&" t vs a cap of "&TEXT(O13,"#,##0")&" t, so it is not a compliant option. The real choice is when the core goes in (2027, 2028 or 2029) and how hard it is run." -> The firing core alone is 88.3% of the envelope and must be in service before the 2027 cap applies. An even 20% a year schedule leaves TEXIN on coal in 2027 at 31,786 t vs a cap of 24,123 t, so it is not a compliant option. The real choice is when the core goes in (2027, 2028 or 2029) and how hard it is run.
B16: Options compared: all four front-load the CAPEX (Tranche 1 in 2027) and differ only in how 2030-2031 is run
B17: Option | C17: T1 in service (year) | D17: T2 in service (year) | E17: Operating biomass mix | J17: Sales volume rule | N17: Status / source
B18: A. Front-loaded, design mix (Tasks 1-3) | C18: 2027 | D18: =C18+1 -> 2028 | E18: Task 1 mix: lowest 5% step keeping CO2e ≥5% below both caps (45%, 60%, 80%, 80%, 80%). | J18: Task 2: carbon-allowed capacity at the 78% design mix binds in 2030-2031. | N18: Base case of Tasks 1-3.
B19: A+. Front-loaded, biomass step-up 2030-2031 | C19: 2027 | D19: =C19+1 -> 2028 | E19: As A to 2029; from 2030 the lowest 5% step keeping CO2e ≥5% below both caps at the held volume. | J19: MIN(Task 2 demand after the ESG gate, boiler limit = 2029 peak heat): holds the 2029 output. | N19: Growth lever flagged in Task 2 and Carbon-Allowed Capacity.
B20: A+C. Front-loaded, credits instead of step-up | C20: 2027 | D20: =C20+1 -> 2028 | E20: As A in every year (80% from 2029); the gap between its CO2e and the A+ path is covered by carbon credits. | J20: Same as A+: holds the 2029 output. | N20: Team option 1: credits replace 100% of the A+ step-up (inputs below).
B21: A+H. Front-loaded, half step-up, half credits | C21: 2027 | D21: =C21+1 -> 2028 | E21: A + 50% × (A+ − A) from 2030: 82.5% (2030), 85% (2031); credits cover the other half of the A+ reduction. | J21: Same as A+: holds the 2029 output. | N21: Team option 2: equal tonnes from biomass and from credits (inputs below).
B22: B, C, D. Delay 1 year, delay 2 years, even 20% a year | C22: 2028+ | D22: n/a | E22: Coal only in 2027 (and 2028 for C); D cannot fund the firing core in 2027. | J22: Task 4 delay engine; even phasing test above. | N22: Screened out: each breaches the 2027-2028 caps, so none can be recommended.
B24: Boiler heat limit used for A+, A+C, A+H (× 2026 heat) | C24: =MAX('Task 2_Conversion & Forecast'!C27:'Task 2_Conversion & Forecast'!H27) -> 1.72325 | D24: × | E24: Task 2 peak (2029); the retrofitted system is assumed able to supply up to that load; no boiler rating is given in the case (R08).
B25: Sales volume at the boiler limit | C25: =C24*'Sales Forecast & Case 2A KPI'!C21 -> 8650715 | D25: pcs | E25: Limit × 2026 volume (heat scales with volume, Task 1).
B27: Carbon credit inputs: a Task 5 estimate for the recommendation; the Task 1 emission boundary is unchanged
B28: Input | C28: Value | D28: Unit | E28: Basis / source
B29: Carbon credit price, high-quality avoidance credits (rated A-AAA) | C29: 14.8 | D29: USD/tCO2e | E29: 2026 market level: A-AAA rated credits average USD 14.80/t (MSCI and Allied Offsets data, via Regreener). Range for context: voluntary market average USD 6.34/t (Ecosystem Marketplace 2025, via Senken); removal credits (ARR) EUR 22-50/t (Senken, Sep 2026). Credits are bought in 2030-2031, so a 2026 price is a lower-bound estimate.
B30: Share of the A+ step-up replaced by credits: A+C | C30: 1 | D30: % | E30: Option 1: biomass stays at the A mix; credits = A+C in-boundary CO2e − A+ CO2e, each year.
B31: Share of the A+ step-up replaced by credits: A+H | C31: 0.5 | D31: % | E31: Option 2: half of the A+ step-up in biomass, half in credits; the two halves are equal in tonnes.
B32: Offset limit: credits counted toward the LSC cap, max share of the annual cap | C32: 0.3 | D32: % of cap | E32: Assumption by analogy with Vietnam's carbon market rule (Decree 119/2025/ND-CP amending Decree 06/2022): a covered facility may use carbon credits for at most 30% of its allocated allowances (VnEconomy, Feb 2026). The LSC cap plays the role of the allowance; credits above the limit are bought but do not count.
B33: Tax treatment of the credit cost | C33: Deductible | D33: CIT 20% | E33: Assumption: the credit purchase is expensed in the year it is bought and is deductible for CIT (Task 3 rate); paid in cash, no working-capital effect.
B34: Break-even credit price vs the A+ biomass step-up | C34: =(SUM(L190:P190)-SUM(L191:P191))/SUM(D156:H156) -> 21.195964 | D34: USD/tCO2e | E34: Credit price at which A+C and A+ have the same EBIT: (A+ ESG OPEX − A+C ESG OPEX, 2027-2031) ÷ credits bought by A+C. Above it, the biomass step-up is cheaper.
B35: Scope note | C35: Emission Target B17 and F17 fix the boundary at coal + biomass combustion, and Tasks 1-4 keep it. Credits do not change in-boundary CO2e. They are netted only in this Task 5 strategy view, as the "quantified offsets" Emission Target B20 lets teams propose, up to the offset limit above. The in-boundary 2031 reduction stays a scored ESG sub-criterion, so reliance on credits is penalised, and reporting the two figures separately avoids the R07 claim error.
B36: Sources (links) | C36: Senken: credit prices 2026 | F36: Regreener: VCM update | J36: S&P Global: EUA, 5 Oct 2026 | M36: VnEconomy: 30% offset rule
B38: Decision matrix 2027-2031: raw values, gates, CRITIC objective weights and TOPSIS ranking
B39: Metric | C39: A | D39: A+ | E39: A+C | F39: A+H | G39: Type | H39: Code | J39: How it is measured
B40: Growth
B41: Cumulative revenue (USD) | C41: =SUM(D126:H126) -> 1.3435959e+08 | D41: =SUM(D127:H127) -> 1.4787848e+08 | E41: =SUM(D128:H128) -> 1.4787848e+08 | F41: =SUM(D129:H129) -> 1.4787848e+08 | G41: Benefit | H41: C1 | J41: Growth. Sum 2027-2031.
B42: 2031 sales vs 2026 (×) | C42: =H119/C119 -> 1.2202078 | D42: =H120/C120 -> 1.72325 | E42: =H121/C121 -> 1.72325 | F42: =H122/C122 -> 1.72325 | G42: Benefit | H42: C2 | J42: Growth. End-of-roadmap scale.
B43: Profitability
B44: Cumulative net profit (USD) | C44: =SUM(D210:H210) -> 12255574 | D44: =SUM(D211:H211) -> 13593650 | E44: =SUM(D212:H212) -> 13627576 | F44: =SUM(D213:H213) -> 13610613 | G44: Benefit | H44: C3 | J44: Profitability. Sum 2027-2031, after the carbon credit cost.
B45: Lowest NPM in any year | C45: =MIN(L210:P210) -> 0.085829879 | D45: =MIN(L211:P211) -> 0.089860483 | E45: =MIN(L212:P212) -> 0.090541065 | F45: =MIN(L213:P213) -> 0.090200774 | G45: Benefit | H45: C4 | J45: Profitability. Weakest year.
B46: Cash flow
B47: Cumulative free cash flow (USD) | C47: =P224 -> 11584556 | D47: =P225 -> 11409862 | E47: =P226 -> 11443787 | F47: =P227 -> 11426824 | G47: Benefit | H47: C5 | J47: Cash flow. 2027-2031.
B48: Lowest annual free cash flow (USD) | C48: =MIN(D224:H224) -> 974255.27 | D48: =MIN(D225:H225) -> 974255.27 | E48: =MIN(D226:H226) -> 974255.27 | F48: =MIN(D227:H227) -> 974255.27 | G48: Benefit | H48: C6 | J48: Cash flow. Peak funding pressure (2027, Tranche 1 year); positive = self-funded every year.
B49: ESG compliance
B50: Carbon credit cost 2027-2031 (USD) | C50: =SUM(L168:P168) -> 0 | D50: =SUM(L169:P169) -> 0 | E50: =SUM(L170:P170) -> 98127.025 | F50: =SUM(L171:P171) -> 49063.512 | G50: Cost | H50: C7 | J50: ESG. Credits bought × price (inputs above); already inside net profit and FCF.
B51: CO2e reduction in 2031 vs 2026, in-boundary | C51: =1-P147/'Task 1_ESG Roadmap'!$C$73 -> 0.66205661 | D51: =1-P148/'Task 1_ESG Roadmap'!$C$73 -> 0.67848454 | E51: =1-P149/'Task 1_ESG Roadmap'!$C$73 -> 0.52273626 | F51: =1-P150/'Task 1_ESG Roadmap'!$C$73 -> 0.6006104 | G51: Benefit | H51: C8 | J51: ESG. Coal + biomass combustion only (Emission Target B17); target 64% (C11).
B52: Execution risk
B53: Peak biomass fuel vs case design tonnage (×) | C53: =MAX(D175:H175)/'Task 3_P&L'!$N$46 -> 1.3786 | D53: =MAX(D176:H176)/'Task 3_P&L'!$N$46 -> 1.550925 | E53: =MAX(D177:H177)/'Task 3_P&L'!$N$46 -> 1.3786 | F53: =MAX(D178:H178)/'Task 3_P&L'!$N$46 -> 1.4647625 | G53: Cost | H53: C9 | J53: Execution risk. Supply (R01), moisture (R02) and fouling (R04) exposure grows with tonnage; 1.00x = 18,125 t/yr (ESG_CAPEX OPEX E35 + E36).
B54: Gates (all must be met)
B55: NPM constraint met every year | C55: =IF(COUNTIF(D217:H217,"PASS")=5,"Yes","No") -> Yes | D55: =IF(COUNTIF(D218:H218,"PASS")=5,"Yes","No") -> Yes | E55: =IF(COUNTIF(D219:H219,"PASS")=5,"Yes","No") -> Yes | F55: =IF(COUNTIF(D220:H220,"PASS")=5,"Yes","No") -> Yes | G55: Yes | J55: Table 03.
B56: Years within both caps, net of counted credits (of 5) | C56: =COUNTIF(D161:H161,"Compliant") -> 5 | D56: =COUNTIF(D162:H162,"Compliant") -> 5 | E56: =COUNTIF(D163:H163,"Compliant") -> 4 | F56: =COUNTIF(D164:H164,"Compliant") -> 5 | G56: 5 | J56: Annual buyer review (Emission Target B19); credits count up to the offset limit (B20 and input above).
B57: Peak share of the annual cap covered by credits | C57: =MAX(D154/D$112,E154/E$112,F154/F$112,G154/G$112,H154/H$112) -> 0 | D57: =MAX(D155/D$112,E155/E$112,F155/F$112,G155/G$112,H155/H$112) -> 0 | E57: =MAX(D156/D$112,E156/E$112,F156/F$112,G156/G$112,H156/H$112) -> 0.43263412 | F57: =MAX(D157/D$112,E157/E$112,F157/F$112,G157/G$112,H157/H$112) -> 0.21631706 | G57: ≤ limit | J57: Credits needed ÷ buyer cap, worst year; above the offset limit the excess does not count.
B58: Both buyer CO2e caps met every year | C58: =IF(C56=5,"Yes","No") -> Yes | D58: =IF(D56=5,"Yes","No") -> Yes | E58: =IF(E56=5,"Yes","No") -> No | F58: =IF(F56=5,"Yes","No") -> Yes | G58: Yes | J58: Emission Target (mandatory annual improvement).
B59: Full CAPEX envelope in service by 2031 | C59: =IF(ABS(SUM(L196:P196)-'Task 1_ESG Roadmap'!$C$107)<1,"Yes","No") -> Yes | D59: =IF(ABS(SUM(L197:P197)-'Task 1_ESG Roadmap'!$C$107)<1,"Yes","No") -> Yes | E59: =IF(ABS(SUM(L198:P198)-'Task 1_ESG Roadmap'!$C$107)<1,"Yes","No") -> Yes | F59: =IF(ABS(SUM(L199:P199)-'Task 1_ESG Roadmap'!$C$107)<1,"Yes","No") -> Yes | G59: Yes | J59: Table 03 (no scope reduction).
B60: Eligible (passes all gates) | C60: =IF(AND(C55="Yes",C58="Yes",C59="Yes"),"Yes","No") -> Yes | D60: =IF(AND(D55="Yes",D58="Yes",D59="Yes"),"Yes","No") -> Yes | E60: =IF(AND(E55="Yes",E58="Yes",E59="Yes"),"Yes","No") -> No | F60: =IF(AND(F55="Yes",F58="Yes",F59="Yes"),"Yes","No") -> Yes | G60: Yes | J60: Only eligible options can be recommended.
B62: Step 1. Normalised decision matrix R (4 options × 9 sub-criteria, min-max to 0-1) | J62: Benefit: (x − min) ÷ (max − min); cost: (max − x) ÷ (max − min). A sub-criterion identical for all options gets 1 (no information).
B63: Option | C63: C1 Revenue | D63: C2 2031 scale | E63: C3 Net profit | F63: C4 Lowest NPM | G63: C5 FCF | H63: C6 Lowest FCF | J63: C7 Credit cost | K63: C8 CO2e cut 2031 | L63: C9 Peak biomass | M63: Group
B64: Type | C64: Benefit | D64: Benefit | E64: Benefit | F64: Benefit | G64: Benefit | H64: Benefit | J64: Cost | K64: Benefit | L64: Cost | M64: C1-C2 Growth · C3-C4 Profitability · C5-C6 Cash flow · C7-C8 ESG · C9 Execution risk
B65: A | C65: =IF(MAX($C$41:$F$41)=MIN($C$41:$F$41),1,(C41-MIN($C$41:$F$41))/(MAX($C$41:$F$41)-MIN($C$41:$F$41))) -> 0 | D65: =IF(MAX($C$42:$F$42)=MIN($C$42:$F$42),1,(C42-MIN($C$42:$F$42))/(MAX($C$42:$F$42)-MIN($C$42:$F$42))) -> 0 | E65: =IF(MAX($C$44:$F$44)=MIN($C$44:$F$44),1,(C44-MIN($C$44:$F$44))/(MAX($C$44:$F$44)-MIN($C$44:$F$44))) -> 0 | F65: =IF(MAX($C$45:$F$45)=MIN($C$45:$F$45),1,(C45-MIN($C$45:$F$45))/(MAX($C$45:$F$45)-MIN($C$45:$F$45))) -> 0 | G65: =IF(MAX($C$47:$F$47)=MIN($C$47:$F$47),1,(C47-MIN($C$47:$F$47))/(MAX($C$47:$F$47)-MIN($C$47:$F$47))) -> 1 | H65: =IF(MAX($C$48:$F$48)=MIN($C$48:$F$48),1,(C48-MIN($C$48:$F$48))/(MAX($C$48:$F$48)-MIN($C$48:$F$48))) -> 1 | J65: =IF(MAX($C$50:$F$50)=MIN($C$50:$F$50),1,(MAX($C$50:$F$50)-C50)/(MAX($C$50:$F$50)-MIN($C$50:$F$50))) -> 1 | K65: =IF(MAX($C$51:$F$51)=MIN($C$51:$F$51),1,(C51-MIN($C$51:$F$51))/(MAX($C$51:$F$51)-MIN($C$51:$F$51))) -> 0.89452256 | L65: =IF(MAX($C$53:$F$53)=MIN($C$53:$F$53),1,(MAX($C$53:$F$53)-C53)/(MAX($C$53:$F$53)-MIN($C$53:$F$53))) -> 1
B66: A+ | C66: =IF(MAX($C$41:$F$41)=MIN($C$41:$F$41),1,(D41-MIN($C$41:$F$41))/(MAX($C$41:$F$41)-MIN($C$41:$F$41))) -> 1 | D66: =IF(MAX($C$42:$F$42)=MIN($C$42:$F$42),1,(D42-MIN($C$42:$F$42))/(MAX($C$42:$F$42)-MIN($C$42:$F$42))) -> 1 | E66: =IF(MAX($C$44:$F$44)=MIN($C$44:$F$44),1,(D44-MIN($C$44:$F$44))/(MAX($C$44:$F$44)-MIN($C$44:$F$44))) -> 0.97527317 | F66: =IF(MAX($C$45:$F$45)=MIN($C$45:$F$45),1,(D45-MIN($C$45:$F$45))/(MAX($C$45:$F$45)-MIN($C$45:$F$45))) -> 0.85553918 | G66: =IF(MAX($C$47:$F$47)=MIN($C$47:$F$47),1,(D47-MIN($C$47:$F$47))/(MAX($C$47:$F$47)-MIN($C$47:$F$47))) -> 0 | H66: =IF(MAX($C$48:$F$48)=MIN($C$48:$F$48),1,(D48-MIN($C$48:$F$48))/(MAX($C$48:$F$48)-MIN($C$48:$F$48))) -> 1 | J66: =IF(MAX($C$50:$F$50)=MIN($C$50:$F$50),1,(MAX($C$50:$F$50)-D50)/(MAX($C$50:$F$50)-MIN($C$50:$F$50))) -> 1 | K66: =IF(MAX($C$51:$F$51)=MIN($C$51:$F$51),1,(D51-MIN($C$51:$F$51))/(MAX($C$51:$F$51)-MIN($C$51:$F$51))) -> 1 | L66: =IF(MAX($C$53:$F$53)=MIN($C$53:$F$53),1,(MAX($C$53:$F$53)-D53)/(MAX($C$53:$F$53)-MIN($C$53:$F$53))) -> 0
B67: A+C | C67: =IF(MAX($C$41:$F$41)=MIN($C$41:$F$41),1,(E41-MIN($C$41:$F$41))/(MAX($C$41:$F$41)-MIN($C$41:$F$41))) -> 1 | D67: =IF(MAX($C$42:$F$42)=MIN($C$42:$F$42),1,(E42-MIN($C$42:$F$42))/(MAX($C$42:$F$42)-MIN($C$42:$F$42))) -> 1 | E67: =IF(MAX($C$44:$F$44)=MIN($C$44:$F$44),1,(E44-MIN($C$44:$F$44))/(MAX($C$44:$F$44)-MIN($C$44:$F$44))) -> 1 | F67: =IF(MAX($C$45:$F$45)=MIN($C$45:$F$45),1,(E45-MIN($C$45:$F$45))/(MAX($C$45:$F$45)-MIN($C$45:$F$45))) -> 1 | G67: =IF(MAX($C$47:$F$47)=MIN($C$47:$F$47),1,(E47-MIN($C$47:$F$47))/(MAX($C$47:$F$47)-MIN($C$47:$F$47))) -> 0.19419802 | H67: =IF(MAX($C$48:$F$48)=MIN($C$48:$F$48),1,(E48-MIN($C$48:$F$48))/(MAX($C$48:$F$48)-MIN($C$48:$F$48))) -> 1 | J67: =IF(MAX($C$50:$F$50)=MIN($C$50:$F$50),1,(MAX($C$50:$F$50)-E50)/(MAX($C$50:$F$50)-MIN($C$50:$F$50))) -> 0 | K67: =IF(MAX($C$51:$F$51)=MIN($C$51:$F$51),1,(E51-MIN($C$51:$F$51))/(MAX($C$51:$F$51)-MIN($C$51:$F$51))) -> 0 | L67: =IF(MAX($C$53:$F$53)=MIN($C$53:$F$53),1,(MAX($C$53:$F$53)-E53)/(MAX($C$53:$F$53)-MIN($C$53:$F$53))) -> 1
B68: A+H | C68: =IF(MAX($C$41:$F$41)=MIN($C$41:$F$41),1,(F41-MIN($C$41:$F$41))/(MAX($C$41:$F$41)-MIN($C$41:$F$41))) -> 1 | D68: =IF(MAX($C$42:$F$42)=MIN($C$42:$F$42),1,(F42-MIN($C$42:$F$42))/(MAX($C$42:$F$42)-MIN($C$42:$F$42))) -> 1 | E68: =IF(MAX($C$44:$F$44)=MIN($C$44:$F$44),1,(F44-MIN($C$44:$F$44))/(MAX($C$44:$F$44)-MIN($C$44:$F$44))) -> 0.98763659 | F68: =IF(MAX($C$45:$F$45)=MIN($C$45:$F$45),1,(F45-MIN($C$45:$F$45))/(MAX($C$45:$F$45)-MIN($C$45:$F$45))) -> 0.92776959 | G68: =IF(MAX($C$47:$F$47)=MIN($C$47:$F$47),1,(F47-MIN($C$47:$F$47))/(MAX($C$47:$F$47)-MIN($C$47:$F$47))) -> 0.097099009 | H68: =IF(MAX($C$48:$F$48)=MIN($C$48:$F$48),1,(F48-MIN($C$48:$F$48))/(MAX($C$48:$F$48)-MIN($C$48:$F$48))) -> 1 | J68: =IF(MAX($C$50:$F$50)=MIN($C$50:$F$50),1,(MAX($C$50:$F$50)-F50)/(MAX($C$50:$F$50)-MIN($C$50:$F$50))) -> 0.5 | K68: =IF(MAX($C$51:$F$51)=MIN($C$51:$F$51),1,(F51-MIN($C$51:$F$51))/(MAX($C$51:$F$51)-MIN($C$51:$F$51))) -> 0.5 | L68: =IF(MAX($C$53:$F$53)=MIN($C$53:$F$53),1,(MAX($C$53:$F$53)-F53)/(MAX($C$53:$F$53)-MIN($C$53:$F$53))) -> 0.5
B70: Step 2. CRITIC: correlation between sub-criteria r_jk (9 × 9, Pearson on the columns of R) | J70: A sub-criterion with zero spread carries no information: its correlations are set to 1, so it adds no conflict.
B71: Criterion | C71: C1 Revenue | D71: C2 2031 scale | E71: C3 Net profit | F71: C4 Lowest NPM | G71: C5 FCF | H71: C6 Lowest FCF | J71: C7 Credit cost | K71: C8 CO2e cut 2031 | L71: C9 Peak biomass
B72: C1 Revenue | C72: =IF(OR($C$82=0,$C$82=0),1,CORREL($C$65:$C$68,$C$65:$C$68)) -> 1 | D72: =IF(OR($C$82=0,$D$82=0),1,CORREL($C$65:$C$68,$D$65:$D$68)) -> 1 | E72: =IF(OR($C$82=0,$E$82=0),1,CORREL($C$65:$C$68,$E$65:$E$68)) -> 0.99979113 | F72: =IF(OR($C$82=0,$F$82=0),1,CORREL($C$65:$C$68,$F$65:$F$68)) -> 0.99201504 | G72: =IF(OR($C$82=0,$G$82=0),1,CORREL($C$65:$C$68,$G$65:$G$68)) -> -0.98492761 | H72: =IF(OR($C$82=0,$H$82=0),1,CORREL($C$65:$C$68,$H$65:$H$68)) -> 1 | J72: =IF(OR($C$82=0,$J$82=0),1,CORREL($C$65:$C$68,$J$65:$J$68)) -> -0.52223297 | K72: =IF(OR($C$82=0,$K$82=0),1,CORREL($C$65:$C$68,$K$65:$K$68)) -> -0.43506366 | L72: =IF(OR($C$82=0,$L$82=0),1,CORREL($C$65:$C$68,$L$65:$L$68)) -> -0.52223297
B73: C2 2031 scale | C73: =IF(OR($D$82=0,$C$82=0),1,CORREL($D$65:$D$68,$C$65:$C$68)) -> 1 | D73: =IF(OR($D$82=0,$D$82=0),1,CORREL($D$65:$D$68,$D$65:$D$68)) -> 1 | E73: =IF(OR($D$82=0,$E$82=0),1,CORREL($D$65:$D$68,$E$65:$E$68)) -> 0.99979113 | F73: =IF(OR($D$82=0,$F$82=0),1,CORREL($D$65:$D$68,$F$65:$F$68)) -> 0.99201504 | G73: =IF(OR($D$82=0,$G$82=0),1,CORREL($D$65:$D$68,$G$65:$G$68)) -> -0.98492761 | H73: =IF(OR($D$82=0,$H$82=0),1,CORREL($D$65:$D$68,$H$65:$H$68)) -> 1 | J73: =IF(OR($D$82=0,$J$82=0),1,CORREL($D$65:$D$68,$J$65:$J$68)) -> -0.52223297 | K73: =IF(OR($D$82=0,$K$82=0),1,CORREL($D$65:$D$68,$K$65:$K$68)) -> -0.43506366 | L73: =IF(OR($D$82=0,$L$82=0),1,CORREL($D$65:$D$68,$L$65:$L$68)) -> -0.52223297
B74: C3 Net profit | C74: =IF(OR($E$82=0,$C$82=0),1,CORREL($E$65:$E$68,$C$65:$C$68)) -> 0.99979113 | D74: =IF(OR($E$82=0,$D$82=0),1,CORREL($E$65:$E$68,$D$65:$D$68)) -> 0.99979113 | E74: =IF(OR($E$82=0,$E$82=0),1,CORREL($E$65:$E$68,$E$65:$E$68)) -> 1 | F74: =IF(OR($E$82=0,$F$82=0),1,CORREL($E$65:$E$68,$F$65:$F$68)) -> 0.99438545 | G74: =IF(OR($E$82=0,$G$82=0),1,CORREL($E$65:$E$68,$G$65:$G$68)) -> -0.98118682 | H74: =IF(OR($E$82=0,$H$82=0),1,CORREL($E$65:$E$68,$H$65:$H$68)) -> 1 | J74: =IF(OR($E$82=0,$J$82=0),1,CORREL($E$65:$E$68,$J$65:$J$68)) -> -0.53955333 | K74: =IF(OR($E$82=0,$K$82=0),1,CORREL($E$65:$E$68,$K$65:$K$68)) -> -0.45337501 | L74: =IF(OR($E$82=0,$L$82=0),1,CORREL($E$65:$E$68,$L$65:$L$68)) -> -0.50469444
B75: C4 Lowest NPM | C75: =IF(OR($F$82=0,$C$82=0),1,CORREL($F$65:$F$68,$C$65:$C$68)) -> 0.99201504 | D75: =IF(OR($F$82=0,$D$82=0),1,CORREL($F$65:$F$68,$D$65:$D$68)) -> 0.99201504 | E75: =IF(OR($F$82=0,$E$82=0),1,CORREL($F$65:$F$68,$E$65:$E$68)) -> 0.99438545 | F75: =IF(OR($F$82=0,$F$82=0),1,CORREL($F$65:$F$68,$F$65:$F$68)) -> 1 | G75: =IF(OR($F$82=0,$G$82=0),1,CORREL($F$65:$F$68,$G$65:$G$68)) -> -0.95524848 | H75: =IF(OR($F$82=0,$H$82=0),1,CORREL($F$65:$F$68,$H$65:$H$68)) -> 1 | J75: =IF(OR($F$82=0,$J$82=0),1,CORREL($F$65:$F$68,$J$65:$J$68)) -> -0.62561811 | K75: =IF(OR($F$82=0,$K$82=0),1,CORREL($F$65:$F$68,$K$65:$K$68)) -> -0.54514774 | L75: =IF(OR($F$82=0,$L$82=0),1,CORREL($F$65:$F$68,$L$65:$L$68)) -> -0.41050781
B76: C5 FCF | C76: =IF(OR($G$82=0,$C$82=0),1,CORREL($G$65:$G$68,$C$65:$C$68)) -> -0.98492761 | D76: =IF(OR($G$82=0,$D$82=0),1,CORREL($G$65:$G$68,$D$65:$D$68)) -> -0.98492761 | E76: =IF(OR($G$82=0,$E$82=0),1,CORREL($G$65:$G$68,$E$65:$E$68)) -> -0.98118682 | F76: =IF(OR($G$82=0,$F$82=0),1,CORREL($G$65:$G$68,$F$65:$F$68)) -> -0.95524848 | G76: =IF(OR($G$82=0,$G$82=0),1,CORREL($G$65:$G$68,$G$65:$G$68)) -> 1 | H76: =IF(OR($G$82=0,$H$82=0),1,CORREL($G$65:$G$68,$H$65:$H$68)) -> 1 | J76: =IF(OR($G$82=0,$J$82=0),1,CORREL($G$65:$G$68,$J$65:$J$68)) -> 0.36685489 | K76: =IF(OR($G$82=0,$K$82=0),1,CORREL($G$65:$G$68,$K$65:$K$68)) -> 0.27276675 | L76: =IF(OR($G$82=0,$L$82=0),1,CORREL($G$65:$G$68,$L$65:$L$68)) -> 0.66186846
B77: C6 Lowest FCF | C77: =IF(OR($H$82=0,$C$82=0),1,CORREL($H$65:$H$68,$C$65:$C$68)) -> 1 | D77: =IF(OR($H$82=0,$D$82=0),1,CORREL($H$65:$H$68,$D$65:$D$68)) -> 1 | E77: =IF(OR($H$82=0,$E$82=0),1,CORREL($H$65:$H$68,$E$65:$E$68)) -> 1 | F77: =IF(OR($H$82=0,$F$82=0),1,CORREL($H$65:$H$68,$F$65:$F$68)) -> 1 | G77: =IF(OR($H$82=0,$G$82=0),1,CORREL($H$65:$H$68,$G$65:$G$68)) -> 1 | H77: =IF(OR($H$82=0,$H$82=0),1,CORREL($H$65:$H$68,$H$65:$H$68)) -> 1 | J77: =IF(OR($H$82=0,$J$82=0),1,CORREL($H$65:$H$68,$J$65:$J$68)) -> 1 | K77: =IF(OR($H$82=0,$K$82=0),1,CORREL($H$65:$H$68,$K$65:$K$68)) -> 1 | L77: =IF(OR($H$82=0,$L$82=0),1,CORREL($H$65:$H$68,$L$65:$L$68)) -> 1
B78: C7 Credit cost | C78: =IF(OR($J$82=0,$C$82=0),1,CORREL($J$65:$J$68,$C$65:$C$68)) -> -0.52223297 | D78: =IF(OR($J$82=0,$D$82=0),1,CORREL($J$65:$J$68,$D$65:$D$68)) -> -0.52223297 | E78: =IF(OR($J$82=0,$E$82=0),1,CORREL($J$65:$J$68,$E$65:$E$68)) -> -0.53955333 | F78: =IF(OR($J$82=0,$F$82=0),1,CORREL($J$65:$J$68,$F$65:$F$68)) -> -0.62561811 | G78: =IF(OR($J$82=0,$G$82=0),1,CORREL($J$65:$J$68,$G$65:$G$68)) -> 0.36685489 | H78: =IF(OR($J$82=0,$H$82=0),1,CORREL($J$65:$J$68,$H$65:$H$68)) -> 1 | J78: =IF(OR($J$82=0,$J$82=0),1,CORREL($J$65:$J$68,$J$65:$J$68)) -> 1 | K78: =IF(OR($J$82=0,$K$82=0),1,CORREL($J$65:$J$68,$K$65:$K$68)) -> 0.99506803 | L78: =IF(OR($J$82=0,$L$82=0),1,CORREL($J$65:$J$68,$L$65:$L$68)) -> -0.45454545
B79: C8 CO2e cut 2031 | C79: =IF(OR($K$82=0,$C$82=0),1,CORREL($K$65:$K$68,$C$65:$C$68)) -> -0.43506366 | D79: =IF(OR($K$82=0,$D$82=0),1,CORREL($K$65:$K$68,$D$65:$D$68)) -> -0.43506366 | E79: =IF(OR($K$82=0,$E$82=0),1,CORREL($K$65:$K$68,$E$65:$E$68)) -> -0.45337501 | F79: =IF(OR($K$82=0,$F$82=0),1,CORREL($K$65:$K$68,$F$65:$F$68)) -> -0.54514774 | G79: =IF(OR($K$82=0,$G$82=0),1,CORREL($K$65:$K$68,$G$65:$G$68)) -> 0.27276675 | H79: =IF(OR($K$82=0,$H$82=0),1,CORREL($K$65:$K$68,$H$65:$H$68)) -> 1 | J79: =IF(OR($K$82=0,$J$82=0),1,CORREL($K$65:$K$68,$J$65:$J$68)) -> 0.99506803 | K79: =IF(OR($K$82=0,$K$82=0),1,CORREL($K$65:$K$68,$K$65:$K$68)) -> 1 | L79: =IF(OR($K$82=0,$L$82=0),1,CORREL($K$65:$K$68,$L$65:$L$68)) -> -0.54065885
B80: C9 Peak biomass | C80: =IF(OR($L$82=0,$C$82=0),1,CORREL($L$65:$L$68,$C$65:$C$68)) -> -0.52223297 | D80: =IF(OR($L$82=0,$D$82=0),1,CORREL($L$65:$L$68,$D$65:$D$68)) -> -0.52223297 | E80: =IF(OR($L$82=0,$E$82=0),1,CORREL($L$65:$L$68,$E$65:$E$68)) -> -0.50469444 | F80: =IF(OR($L$82=0,$F$82=0),1,CORREL($L$65:$L$68,$F$65:$F$68)) -> -0.41050781 | G80: =IF(OR($L$82=0,$G$82=0),1,CORREL($L$65:$L$68,$G$65:$G$68)) -> 0.66186846 | H80: =IF(OR($L$82=0,$H$82=0),1,CORREL($L$65:$L$68,$H$65:$H$68)) -> 1 | J80: =IF(OR($L$82=0,$J$82=0),1,CORREL($L$65:$L$68,$J$65:$J$68)) -> -0.45454545 | K80: =IF(OR($L$82=0,$K$82=0),1,CORREL($L$65:$L$68,$K$65:$K$68)) -> -0.54065885 | L80: =IF(OR($L$82=0,$L$82=0),1,CORREL($L$65:$L$68,$L$65:$L$68)) -> 1
B81: Step 3. CRITIC weights: C_j = σ_j × Σ_k (1 − r_jk); w_j = C_j ÷ Σ C_j | J81: σ_j = standard deviation of column j of R (contrast); Σ(1 − r_jk) = conflict with the other sub-criteria.
B82: σ_j (contrast) | C82: =STDEV(C65:C68) -> 0.5 | D82: =STDEV(D65:D68) -> 0.5 | E82: =STDEV(E65:E68) -> 0.49392146 | F82: =STDEV(F65:F68) -> 0.46761871 | G82: =STDEV(G65:G68) -> 0.45835906 | H82: =STDEV(H65:H68) -> 0 | J82: =STDEV(J65:J68) -> 0.47871355 | K82: =STDEV(K65:K68) -> 0.45340785 | L82: =STDEV(L65:L68) -> 0.47871355 | M82: Largest weights go to the sub-criteria that separate the options most and agree least with the others.
B83: Σ_k (1 − r_jk) (conflict) | C83: =9-SUM(C72:H72,J72:L72) -> 6.472651 | D83: =9-SUM(C73:H73,J73:L73) -> 6.472651 | E83: =9-SUM(C74:H74,J74:L74) -> 6.4848419 | F83: =9-SUM(C75:H75,J75:L75) -> 6.5581066 | G83: =9-SUM(C76:H76,J76:L76) -> 9.6048004 | H83: =9-SUM(C77:H77,J77:L77) -> 0 | J83: =9-SUM(C78:H78,J78:L78) -> 8.3022599 | K83: =9-SUM(C79:H79,J79:L79) -> 8.1414742 | L83: =9-SUM(C80:H80,J80:L80) -> 9.293004
B84: C_j = σ_j × Σ (1 − r_jk) | C84: =C82*C83 -> 3.2363255 | D84: =D82*D83 -> 3.2363255 | E84: =E82*E83 -> 3.2030026 | F84: =F82*F83 -> 3.0666934 | G84: =G82*G83 -> 4.4024473 | H84: =H82*H83 -> 0 | J84: =J82*J83 -> 3.9744044 | K84: =K82*K83 -> 3.6914083 | L84: =L82*L83 -> 4.448687
B85: Weight w_j | C85: =C84/(SUM(C84:H84,J84:L84)) -> 0.11060846 | D85: =D84/(SUM(C84:H84,J84:L84)) -> 0.11060846 | E85: =E84/(SUM(C84:H84,J84:L84)) -> 0.10946958 | F85: =F84/(SUM(C84:H84,J84:L84)) -> 0.10481091 | G85: =G84/(SUM(C84:H84,J84:L84)) -> 0.15046321 | H85: =H84/(SUM(C84:H84,J84:L84)) -> 0 | J85: =J84/(SUM(C84:H84,J84:L84)) -> 0.13583391 | K85: =K84/(SUM(C84:H84,J84:L84)) -> 0.12616191 | L85: =L84/(SUM(C84:H84,J84:L84)) -> 0.15204355 | M85: Σ w_j | N85: =SUM(C85:H85,J85:L85) -> 1
B87: Step 4. Weighted normalised matrix V = R × w (4 × 9) and TOPSIS | J87: Ideal A+ = column max of V, anti-ideal A− = column min (R is already oriented, so higher is better everywhere).
B88: Option | C88: C1 Revenue | D88: C2 2031 scale | E88: C3 Net profit | F88: C4 Lowest NPM | G88: C5 FCF | H88: C6 Lowest FCF | J88: C7 Credit cost | K88: C8 CO2e cut 2031 | L88: C9 Peak biomass | M88: D+ (to ideal) | N88: D− (to anti-ideal) | O88: Closeness CC | P88: Rank (eligible)
B89: A | C89: =C65*C$85 -> 0 | D89: =D65*D$85 -> 0 | E89: =E65*E$85 -> 0 | F89: =F65*F$85 -> 0 | G89: =G65*G$85 -> 0.15046321 | H89: =H65*H$85 -> 0 | J89: =J65*J$85 -> 0.13583391 | K89: =K65*K$85 -> 0.11285467 | L89: =L65*L$85 -> 0.15204355 | M89: =SQRT(SUMXMY2(C89:H89,C$93:H$93)+SUMXMY2(J89:L89,J$93:L$93)) -> 0.21820739 | N89: =SQRT(SUMXMY2(C89:H89,C$94:H$94)+SUMXMY2(J89:L89,J$94:L$94)) -> 0.27738682 | O89: =N89/(M89+N89) -> 0.55970554 | P89: =IF(C$60="Yes",COUNTIF($C$105:$F$105,">"&C105)+1,"Not eligible") -> 3
B90: A+ | C90: =C66*C$85 -> 0.11060846 | D90: =D66*D$85 -> 0.11060846 | E90: =E66*E$85 -> 0.10676274 | F90: =F66*F$85 -> 0.089669844 | G90: =G66*G$85 -> 0 | H90: =H66*H$85 -> 0 | J90: =J66*J$85 -> 0.13583391 | K90: =K66*K$85 -> 0.12616191 | L90: =L66*L$85 -> 0 | M90: =SQRT(SUMXMY2(C90:H90,C$93:H$93)+SUMXMY2(J90:L90,J$93:L$93)) -> 0.21445978 | N90: =SQRT(SUMXMY2(C90:H90,C$94:H$94)+SUMXMY2(J90:L90,J$94:L$94)) -> 0.27977689 | O90: =N90/(M90+N90) -> 0.56607877 | P90: =IF(D$60="Yes",COUNTIF($C$105:$F$105,">"&D105)+1,"Not eligible") -> 2
B91: A+C | C91: =C67*C$85 -> 0.11060846 | D91: =D67*D$85 -> 0.11060846 | E91: =E67*E$85 -> 0.10946958 | F91: =F67*F$85 -> 0.10481091 | G91: =G67*G$85 -> 0.029219657 | H91: =H67*H$85 -> 0 | J91: =J67*J$85 -> 0 | K91: =K67*K$85 -> 0 | L91: =L67*L$85 -> 0.15204355 | M91: =SQRT(SUMXMY2(C91:H91,C$93:H$93)+SUMXMY2(J91:L91,J$93:L$93)) -> 0.22151225 | N91: =SQRT(SUMXMY2(C91:H91,C$94:H$94)+SUMXMY2(J91:L91,J$94:L$94)) -> 0.26722352 | O91: =N91/(M91+N91) -> 0.54676481 | P91: =IF(E$60="Yes",COUNTIF($C$105:$F$105,">"&E105)+1,"Not eligible") -> Not eligible
B92: A+H | C92: =C68*C$85 -> 0.11060846 | D92: =D68*D$85 -> 0.11060846 | E92: =E68*E$85 -> 0.10811616 | F92: =F68*F$85 -> 0.097240379 | G92: =G68*G$85 -> 0.014609829 | H92: =H68*H$85 -> 0 | J92: =J68*J$85 -> 0.067916956 | K92: =K68*K$85 -> 0.063080953 | L92: =L68*L$85 -> 0.076021776 | M92: =SQRT(SUMXMY2(C92:H92,C$93:H$93)+SUMXMY2(J92:L92,J$93:L$93)) -> 0.1813464 | N92: =SQRT(SUMXMY2(C92:H92,C$94:H$94)+SUMXMY2(J92:L92,J$94:L$94)) -> 0.24535268 | O92: =N92/(M92+N92) -> 0.57500166 | P92: =IF(F$60="Yes",COUNTIF($C$105:$F$105,">"&F105)+1,"Not eligible") -> 1
B93: Ideal A+ (max of each column) | C93: =MAX(C89:C92) -> 0.11060846 | D93: =MAX(D89:D92) -> 0.11060846 | E93: =MAX(E89:E92) -> 0.10946958 | F93: =MAX(F89:F92) -> 0.10481091 | G93: =MAX(G89:G92) -> 0.15046321 | H93: =MAX(H89:H92) -> 0 | J93: =MAX(J89:J92) -> 0.13583391 | K93: =MAX(K89:K92) -> 0.12616191 | L93: =MAX(L89:L92) -> 0.15204355
B94: Anti-ideal A− (min of each column) | C94: =MIN(C89:C92) -> 0 | D94: =MIN(D89:D92) -> 0 | E94: =MIN(E89:E92) -> 0 | F94: =MIN(F89:F92) -> 0 | G94: =MIN(G89:G92) -> 0 | H94: =MIN(H89:H92) -> 0 | J94: =MIN(J89:J92) -> 0 | K94: =MIN(K89:K92) -> 0 | L94: =MIN(L89:L92) -> 0
B96: Step 5. Ranking result and cross-check with two other methods (same CRITIC weights)
B97: Method | C97: A | D97: A+ | E97: A+C | F97: A+H | G97: Better | H97: Winner (eligible) | J97: Reading
B98: TOPSIS closeness CC (main method) | C98: =O89 -> 0.55970554 | D98: =O90 -> 0.56607877 | E98: =O91 -> 0.54676481 | F98: =O92 -> 0.57500166 | G98: Higher | H98: {=INDEX($C$39:$F$39,MATCH(MAX($C$105:$F$105),$C$105:$F$105,0))} -> A+H | J98: Main ranking: distance to the ideal and anti-ideal option on all nine weighted sub-criteria.
B99: VIKOR Q (v = 0.5) | C99: =0.5*(C103-MIN($C$103:$F$103))/(MAX($C$103:$F$103)-MIN($C$103:$F$103))+0.5*(C104-MIN($C$104:$F$104))/(MAX($C$104:$F$104)-MIN($C$104:$F$104)) -> 0.5 | D99: =0.5*(D103-MIN($C$103:$F$103))/(MAX($C$103:$F$103)-MIN($C$103:$F$103))+0.5*(D104-MIN($C$104:$F$104))/(MAX($C$104:$F$104)-MIN($C$104:$F$104)) -> 0.5 | E99: =0.5*(E103-MIN($C$103:$F$103))/(MAX($C$103:$F$103)-MIN($C$103:$F$103))+0.5*(E104-MIN($C$104:$F$104))/(MAX($C$104:$F$104)-MIN($C$104:$F$104)) -> 0.54918002 | F99: =0.5*(F103-MIN($C$103:$F$103))/(MAX($C$103:$F$103)-MIN($C$103:$F$103))+0.5*(F104-MIN($C$104:$F$104))/(MAX($C$104:$F$104)-MIN($C$104:$F$104)) -> 0.42702355 | G99: Lower | H99: {=INDEX($C$39:$F$39,MATCH(MIN($C$106:$F$106),$C$106:$F$106,0))} -> A+H | J99: Compromise ranking: penalises the single worst weighted gap (regret), so lopsided options lose.
B100: SAW (Σ w_j × r_ij) | C100: =SUMPRODUCT($C$85:$H$85,C65:H65)+SUMPRODUCT($J$85:$L$85,J65:L65) -> 0.55119535 | D100: =SUMPRODUCT($C$85:$H$85,C66:H66)+SUMPRODUCT($J$85:$L$85,J66:L66) -> 0.67964533 | E100: =SUMPRODUCT($C$85:$H$85,C67:H67)+SUMPRODUCT($J$85:$L$85,J67:L67) -> 0.61676063 | F100: =SUMPRODUCT($C$85:$H$85,C68:H68)+SUMPRODUCT($J$85:$L$85,J68:L68) -> 0.64820298 | G100: Higher | H100: {=INDEX($C$39:$F$39,MATCH(MAX($C$107:$F$107),$C$107:$F$107,0))} -> A+ | J100: Simple weighted sum: fully compensatory, a large gain on one sub-criterion can offset a zero elsewhere.
B101: Recommended option (highest TOPSIS CC among eligible options) | C101: =H98 -> A+H | J101: ="Methods agreeing with TOPSIS: "&(COUNTIF(H98:H100,H98)-1)&" of 2" -> Methods agreeing with TOPSIS: 1 of 2
B102: Helpers: VIKOR S and R, and eligible-only values used to pick the winners
B103: VIKOR S = Σ w_j (1 − r_ij) | C103: =SUMPRODUCT($C$85:$H$85,1-C65:H65)+SUMPRODUCT($J$85:$L$85,1-J65:L65) -> 0.44880465 | D103: =SUMPRODUCT($C$85:$H$85,1-C66:H66)+SUMPRODUCT($J$85:$L$85,1-J66:L66) -> 0.32035467 | E103: =SUMPRODUCT($C$85:$H$85,1-C67:H67)+SUMPRODUCT($J$85:$L$85,1-J67:L67) -> 0.38323937 | F103: =SUMPRODUCT($C$85:$H$85,1-C68:H68)+SUMPRODUCT($J$85:$L$85,1-J68:L68) -> 0.35179702
B104: VIKOR R = max w_j (1 − r_ij) | C104: =MAX(C$85*(1-C65),D$85*(1-D65),E$85*(1-E65),F$85*(1-F65),G$85*(1-G65),H$85*(1-H65),J$85*(1-J65),K$85*(1-K65),L$85*(1-L65)) -> 0.11060846 | D104: =MAX(C$85*(1-C66),D$85*(1-D66),E$85*(1-E66),F$85*(1-F66),G$85*(1-G66),H$85*(1-H66),J$85*(1-J66),K$85*(1-K66),L$85*(1-L66)) -> 0.15204355 | E104: =MAX(C$85*(1-C67),D$85*(1-D67),E$85*(1-E67),F$85*(1-F67),G$85*(1-G67),H$85*(1-H67),J$85*(1-J67),K$85*(1-K67),L$85*(1-L67)) -> 0.13583391 | F104: =MAX(C$85*(1-C68),D$85*(1-D68),E$85*(1-E68),F$85*(1-F68),G$85*(1-G68),H$85*(1-H68),J$85*(1-J68),K$85*(1-K68),L$85*(1-L68)) -> 0.13585338
B105: TOPSIS CC, eligible only (−1 if not) | C105: =IF(C$60="Yes",C98,-1) -> 0.55970554 | D105: =IF(D$60="Yes",D98,-1) -> 0.56607877 | E105: =IF(E$60="Yes",E98,-1) -> -1 | F105: =IF(F$60="Yes",F98,-1) -> 0.57500166
B106: VIKOR Q, eligible only (9 if not) | C106: =IF(C$60="Yes",C99,9) -> 0.5 | D106: =IF(D$60="Yes",D99,9) -> 0.5 | E106: =IF(E$60="Yes",E99,9) -> 9 | F106: =IF(F$60="Yes",F99,9) -> 0.42702355
B107: SAW, eligible only (−1 if not) | C107: =IF(C$60="Yes",C100,-1) -> 0.55119535 | D107: =IF(D$60="Yes",D100,-1) -> 0.67964533 | E107: =IF(E$60="Yes",E100,-1) -> -1 | F107: =IF(F$60="Yes",F100,-1) -> 0.64820298
B109: Option engine: year-by-year results, one small table per metric (rows = options)
B110: Year parameters | C110: 2026 | D110: 2027 | E110: 2028 | F110: 2029 | G110: 2030 | H110: 2031
B111: Calendar year | C111: 2026 | D111: 2027 | E111: 2028 | F111: 2029 | G111: 2030 | H111: 2031
...

Sheet ESG_CAPEX OPEX
A1: ESG FUEL CONVERSION: CAPEX & OPEX MODEL
A2: Case purpose: design a full biomass-capable thermal-energy system for TEXIN. All monetary values are case-study assumptions unless a source is explicitly cited.
A4: A. Core operating assumptions
A5: Assumption | B5: Value | C5: Unit | D5: Case note/source
A6: Annual useful heat demand | B6: 300000 | C6: GJ/year | D6: Case assumption, sized for textile dyeing/finishing steam demand
A7: Coal NCV | B7: 25 | C7: GJ/t | D7: From existing workbook: CO2 Emission Calculation
A8: Rice husk pellet NCV | B8: 16 | C8: GJ/t | D8: From existing workbook: CO2 Emission Calculation
